Workbook

Sheet Home
B2: Food Delivery Analytics – Dashboard Hub
B3: 1,200 orders · 350 customers · 12 restaurants · 12 cities · 1-Jan-2025 to 4-Feb-2026. Every number is a live formula on the Data sheet.
B5: TOTAL ORDERS | D5: NET REVENUE | F5: DELIVERY SUCCESS | H5: CANCELLATION RATE | J5: AVG DELIVERY TIME | L5: AVG CUSTOMER RATING
B6: =COUNTA(d_ID) -> 1200 | D6: =SUMIFS(d_Net,d_Status,"Delivered") -> 699950 | F6: =IFERROR(COUNTIFS(d_Status,"Delivered")/COUNTA(d_ID),0) -> 0.65916667 | H6: =IFERROR(COUNTIFS(d_Status,"Cancelled")/COUNTA(d_ID),0) -> 0.16833333 | J6: =IFERROR(AVERAGEIFS(d_Time,d_Status,"Delivered"),0) -> 41.530973 | L6: =AVERAGE(d_CRating) -> 4.0183333
B7: All statuses | D7: Delivered orders | F7: Delivered ÷ all | H7: Cancelled ÷ all | J7: Delivered orders | L7: Out of 5
B10: Dashboards (click to open)
B12: 1. Order Analytics | F12: Volume, status mix, cuisine, payment, city
B14: 2. Restaurant Performance | F14: Revenue, ratings, speed, cancel rate per restaurant
B16: 3. Customer Analytics | F16: Repeat rate, age, gender, top customers
B18: 4. Delivery Partner Analytics | F18: Delivery fleet by city & distance (no partner ID in data)
B20: 5. Delivery Time | F20: Time bands, SLA on-time %, city & distance
B22: 6. Cancellation Analysis | F22: Rates by city, restaurant, payment, cuisine
B24: 7. Rating & Review | F24: Rating distribution, by restaurant / cuisine / city
B26: 8. Revenue Dashboard | F26: Gross, discounts, net by month, city, cuisine
B28: 9. Explorer | F28: Pick any grouping + metric; chart rebuilds instantly
B31: Definitions & assumptions
B32: • Interactive: each dashboard has yellow dropdown filters (Year, City, Cuisine, Payment, Order type) in row 4 – every KPI, chart and table recalculates. Set to All to clear. Home KPIs are always unfiltered.
B33: • Net revenue / gross revenue / discounts count Delivered orders only; Pending and Cancelled orders are reported separately.
B34: • Delivery-time metrics use Delivered orders only. SLA target is an input on the Delivery Time sheet (assumed 45 min).
B35: • Cancel rate = Cancelled ÷ all orders in the group. Lost value = Gross_Amount of cancelled orders.
B36: • Delivery Partner Analytics: the source file has no partner/rider column, so Order_Type = Delivery is used as the fleet.
B37: • Rating & Review: the source has star ratings only (no review text). Restaurant_Rating varies per order, so averages are used.
B38: • Blue font = editable inputs (month starts, band limits, SLA). Formulas read named ranges d_* on Data rows 2–5000, so appended rows are picked up.
B39: • Customers helper sheet lists customer IDs; add new IDs there if new customers are appended. Feb-26 is a partial month.

Sheet Order Analytics
B2: Order Analytics
B3: Order volume, status mix, order type, cuisines, payment methods and city demand. Source: Data sheet (1,200 orders, 1-Jan-2025 to 4-Feb-2026). ▸ Use the yellow filters in row 4 – every KPI, chart and table updates. | L3: ← Back to Home
B4: Year: | C4: All | D4: City: | E4: All | F4: Cuisine: | G4: All | H4: Payment: | I4: All | J4: Order type: | K4: All | L4: ="Orders in view: "&TEXT(COUNTIFS(d_ID,"<>",d_Year,$P$4,d_City,$Q$4,d_Cuisine,$R$4,d_Pay,$S$4,d_Type,$T$4),"#,##0") -> Orders in view: 1,200 | P4: =IF(C4="All",">0",C4) -> >0 | Q4: =IF(E4="All","*",E4) -> * | R4: =IF(G4="All","*",G4) -> * | S4: =IF(I4="All","*",I4) -> * | T4: =IF(K4="All","*",K4) -> *
B5: TOTAL ORDERS | D5: DELIVERED | F5: PENDING | H5: CANCELLED | J5: AVG ORDER VALUE | L5: DELIVERY SHARE
B6: =COUNTIFS(d_ID,"<>",d_Year,$P$4,d_City,$Q$4,d_Cuisine,$R$4,d_Pay,$S$4,d_Type,$T$4) -> 1200 | D6: =COUNTIFS(d_Status,"Delivered",d_Year,$P$4,d_City,$Q$4,d_Cuisine,$R$4,d_Pay,$S$4,d_Type,$T$4) -> 791 | F6: =COUNTIFS(d_Status,"Pending",d_Year,$P$4,d_City,$Q$4,d_Cuisine,$R$4,d_Pay,$S$4,d_Type,$T$4) -> 207 | H6: =COUNTIFS(d_Status,"Cancelled",d_Year,$P$4,d_City,$Q$4,d_Cuisine,$R$4,d_Pay,$S$4,d_Type,$T$4) -> 202 | J6: =AVERAGEIFS(d_OV,d_ID,"<>",d_Year,$P$4,d_City,$Q$4,d_Cuisine,$R$4,d_Pay,$S$4,d_Type,$T$4) -> 931.2875 | L6: =IFERROR(COUNTIFS(d_Type,"Delivery",d_Year,$P$4,d_City,$Q$4,d_Cuisine,$R$4,d_Pay,$S$4,d_Type,$T$4)/COUNTIFS(d_ID,"<>",d_Year,$P$4,d_City,$Q$4,d_Cuisine,$R$4,d_Pay,$S$4,d_Type,$T$4),0) -> 0.73416667
B7: All statuses | D7: Completed orders | F7: Not yet completed | H7: Cancelled orders | J7: Food value, all orders | L7: Delivery vs pickup
B57: Supporting data (feeds the charts above)
B59: Monthly order trend
B60: Month | C60: Month start | D60: Orders | E60: Delivered | F60: Pending | G60: Cancelled | H60: Avg order value
B61: =TEXT(C61,"mmm-yy") -> Jan-25 | C61: 45658 | D61: =COUNTIFS(d_Date,">="&$C61,d_Date,"<"&EDATE($C61,1),d_Year,$P$4,d_City,$Q$4,d_Cuisine,$R$4,d_Pay,$S$4,d_Type,$T$4) -> 93 | E61: =COUNTIFS(d_Date,">="&$C61,d_Date,"<"&EDATE($C61,1),d_Status,"Delivered",d_Year,$P$4,d_City,$Q$4,d_Cuisine,$R$4,d_Pay,$S$4,d_Type,$T$4) -> 66 | F61: =COUNTIFS(d_Date,">="&$C61,d_Date,"<"&EDATE($C61,1),d_Status,"Pending",d_Year,$P$4,d_City,$Q$4,d_Cuisine,$R$4,d_Pay,$S$4,d_Type,$T$4) -> 12 | G61: =COUNTIFS(d_Date,">="&$C61,d_Date,"<"&EDATE($C61,1),d_Status,"Cancelled",d_Year,$P$4,d_City,$Q$4,d_Cuisine,$R$4,d_Pay,$S$4,d_Type,$T$4) -> 15 | H61: =IFERROR(AVERAGEIFS(d_OV,d_Date,">="&$C61,d_Date,"<"&EDATE($C61,1),d_Year,$P$4,d_City,$Q$4,d_Cuisine,$R$4,d_Pay,$S$4,d_Type,$T$4),0) -> 919.65591
B62: =TEXT(C62,"mmm-yy") -> Feb-25 | C62: 45689 | D62: =COUNTIFS(d_Date,">="&$C62,d_Date,"<"&EDATE($C62,1),d_Year,$P$4,d_City,$Q$4,d_Cuisine,$R$4,d_Pay,$S$4,d_Type,$T$4) -> 84 | E62: =COUNTIFS(d_Date,">="&$C62,d_Date,"<"&EDATE($C62,1),d_Status,"Delivered",d_Year,$P$4,d_City,$Q$4,d_Cuisine,$R$4,d_Pay,$S$4,d_Type,$T$4) -> 48 | F62: =COUNTIFS(d_Date,">="&$C62,d_Date,"<"&EDATE($C62,1),d_Status,"Pending",d_Year,$P$4,d_City,$Q$4,d_Cuisine,$R$4,d_Pay,$S$4,d_Type,$T$4) -> 21 | G62: =COUNTIFS(d_Date,">="&$C62,d_Date,"<"&EDATE($C62,1),d_Status,"Cancelled",d_Year,$P$4,d_City,$Q$4,d_Cuisine,$R$4,d_Pay,$S$4,d_Type,$T$4) -> 15 | H62: =IFERROR(AVERAGEIFS(d_OV,d_Date,">="&$C62,d_Date,"<"&EDATE($C62,1),d_Year,$P$4,d_City,$Q$4,d_Cuisine,$R$4,d_Pay,$S$4,d_Type,$T$4),0) -> 942.97619
B63: =TEXT(C63,"mmm-yy") -> Mar-25 | C63: 45717 | D63: =COUNTIFS(d_Date,">="&$C63,d_Date,"<"&EDATE($C63,1),d_Year,$P$4,d_City,$Q$4,d_Cuisine,$R$4,d_Pay,$S$4,d_Type,$T$4) -> 93 | E63: =COUNTIFS(d_Date,">="&$C63,d_Date,"<"&EDATE($C63,1),d_Status,"Delivered",d_Year,$P$4,d_City,$Q$4,d_Cuisine,$R$4,d_Pay,$S$4,d_Type,$T$4) -> 55 | F63: =COUNTIFS(d_Date,">="&$C63,d_Date,"<"&EDATE($C63,1),d_Status,"Pending",d_Year,$P$4,d_City,$Q$4,d_Cuisine,$R$4,d_Pay,$S$4,d_Type,$T$4) -> 19 | G63: =COUNTIFS(d_Date,">="&$C63,d_Date,"<"&EDATE($C63,1),d_Status,"Cancelled",d_Year,$P$4,d_City,$Q$4,d_Cuisine,$R$4,d_Pay,$S$4,d_Type,$T$4) -> 19 | H63: =IFERROR(AVERAGEIFS(d_OV,d_Date,">="&$C63,d_Date,"<"&EDATE($C63,1),d_Year,$P$4,d_City,$Q$4,d_Cuisine,$R$4,d_Pay,$S$4,d_Type,$T$4),0) -> 969.89247
B64: =TEXT(C64,"mmm-yy") -> Apr-25 | C64: 45748 | D64: =COUNTIFS(d_Date,">="&$C64,d_Date,"<"&EDATE($C64,1),d_Year,$P$4,d_City,$Q$4,d_Cuisine,$R$4,d_Pay,$S$4,d_Type,$T$4) -> 90 | E64: =COUNTIFS(d_Date,">="&$C64,d_Date,"<"&EDATE($C64,1),d_Status,"Delivered",d_Year,$P$4,d_City,$Q$4,d_Cuisine,$R$4,d_Pay,$S$4,d_Type,$T$4) -> 61 | F64: =COUNTIFS(d_Date,">="&$C64,d_Date,"<"&EDATE($C64,1),d_Status,"Pending",d_Year,$P$4,d_City,$Q$4,d_Cuisine,$R$4,d_Pay,$S$4,d_Type,$T$4) -> 12 | G64: =COUNTIFS(d_Date,">="&$C64,d_Date,"<"&EDATE($C64,1),d_Status,"Cancelled",d_Year,$P$4,d_City,$Q$4,d_Cuisine,$R$4,d_Pay,$S$4,d_Type,$T$4) -> 17 | H64: =IFERROR(AVERAGEIFS(d_OV,d_Date,">="&$C64,d_Date,"<"&EDATE($C64,1),d_Year,$P$4,d_City,$Q$4,d_Cuisine,$R$4,d_Pay,$S$4,d_Type,$T$4),0) -> 883.05556
B65: =TEXT(C65,"mmm-yy") -> May-25 | C65: 45778 | D65: =COUNTIFS(d_Date,">="&$C65,d_Date,"<"&EDATE($C65,1),d_Year,$P$4,d_City,$Q$4,d_Cuisine,$R$4,d_Pay,$S$4,d_Type,$T$4) -> 93 | E65: =COUNTIFS(d_Date,">="&$C65,d_Date,"<"&EDATE($C65,1),d_Status,"Delivered",d_Year,$P$4,d_City,$Q$4,d_Cuisine,$R$4,d_Pay,$S$4,d_Type,$T$4) -> 59 | F65: =COUNTIFS(d_Date,">="&$C65,d_Date,"<"&EDATE($C65,1),d_Status,"Pending",d_Year,$P$4,d_City,$Q$4,d_Cuisine,$R$4,d_Pay,$S$4,d_Type,$T$4) -> 18 | G65: =COUNTIFS(d_Date,">="&$C65,d_Date,"<"&EDATE($C65,1),d_Status,"Cancelled",d_Year,$P$4,d_City,$Q$4,d_Cuisine,$R$4,d_Pay,$S$4,d_Type,$T$4) -> 16 | H65: =IFERROR(AVERAGEIFS(d_OV,d_Date,">="&$C65,d_Date,"<"&EDATE($C65,1),d_Year,$P$4,d_City,$Q$4,d_Cuisine,$R$4,d_Pay,$S$4,d_Type,$T$4),0) -> 921.97849
B66: =TEXT(C66,"mmm-yy") -> Jun-25 | C66: 45809 | D66: =COUNTIFS(d_Date,">="&$C66,d_Date,"<"&EDATE($C66,1),d_Year,$P$4,d_City,$Q$4,d_Cuisine,$R$4,d_Pay,$S$4,d_Type,$T$4) -> 90 | E66: =COUNTIFS(d_Date,">="&$C66,d_Date,"<"&EDATE($C66,1),d_Status,"Delivered",d_Year,$P$4,d_City,$Q$4,d_Cuisine,$R$4,d_Pay,$S$4,d_Type,$T$4) -> 58 | F66: =COUNTIFS(d_Date,">="&$C66,d_Date,"<"&EDATE($C66,1),d_Status,"Pending",d_Year,$P$4,d_City,$Q$4,d_Cuisine,$R$4,d_Pay,$S$4,d_Type,$T$4) -> 13 | G66: =COUNTIFS(d_Date,">="&$C66,d_Date,"<"&EDATE($C66,1),d_Status,"Cancelled",d_Year,$P$4,d_City,$Q$4,d_Cuisine,$R$4,d_Pay,$S$4,d_Type,$T$4) -> 19 | H66: =IFERROR(AVERAGEIFS(d_OV,d_Date,">="&$C66,d_Date,"<"&EDATE($C66,1),d_Year,$P$4,d_City,$Q$4,d_Cuisine,$R$4,d_Pay,$S$4,d_Type,$T$4),0) -> 997.96667
B67: =TEXT(C67,"mmm-yy") -> Jul-25 | C67: 45839 | D67: =COUNTIFS(d_Date,">="&$C67,d_Date,"<"&EDATE($C67,1),d_Year,$P$4,d_City,$Q$4,d_Cuisine,$R$4,d_Pay,$S$4,d_Type,$T$4) -> 93 | E67: =COUNTIFS(d_Date,">="&$C67,d_Date,"<"&EDATE($C67,1),d_Status,"Delivered",d_Year,$P$4,d_City,$Q$4,d_Cuisine,$R$4,d_Pay,$S$4,d_Type,$T$4) -> 59 | F67: =COUNTIFS(d_Date,">="&$C67,d_Date,"<"&EDATE($C67,1),d_Status,"Pending",d_Year,$P$4,d_City,$Q$4,d_Cuisine,$R$4,d_Pay,$S$4,d_Type,$T$4) -> 18 | G67: =COUNTIFS(d_Date,">="&$C67,d_Date,"<"&EDATE($C67,1),d_Status,"Cancelled",d_Year,$P$4,d_City,$Q$4,d_Cuisine,$R$4,d_Pay,$S$4,d_Type,$T$4) -> 16 | H67: =IFERROR(AVERAGEIFS(d_OV,d_Date,">="&$C67,d_Date,"<"&EDATE($C67,1),d_Year,$P$4,d_City,$Q$4,d_Cuisine,$R$4,d_Pay,$S$4,d_Type,$T$4),0) -> 989.21505
B68: =TEXT(C68,"mmm-yy") -> Aug-25 | C68: 45870 | D68: =COUNTIFS(d_Date,">="&$C68,d_Date,"<"&EDATE($C68,1),d_Year,$P$4,d_City,$Q$4,d_Cuisine,$R$4,d_Pay,$S$4,d_Type,$T$4) -> 93 | E68: =COUNTIFS(d_Date,">="&$C68,d_Date,"<"&EDATE($C68,1),d_Status,"Delivered",d_Year,$P$4,d_City,$Q$4,d_Cuisine,$R$4,d_Pay,$S$4,d_Type,$T$4) -> 70 | F68: =COUNTIFS(d_Date,">="&$C68,d_Date,"<"&EDATE($C68,1),d_Status,"Pending",d_Year,$P$4,d_City,$Q$4,d_Cuisine,$R$4,d_Pay,$S$4,d_Type,$T$4) -> 11 | G68: =COUNTIFS(d_Date,">="&$C68,d_Date,"<"&EDATE($C68,1),d_Status,"Cancelled",d_Year,$P$4,d_City,$Q$4,d_Cuisine,$R$4,d_Pay,$S$4,d_Type,$T$4) -> 12 | H68: =IFERROR(AVERAGEIFS(d_OV,d_Date,">="&$C68,d_Date,"<"&EDATE($C68,1),d_Year,$P$4,d_City,$Q$4,d_Cuisine,$R$4,d_Pay,$S$4,d_Type,$T$4),0) -> 876.88172
B69: =TEXT(C69,"mmm-yy") -> Sep-25 | C69: 45901 | D69: =COUNTIFS(d_Date,">="&$C69,d_Date,"<"&EDATE($C69,1),d_Year,$P$4,d_City,$Q$4,d_Cuisine,$R$4,d_Pay,$S$4,d_Type,$T$4) -> 90 | E69: =COUNTIFS(d_Date,">="&$C69,d_Date,"<"&EDATE($C69,1),d_Status,"Delivered",d_Year,$P$4,d_City,$Q$4,d_Cuisine,$R$4,d_Pay,$S$4,d_Type,$T$4) -> 60 | F69: =COUNTIFS(d_Date,">="&$C69,d_Date,"<"&EDATE($C69,1),d_Status,"Pending",d_Year,$P$4,d_City,$Q$4,d_Cuisine,$R$4,d_Pay,$S$4,d_Type,$T$4) -> 14 | G69: =COUNTIFS(d_Date,">="&$C69,d_Date,"<"&EDATE($C69,1),d_Status,"Cancelled",d_Year,$P$4,d_City,$Q$4,d_Cuisine,$R$4,d_Pay,$S$4,d_Type,$T$4) -> 16 | H69: =IFERROR(AVERAGEIFS(d_OV,d_Date,">="&$C69,d_Date,"<"&EDATE($C69,1),d_Year,$P$4,d_City,$Q$4,d_Cuisine,$R$4,d_Pay,$S$4,d_Type,$T$4),0) -> 910.43333
B70: =TEXT(C70,"mmm-yy") -> Oct-25 | C70: 45931 | D70: =COUNTIFS(d_Date,">="&$C70,d_Date,"<"&EDATE($C70,1),d_Year,$P$4,d_City,$Q$4,d_Cuisine,$R$4,d_Pay,$S$4,d_Type,$T$4) -> 93 | E70: =COUNTIFS(d_Date,">="&$C70,d_Date,"<"&EDATE($C70,1),d_Status,"Delivered",d_Year,$P$4,d_City,$Q$4,d_Cuisine,$R$4,d_Pay,$S$4,d_Type,$T$4) -> 63 | F70: =COUNTIFS(d_Date,">="&$C70,d_Date,"<"&EDATE($C70,1),d_Status,"Pending",d_Year,$P$4,d_City,$Q$4,d_Cuisine,$R$4,d_Pay,$S$4,d_Type,$T$4) -> 15 | G70: =COUNTIFS(d_Date,">="&$C70,d_Date,"<"&EDATE($C70,1),d_Status,"Cancelled",d_Year,$P$4,d_City,$Q$4,d_Cuisine,$R$4,d_Pay,$S$4,d_Type,$T$4) -> 15 | H70: =IFERROR(AVERAGEIFS(d_OV,d_Date,">="&$C70,d_Date,"<"&EDATE($C70,1),d_Year,$P$4,d_City,$Q$4,d_Cuisine,$R$4,d_Pay,$S$4,d_Type,$T$4),0) -> 937.03226
B71: =TEXT(C71,"mmm-yy") -> Nov-25 | C71: 45962 | D71: =COUNTIFS(d_Date,">="&$C71,d_Date,"<"&EDATE($C71,1),d_Year,$P$4,d_City,$Q$4,d_Cuisine,$R$4,d_Pay,$S$4,d_Type,$T$4) -> 90 | E71: =COUNTIFS(d_Date,">="&$C71,d_Date,"<"&EDATE($C71,1),d_Status,"Delivered",d_Year,$P$4,d_City,$Q$4,d_Cuisine,$R$4,d_Pay,$S$4,d_Type,$T$4) -> 61 | F71: =COUNTIFS(d_Date,">="&$C71,d_Date,"<"&EDATE($C71,1),d_Status,"Pending",d_Year,$P$4,d_City,$Q$4,d_Cuisine,$R$4,d_Pay,$S$4,d_Type,$T$4) -> 14 | G71: =COUNTIFS(d_Date,">="&$C71,d_Date,"<"&EDATE($C71,1),d_Status,"Cancelled",d_Year,$P$4,d_City,$Q$4,d_Cuisine,$R$4,d_Pay,$S$4,d_Type,$T$4) -> 15 | H71: =IFERROR(AVERAGEIFS(d_OV,d_Date,">="&$C71,d_Date,"<"&EDATE($C71,1),d_Year,$P$4,d_City,$Q$4,d_Cuisine,$R$4,d_Pay,$S$4,d_Type,$T$4),0) -> 951.56667
B72: =TEXT(C72,"mmm-yy") -> Dec-25 | C72: 45992 | D72: =COUNTIFS(d_Date,">="&$C72,d_Date,"<"&EDATE($C72,1),d_Year,$P$4,d_City,$Q$4,d_Cuisine,$R$4,d_Pay,$S$4,d_Type,$T$4) -> 93 | E72: =COUNTIFS(d_Date,">="&$C72,d_Date,"<"&EDATE($C72,1),d_Status,"Delivered",d_Year,$P$4,d_City,$Q$4,d_Cuisine,$R$4,d_Pay,$S$4,d_Type,$T$4) -> 61 | F72: =COUNTIFS(d_Date,">="&$C72,d_Date,"<"&EDATE($C72,1),d_Status,"Pending",d_Year,$P$4,d_City,$Q$4,d_Cuisine,$R$4,d_Pay,$S$4,d_Type,$T$4) -> 16 | G72: =COUNTIFS(d_Date,">="&$C72,d_Date,"<"&EDATE($C72,1),d_Status,"Cancelled",d_Year,$P$4,d_City,$Q$4,d_Cuisine,$R$4,d_Pay,$S$4,d_Type,$T$4) -> 16 | H72: =IFERROR(AVERAGEIFS(d_OV,d_Date,">="&$C72,d_Date,"<"&EDATE($C72,1),d_Year,$P$4,d_City,$Q$4,d_Cuisine,$R$4,d_Pay,$S$4,d_Type,$T$4),0) -> 946.56989
... B74: =TEXT(C74,"mmm-yy") -> Feb-26 | C74: 46054 | D74: =COUNTIFS(d_Date,">="&$C74,d_Date,"<"&EDATE($C74,1),d_Year,$P$4,d_City,$Q$4,d_Cuisine,$R$4,d_Pay,$S$4,d_Type,$T$4) -> 12 | E74: =COUNTIFS(d_Date,">="&$C74,d_Date,"<"&EDATE($C74,1),d_Status,"Delivered",d_Year,$P$4,d_City,$Q$4,d_Cuisine,$R$4,d_Pay,$S$4,d_Type,$T$4) -> 7 | F74: =COUNTIFS(d_Date,">="&$C74,d_Date,"<"&EDATE($C74,1),d_Status,"Pending",d_Year,$P$4,d_City,$Q$4,d_Cuisine,$R$4,d_Pay,$S$4,d_Type,$T$4) -> 4 | G74: =COUNTIFS(d_Date,">="&$C74,d_Date,"<"&EDATE($C74,1),d_Status,"Cancelled",d_Year,$P$4,d_City,$Q$4,d_Cuisine,$R$4,d_Pay,$S$4,d_Type,$T$4) -> 1 | H74: =IFERROR(AVERAGEIFS(d_OV,d_Date,">="&$C74,d_Date,"<"&EDATE($C74,1),d_Year,$P$4,d_City,$Q$4,d_Cuisine,$R$4,d_Pay,$S$4,d_Type,$T$4),0) -> 677.41667
B75: Total / Overall | D75: =SUM(D61:D74) -> 1200 | E75: =SUM(E61:E74) -> 791 | F75: =SUM(F61:F74) -> 207 | G75: =SUM(G61:G74) -> 202 | H75: =AVERAGEIFS(d_OV,d_ID,"<>",d_Year,$P$4,d_City,$Q$4,d_Cuisine,$R$4,d_Pay,$S$4,d_Type,$T$4) -> 931.2875
B76: Month start dates are inputs (blue). Feb-26 is a partial month (data ends 4-Feb-2026). Add rows if new months are appended.
B79: Order status mix
B80: Status | C80: Orders | D80: % of orders
B81: Delivered | C81: =COUNTIFS(d_Status,$B81,d_Year,$P$4,d_City,$Q$4,d_Cuisine,$R$4,d_Pay,$S$4,d_Type,$T$4) -> 791 | D81: =IFERROR(C81/COUNTIFS(d_ID,"<>",d_Year,$P$4,d_City,$Q$4,d_Cuisine,$R$4,d_Pay,$S$4,d_Type,$T$4),0) -> 0.65916667
B82: Pending | C82: =COUNTIFS(d_Status,$B82,d_Year,$P$4,d_City,$Q$4,d_Cuisine,$R$4,d_Pay,$S$4,d_Type,$T$4) -> 207 | D82: =IFERROR(C82/COUNTIFS(d_ID,"<>",d_Year,$P$4,d_City,$Q$4,d_Cuisine,$R$4,d_Pay,$S$4,d_Type,$T$4),0) -> 0.1725
B83: Cancelled | C83: =COUNTIFS(d_Status,$B83,d_Year,$P$4,d_City,$Q$4,d_Cuisine,$R$4,d_Pay,$S$4,d_Type,$T$4) -> 202 | D83: =IFERROR(C83/COUNTIFS(d_ID,"<>",d_Year,$P$4,d_City,$Q$4,d_Cuisine,$R$4,d_Pay,$S$4,d_Type,$T$4),0) -> 0.16833333
B84: Total / Overall | C84: =SUM(C81:C83) -> 1200 | D84: =SUM(D81:D83) -> 1
B87: Order type by status
B88: Order type | C88: Delivered | D88: Pending | E88: Cancelled | F88: Total
B89: Delivery | C89: =COUNTIFS(d_Type,$B89,d_Status,"Delivered",d_Year,$P$4,d_City,$Q$4,d_Cuisine,$R$4,d_Pay,$S$4,d_Type,$T$4) -> 592 | D89: =COUNTIFS(d_Type,$B89,d_Status,"Pending",d_Year,$P$4,d_City,$Q$4,d_Cuisine,$R$4,d_Pay,$S$4,d_Type,$T$4) -> 146 | E89: =COUNTIFS(d_Type,$B89,d_Status,"Cancelled",d_Year,$P$4,d_City,$Q$4,d_Cuisine,$R$4,d_Pay,$S$4,d_Type,$T$4) -> 143 | F89: =SUM(C89:E89) -> 881
B90: Pickup | C90: =COUNTIFS(d_Type,$B90,d_Status,"Delivered",d_Year,$P$4,d_City,$Q$4,d_Cuisine,$R$4,d_Pay,$S$4,d_Type,$T$4) -> 199 | D90: =COUNTIFS(d_Type,$B90,d_Status,"Pending",d_Year,$P$4,d_City,$Q$4,d_Cuisine,$R$4,d_Pay,$S$4,d_Type,$T$4) -> 61 | E90: =COUNTIFS(d_Type,$B90,d_Status,"Cancelled",d_Year,$P$4,d_City,$Q$4,d_Cuisine,$R$4,d_Pay,$S$4,d_Type,$T$4) -> 59 | F90: =SUM(C90:E90) -> 319
B91: Total / Overall | C91: =SUM(C89:C90) -> 791 | D91: =SUM(D89:D90) -> 207 | E91: =SUM(E89:E90) -> 202 | F91: =SUM(F89:F90) -> 1200
B94: Orders by cuisine
B95: Cuisine | C95: Orders | D95: Avg order value
B96: Burgers | C96: =COUNTIFS(d_Cuisine,$B96,d_Year,$P$4,d_City,$Q$4,d_Cuisine,$R$4,d_Pay,$S$4,d_Type,$T$4) -> 138 | D96: =IFERROR(AVERAGEIFS(d_OV,d_Cuisine,$B96,d_Year,$P$4,d_City,$Q$4,d_Cuisine,$R$4,d_Pay,$S$4,d_Type,$T$4),0) -> 919.62319
B97: North Indian | C97: =COUNTIFS(d_Cuisine,$B97,d_Year,$P$4,d_City,$Q$4,d_Cuisine,$R$4,d_Pay,$S$4,d_Type,$T$4) -> 136 | D97: =IFERROR(AVERAGEIFS(d_OV,d_Cuisine,$B97,d_Year,$P$4,d_City,$Q$4,d_Cuisine,$R$4,d_Pay,$S$4,d_Type,$T$4),0) -> 863.52206
B98: Desserts | C98: =COUNTIFS(d_Cuisine,$B98,d_Year,$P$4,d_City,$Q$4,d_Cuisine,$R$4,d_Pay,$S$4,d_Type,$T$4) -> 128 | D98: =IFERROR(AVERAGEIFS(d_OV,d_Cuisine,$B98,d_Year,$P$4,d_City,$Q$4,d_Cuisine,$R$4,d_Pay,$S$4,d_Type,$T$4),0) -> 914.59375
B99: Fast Food | C99: =COUNTIFS(d_Cuisine,$B99,d_Year,$P$4,d_City,$Q$4,d_Cuisine,$R$4,d_Pay,$S$4,d_Type,$T$4) -> 122 | D99: =IFERROR(AVERAGEIFS(d_OV,d_Cuisine,$B99,d_Year,$P$4,d_City,$Q$4,d_Cuisine,$R$4,d_Pay,$S$4,d_Type,$T$4),0) -> 872.77049
B100: Chinese | C100: =COUNTIFS(d_Cuisine,$B100,d_Year,$P$4,d_City,$Q$4,d_Cuisine,$R$4,d_Pay,$S$4,d_Type,$T$4) -> 121 | D100: =IFERROR(AVERAGEIFS(d_OV,d_Cuisine,$B100,d_Year,$P$4,d_City,$Q$4,d_Cuisine,$R$4,d_Pay,$S$4,d_Type,$T$4),0) -> 943.38017
B101: Momos | C101: =COUNTIFS(d_Cuisine,$B101,d_Year,$P$4,d_City,$Q$4,d_Cuisine,$R$4,d_Pay,$S$4,d_Type,$T$4) -> 116 | D101: =IFERROR(AVERAGEIFS(d_OV,d_Cuisine,$B101,d_Year,$P$4,d_City,$Q$4,d_Cuisine,$R$4,d_Pay,$S$4,d_Type,$T$4),0) -> 961.24138
B102: Biryani | C102: =COUNTIFS(d_Cuisine,$B102,d_Year,$P$4,d_City,$Q$4,d_Cuisine,$R$4,d_Pay,$S$4,d_Type,$T$4) -> 115 | D102: =IFERROR(AVERAGEIFS(d_OV,d_Cuisine,$B102,d_Year,$P$4,d_City,$Q$4,d_Cuisine,$R$4,d_Pay,$S$4,d_Type,$T$4),0) -> 949.44348
B103: Healthy | C103: =COUNTIFS(d_Cuisine,$B103,d_Year,$P$4,d_City,$Q$4,d_Cuisine,$R$4,d_Pay,$S$4,d_Type,$T$4) -> 114 | D103: =IFERROR(AVERAGEIFS(d_OV,d_Cuisine,$B103,d_Year,$P$4,d_City,$Q$4,d_Cuisine,$R$4,d_Pay,$S$4,d_Type,$T$4),0) -> 976.47368
B104: Pizza | C104: =COUNTIFS(d_Cuisine,$B104,d_Year,$P$4,d_City,$Q$4,d_Cuisine,$R$4,d_Pay,$S$4,d_Type,$T$4) -> 109 | D104: =IFERROR(AVERAGEIFS(d_OV,d_Cuisine,$B104,d_Year,$P$4,d_City,$Q$4,d_Cuisine,$R$4,d_Pay,$S$4,d_Type,$T$4),0) -> 999.59633
B105: South Indian | C105: =COUNTIFS(d_Cuisine,$B105,d_Year,$P$4,d_City,$Q$4,d_Cuisine,$R$4,d_Pay,$S$4,d_Type,$T$4) -> 101 | D105: =IFERROR(AVERAGEIFS(d_OV,d_Cuisine,$B105,d_Year,$P$4,d_City,$Q$4,d_Cuisine,$R$4,d_Pay,$S$4,d_Type,$T$4),0) -> 936.0297
B106: Total / Overall | C106: =SUM(C96:C105) -> 1200 | D106: =AVERAGEIFS(d_OV,d_ID,"<>",d_Year,$P$4,d_City,$Q$4,d_Cuisine,$R$4,d_Pay,$S$4,d_Type,$T$4) -> 931.2875
B109: Orders by payment method
B110: Payment method | C110: Orders | D110: % of orders
B111: UPI | C111: =COUNTIFS(d_Pay,$B111,d_Year,$P$4,d_City,$Q$4,d_Cuisine,$R$4,d_Pay,$S$4,d_Type,$T$4) -> 496 | D111: =IFERROR(C111/COUNTIFS(d_ID,"<>",d_Year,$P$4,d_City,$Q$4,d_Cuisine,$R$4,d_Pay,$S$4,d_Type,$T$4),0) -> 0.41333333
B112: Credit Card | C112: =COUNTIFS(d_Pay,$B112,d_Year,$P$4,d_City,$Q$4,d_Cuisine,$R$4,d_Pay,$S$4,d_Type,$T$4) -> 239 | D112: =IFERROR(C112/COUNTIFS(d_ID,"<>",d_Year,$P$4,d_City,$Q$4,d_Cuisine,$R$4,d_Pay,$S$4,d_Type,$T$4),0) -> 0.19916667
B113: Debit Card | C113: =COUNTIFS(d_Pay,$B113,d_Year,$P$4,d_City,$Q$4,d_Cuisine,$R$4,d_Pay,$S$4,d_Type,$T$4) -> 232 | D113: =IFERROR(C113/COUNTIFS(d_ID,"<>",d_Year,$P$4,d_City,$Q$4,d_Cuisine,$R$4,d_Pay,$S$4,d_Type,$T$4),0) -> 0.19333333
B114: Cash | C114: =COUNTIFS(d_Pay,$B114,d_Year,$P$4,d_City,$Q$4,d_Cuisine,$R$4,d_Pay,$S$4,d_Type,$T$4) -> 138 | D114: =IFERROR(C114/COUNTIFS(d_ID,"<>",d_Year,$P$4,d_City,$Q$4,d_Cuisine,$R$4,d_Pay,$S$4,d_Type,$T$4),0) -> 0.115
B115: Wallet | C115: =COUNTIFS(d_Pay,$B115,d_Year,$P$4,d_City,$Q$4,d_Cuisine,$R$4,d_Pay,$S$4,d_Type,$T$4) -> 95 | D115: =IFERROR(C115/COUNTIFS(d_ID,"<>",d_Year,$P$4,d_City,$Q$4,d_Cuisine,$R$4,d_Pay,$S$4,d_Type,$T$4),0) -> 0.079166667
B116: Total / Overall | C116: =SUM(C111:C115) -> 1200 | D116: =SUM(D111:D115) -> 1
B119: Orders by city
B120: City | C120: Orders | D120: Avg order value
B121: Delhi | C121: =COUNTIFS(d_City,$B121,d_Year,$P$4,d_City,$Q$4,d_Cuisine,$R$4,d_Pay,$S$4,d_Type,$T$4) -> 119 | D121: =IFERROR(AVERAGEIFS(d_OV,d_City,$B121,d_Year,$P$4,d_City,$Q$4,d_Cuisine,$R$4,d_Pay,$S$4,d_Type,$T$4),0) -> 943.82353
B122: Ahmedabad | C122: =COUNTIFS(d_City,$B122,d_Year,$P$4,d_City,$Q$4,d_Cuisine,$R$4,d_Pay,$S$4,d_Type,$T$4) -> 114 | D122: =IFERROR(AVERAGEIFS(d_OV,d_City,$B122,d_Year,$P$4,d_City,$Q$4,d_Cuisine,$R$4,d_Pay,$S$4,d_Type,$T$4),0) -> 868.15789
B123: Bengaluru | C123: =COUNTIFS(d_City,$B123,d_Year,$P$4,d_City,$Q$4,d_Cuisine,$R$4,d_Pay,$S$4,d_Type,$T$4) -> 110 | D123: =IFERROR(AVERAGEIFS(d_OV,d_City,$B123,d_Year,$P$4,d_City,$Q$4,d_Cuisine,$R$4,d_Pay,$S$4,d_Type,$T$4),0) -> 967.17273
B124: Chennai | C124: =COUNTIFS(d_City,$B124,d_Year,$P$4,d_City,$Q$4,d_Cuisine,$R$4,d_Pay,$S$4,d_Type,$T$4) -> 108 | D124: =IFERROR(AVERAGEIFS(d_OV,d_City,$B124,d_Year,$P$4,d_City,$Q$4,d_Cuisine,$R$4,d_Pay,$S$4,d_Type,$T$4),0) -> 942.82407
B125: Noida | C125: =COUNTIFS(d_City,$B125,d_Year,$P$4,d_City,$Q$4,d_Cuisine,$R$4,d_Pay,$S$4,d_Type,$T$4) -> 107 | D125: =IFERROR(AVERAGEIFS(d_OV,d_City,$B125,d_Year,$P$4,d_City,$Q$4,d_Cuisine,$R$4,d_Pay,$S$4,d_Type,$T$4),0) -> 961.84112
B126: Jaipur | C126: =COUNTIFS(d_City,$B126,d_Year,$P$4,d_City,$Q$4,d_Cuisine,$R$4,d_Pay,$S$4,d_Type,$T$4) -> 102 | D126: =IFERROR(AVERAGEIFS(d_OV,d_City,$B126,d_Year,$P$4,d_City,$Q$4,d_Cuisine,$R$4,d_Pay,$S$4,d_Type,$T$4),0) -> 839.84314
B127: Hyderabad | C127: =COUNTIFS(d_City,$B127,d_Year,$P$4,d_City,$Q$4,d_Cuisine,$R$4,d_Pay,$S$4,d_Type,$T$4) -> 96 | D127: =IFERROR(AVERAGEIFS(d_OV,d_City,$B127,d_Year,$P$4,d_City,$Q$4,d_Cuisine,$R$4,d_Pay,$S$4,d_Type,$T$4),0) -> 965.42708
B128: Pune | C128: =COUNTIFS(d_City,$B128,d_Year,$P$4,d_City,$Q$4,d_Cuisine,$R$4,d_Pay,$S$4,d_Type,$T$4) -> 96 | D128: =IFERROR(AVERAGEIFS(d_OV,d_City,$B128,d_Year,$P$4,d_City,$Q$4,d_Cuisine,$R$4,d_Pay,$S$4,d_Type,$T$4),0) -> 929.5625
B129: Kolkata | C129: =COUNTIFS(d_City,$B129,d_Year,$P$4,d_City,$Q$4,d_Cuisine,$R$4,d_Pay,$S$4,d_Type,$T$4) -> 94 | D129: =IFERROR(AVERAGEIFS(d_OV,d_City,$B129,d_Year,$P$4,d_City,$Q$4,d_Cuisine,$R$4,d_Pay,$S$4,d_Type,$T$4),0) -> 891.73404
B130: Lucknow | C130: =COUNTIFS(d_City,$B130,d_Year,$P$4,d_City,$Q$4,d_Cuisine,$R$4,d_Pay,$S$4,d_Type,$T$4) -> 91 | D130: =IFERROR(AVERAGEIFS(d_OV,d_City,$B130,d_Year,$P$4,d_City,$Q$4,d_Cuisine,$R$4,d_Pay,$S$4,d_Type,$T$4),0) -> 991.30769
B131: Mumbai | C131: =COUNTIFS(d_City,$B131,d_Year,$P$4,d_City,$Q$4,d_Cuisine,$R$4,d_Pay,$S$4,d_Type,$T$4) -> 83 | D131: =IFERROR(AVERAGEIFS(d_OV,d_City,$B131,d_Year,$P$4,d_City,$Q$4,d_Cuisine,$R$4,d_Pay,$S$4,d_Type,$T$4),0) -> 891.86747
B132: Gurugram | C132: =COUNTIFS(d_City,$B132,d_Year,$P$4,d_City,$Q$4,d_Cuisine,$R$4,d_Pay,$S$4,d_Type,$T$4) -> 80 | D132: =IFERROR(AVERAGEIFS(d_OV,d_City,$B132,d_Year,$P$4,d_City,$Q$4,d_Cuisine,$R$4,d_Pay,$S$4,d_Type,$T$4),0) -> 993.6125
B133: Total / Overall | C133: =SUM(C121:C132) -> 1200 | D133: =AVERAGEIFS(d_OV,d_ID,"<>",d_Year,$P$4,d_City,$Q$4,d_Cuisine,$R$4,d_Pay,$S$4,d_Type,$T$4) -> 931.2875

Sheet Restaurant Performance
B2: Restaurant Performance
B3: Orders, revenue, ratings, speed and cancellations for each restaurant. Revenue = Net_Amount of Delivered orders. ▸ Use the yellow filters in row 4 – every KPI, chart and table updates. | L3: ← Back to Home
B4: Year: | C4: All | D4: City: | E4: All | F4: Cuisine: | G4: All | H4: Payment: | I4: All | J4: Order type: | K4: All | L4: ="Orders in view: "&TEXT(COUNTIFS(d_ID,"<>",d_Year,$P$4,d_City,$Q$4,d_Cuisine,$R$4,d_Pay,$S$4,d_Type,$T$4),"#,##0") -> Orders in view: 1,200 | P4: =IF(C4="All",">0",C4) -> >0 | Q4: =IF(E4="All","*",E4) -> * | R4: =IF(G4="All","*",G4) -> * | S4: =IF(I4="All","*",I4) -> * | T4: =IF(K4="All","*",K4) -> *
B5: RESTAURANTS | D5: NET REVENUE | F5: TOP REVENUE RESTAURANT | H5: BEST RATED (CUSTOMERS) | J5: AVG RESTAURANT RATING | L5: HIGHEST CANCEL RATE
B6: =COUNTA(B61:B72) -> 12 | D6: =SUM(G61:G72) -> 699950 | F6: =INDEX(B61:B72,MATCH(MAX(G61:G72),G61:G72,0)) -> Burger House | H6: =INDEX(B61:B72,MATCH(MAX(J61:J72),J61:J72,0)) -> Cafe Aroma | J6: =AVERAGEIFS(d_RRating,d_ID,"<>",d_Year,$P$4,d_City,$Q$4,d_Cuisine,$R$4,d_Pay,$S$4,d_Type,$T$4) -> 3.7175 | L6: =INDEX(B61:B72,MATCH(MAX(F61:F72),F61:F72,0)) -> Food Street
B7: In the data | D7: Delivered orders | F7: Highest net revenue | H7: Highest avg customer rating | J7: Out of 5 | L7: Restaurant to watch
B57: Supporting data (feeds the charts above)
B59: Restaurant scorecard
B60: Restaurant | C60: Orders | D60: Delivered | E60: Cancelled | F60: Cancel rate | G60: Net revenue | H60: Avg order value | I60: Avg restaurant rating | J60: Avg customer rating | K60: Avg delivery time (min) | L60: Revenue rank
B61: Urban Tadka | C61: =COUNTIFS(d_Rest,$B61,d_Year,$P$4,d_City,$Q$4,d_Cuisine,$R$4,d_Pay,$S$4,d_Type,$T$4) -> 117 | D61: =COUNTIFS(d_Rest,$B61,d_Status,"Delivered",d_Year,$P$4,d_City,$Q$4,d_Cuisine,$R$4,d_Pay,$S$4,d_Type,$T$4) -> 78 | E61: =COUNTIFS(d_Rest,$B61,d_Status,"Cancelled",d_Year,$P$4,d_City,$Q$4,d_Cuisine,$R$4,d_Pay,$S$4,d_Type,$T$4) -> 16 | F61: =IFERROR(E61/C61,0) -> 0.13675214 | G61: =SUMIFS(d_Net,d_Rest,$B61,d_Status,"Delivered",d_Year,$P$4,d_City,$Q$4,d_Cuisine,$R$4,d_Pay,$S$4,d_Type,$T$4) -> 66822 | H61: =IFERROR(AVERAGEIFS(d_OV,d_Rest,$B61,d_Year,$P$4,d_City,$Q$4,d_Cuisine,$R$4,d_Pay,$S$4,d_Type,$T$4),0) -> 904.83761 | I61: =IFERROR(AVERAGEIFS(d_RRating,d_Rest,$B61,d_Year,$P$4,d_City,$Q$4,d_Cuisine,$R$4,d_Pay,$S$4,d_Type,$T$4),0) -> 3.7042735 | J61: =IFERROR(AVERAGEIFS(d_CRating,d_Rest,$B61,d_Year,$P$4,d_City,$Q$4,d_Cuisine,$R$4,d_Pay,$S$4,d_Type,$T$4),0) -> 4.0854701 | K61: =IFERROR(AVERAGEIFS(d_Time,d_Rest,$B61,d_Status,"Delivered",d_Year,$P$4,d_City,$Q$4,d_Cuisine,$R$4,d_Pay,$S$4,d_Type,$T$4),0) -> 41.089744 | L61: =RANK(G61,$G$61:$G$72) -> 2
B62: Taste Junction | C62: =COUNTIFS(d_Rest,$B62,d_Year,$P$4,d_City,$Q$4,d_Cuisine,$R$4,d_Pay,$S$4,d_Type,$T$4) -> 107 | D62: =COUNTIFS(d_Rest,$B62,d_Status,"Delivered",d_Year,$P$4,d_City,$Q$4,d_Cuisine,$R$4,d_Pay,$S$4,d_Type,$T$4) -> 73 | E62: =COUNTIFS(d_Rest,$B62,d_Status,"Cancelled",d_Year,$P$4,d_City,$Q$4,d_Cuisine,$R$4,d_Pay,$S$4,d_Type,$T$4) -> 15 | F62: =IFERROR(E62/C62,0) -> 0.14018692 | G62: =SUMIFS(d_Net,d_Rest,$B62,d_Status,"Delivered",d_Year,$P$4,d_City,$Q$4,d_Cuisine,$R$4,d_Pay,$S$4,d_Type,$T$4) -> 60113 | H62: =IFERROR(AVERAGEIFS(d_OV,d_Rest,$B62,d_Year,$P$4,d_City,$Q$4,d_Cuisine,$R$4,d_Pay,$S$4,d_Type,$T$4),0) -> 867.94393 | I62: =IFERROR(AVERAGEIFS(d_RRating,d_Rest,$B62,d_Year,$P$4,d_City,$Q$4,d_Cuisine,$R$4,d_Pay,$S$4,d_Type,$T$4),0) -> 3.7626168 | J62: =IFERROR(AVERAGEIFS(d_CRating,d_Rest,$B62,d_Year,$P$4,d_City,$Q$4,d_Cuisine,$R$4,d_Pay,$S$4,d_Type,$T$4),0) -> 3.9065421 | K62: =IFERROR(AVERAGEIFS(d_Time,d_Rest,$B62,d_Status,"Delivered",d_Year,$P$4,d_City,$Q$4,d_Cuisine,$R$4,d_Pay,$S$4,d_Type,$T$4),0) -> 42.027397 | L62: =RANK(G62,$G$61:$G$72) -> 5
B63: Cafe Aroma | C63: =COUNTIFS(d_Rest,$B63,d_Year,$P$4,d_City,$Q$4,d_Cuisine,$R$4,d_Pay,$S$4,d_Type,$T$4) -> 104 | D63: =COUNTIFS(d_Rest,$B63,d_Status,"Delivered",d_Year,$P$4,d_City,$Q$4,d_Cuisine,$R$4,d_Pay,$S$4,d_Type,$T$4) -> 70 | E63: =COUNTIFS(d_Rest,$B63,d_Status,"Cancelled",d_Year,$P$4,d_City,$Q$4,d_Cuisine,$R$4,d_Pay,$S$4,d_Type,$T$4) -> 22 | F63: =IFERROR(E63/C63,0) -> 0.21153846 | G63: =SUMIFS(d_Net,d_Rest,$B63,d_Status,"Delivered",d_Year,$P$4,d_City,$Q$4,d_Cuisine,$R$4,d_Pay,$S$4,d_Type,$T$4) -> 55539 | H63: =IFERROR(AVERAGEIFS(d_OV,d_Rest,$B63,d_Year,$P$4,d_City,$Q$4,d_Cuisine,$R$4,d_Pay,$S$4,d_Type,$T$4),0) -> 883.95192 | I63: =IFERROR(AVERAGEIFS(d_RRating,d_Rest,$B63,d_Year,$P$4,d_City,$Q$4,d_Cuisine,$R$4,d_Pay,$S$4,d_Type,$T$4),0) -> 3.7586538 | J63: =IFERROR(AVERAGEIFS(d_CRating,d_Rest,$B63,d_Year,$P$4,d_City,$Q$4,d_Cuisine,$R$4,d_Pay,$S$4,d_Type,$T$4),0) -> 4.2403846 | K63: =IFERROR(AVERAGEIFS(d_Time,d_Rest,$B63,d_Status,"Delivered",d_Year,$P$4,d_City,$Q$4,d_Cuisine,$R$4,d_Pay,$S$4,d_Type,$T$4),0) -> 42.228571 | L63: =RANK(G63,$G$61:$G$72) -> 9
B64: Delhi Zaika | C64: =COUNTIFS(d_Rest,$B64,d_Year,$P$4,d_City,$Q$4,d_Cuisine,$R$4,d_Pay,$S$4,d_Type,$T$4) -> 102 | D64: =COUNTIFS(d_Rest,$B64,d_Status,"Delivered",d_Year,$P$4,d_City,$Q$4,d_Cuisine,$R$4,d_Pay,$S$4,d_Type,$T$4) -> 70 | E64: =COUNTIFS(d_Rest,$B64,d_Status,"Cancelled",d_Year,$P$4,d_City,$Q$4,d_Cuisine,$R$4,d_Pay,$S$4,d_Type,$T$4) -> 17 | F64: =IFERROR(E64/C64,0) -> 0.16666667 | G64: =SUMIFS(d_Net,d_Rest,$B64,d_Status,"Delivered",d_Year,$P$4,d_City,$Q$4,d_Cuisine,$R$4,d_Pay,$S$4,d_Type,$T$4) -> 59187 | H64: =IFERROR(AVERAGEIFS(d_OV,d_Rest,$B64,d_Year,$P$4,d_City,$Q$4,d_Cuisine,$R$4,d_Pay,$S$4,d_Type,$T$4),0) -> 926.42157 | I64: =IFERROR(AVERAGEIFS(d_RRating,d_Rest,$B64,d_Year,$P$4,d_City,$Q$4,d_Cuisine,$R$4,d_Pay,$S$4,d_Type,$T$4),0) -> 3.7617647 | J64: =IFERROR(AVERAGEIFS(d_CRating,d_Rest,$B64,d_Year,$P$4,d_City,$Q$4,d_Cuisine,$R$4,d_Pay,$S$4,d_Type,$T$4),0) -> 3.8333333 | K64: =IFERROR(AVERAGEIFS(d_Time,d_Rest,$B64,d_Status,"Delivered",d_Year,$P$4,d_City,$Q$4,d_Cuisine,$R$4,d_Pay,$S$4,d_Type,$T$4),0) -> 42.842857 | L64: =RANK(G64,$G$61:$G$72) -> 6
B65: Burger House | C65: =COUNTIFS(d_Rest,$B65,d_Year,$P$4,d_City,$Q$4,d_Cuisine,$R$4,d_Pay,$S$4,d_Type,$T$4) -> 101 | D65: =COUNTIFS(d_Rest,$B65,d_Status,"Delivered",d_Year,$P$4,d_City,$Q$4,d_Cuisine,$R$4,d_Pay,$S$4,d_Type,$T$4) -> 69 | E65: =COUNTIFS(d_Rest,$B65,d_Status,"Cancelled",d_Year,$P$4,d_City,$Q$4,d_Cuisine,$R$4,d_Pay,$S$4,d_Type,$T$4) -> 17 | F65: =IFERROR(E65/C65,0) -> 0.16831683 | G65: =SUMIFS(d_Net,d_Rest,$B65,d_Status,"Delivered",d_Year,$P$4,d_City,$Q$4,d_Cuisine,$R$4,d_Pay,$S$4,d_Type,$T$4) -> 67652 | H65: =IFERROR(AVERAGEIFS(d_OV,d_Rest,$B65,d_Year,$P$4,d_City,$Q$4,d_Cuisine,$R$4,d_Pay,$S$4,d_Type,$T$4),0) -> 1019.6931 | I65: =IFERROR(AVERAGEIFS(d_RRating,d_Rest,$B65,d_Year,$P$4,d_City,$Q$4,d_Cuisine,$R$4,d_Pay,$S$4,d_Type,$T$4),0) -> 3.6237624 | J65: =IFERROR(AVERAGEIFS(d_CRating,d_Rest,$B65,d_Year,$P$4,d_City,$Q$4,d_Cuisine,$R$4,d_Pay,$S$4,d_Type,$T$4),0) -> 3.9009901 | K65: =IFERROR(AVERAGEIFS(d_Time,d_Rest,$B65,d_Status,"Delivered",d_Year,$P$4,d_City,$Q$4,d_Cuisine,$R$4,d_Pay,$S$4,d_Type,$T$4),0) -> 41.202899 | L65: =RANK(G65,$G$61:$G$72) -> 1
B66: Spice Hub | C66: =COUNTIFS(d_Rest,$B66,d_Year,$P$4,d_City,$Q$4,d_Cuisine,$R$4,d_Pay,$S$4,d_Type,$T$4) -> 100 | D66: =COUNTIFS(d_Rest,$B66,d_Status,"Delivered",d_Year,$P$4,d_City,$Q$4,d_Cuisine,$R$4,d_Pay,$S$4,d_Type,$T$4) -> 67 | E66: =COUNTIFS(d_Rest,$B66,d_Status,"Cancelled",d_Year,$P$4,d_City,$Q$4,d_Cuisine,$R$4,d_Pay,$S$4,d_Type,$T$4) -> 11 | F66: =IFERROR(E66/C66,0) -> 0.11 | G66: =SUMIFS(d_Net,d_Rest,$B66,d_Status,"Delivered",d_Year,$P$4,d_City,$Q$4,d_Cuisine,$R$4,d_Pay,$S$4,d_Type,$T$4) -> 63464 | H66: =IFERROR(AVERAGEIFS(d_OV,d_Rest,$B66,d_Year,$P$4,d_City,$Q$4,d_Cuisine,$R$4,d_Pay,$S$4,d_Type,$T$4),0) -> 926.22 | I66: =IFERROR(AVERAGEIFS(d_RRating,d_Rest,$B66,d_Year,$P$4,d_City,$Q$4,d_Cuisine,$R$4,d_Pay,$S$4,d_Type,$T$4),0) -> 3.676 | J66: =IFERROR(AVERAGEIFS(d_CRating,d_Rest,$B66,d_Year,$P$4,d_City,$Q$4,d_Cuisine,$R$4,d_Pay,$S$4,d_Type,$T$4),0) -> 4 | K66: =IFERROR(AVERAGEIFS(d_Time,d_Rest,$B66,d_Status,"Delivered",d_Year,$P$4,d_City,$Q$4,d_Cuisine,$R$4,d_Pay,$S$4,d_Type,$T$4),0) -> 40.402985 | L66: =RANK(G66,$G$61:$G$72) -> 3
B67: Pizza Point | C67: =COUNTIFS(d_Rest,$B67,d_Year,$P$4,d_City,$Q$4,d_Cuisine,$R$4,d_Pay,$S$4,d_Type,$T$4) -> 99 | D67: =COUNTIFS(d_Rest,$B67,d_Status,"Delivered",d_Year,$P$4,d_City,$Q$4,d_Cuisine,$R$4,d_Pay,$S$4,d_Type,$T$4) -> 74 | E67: =COUNTIFS(d_Rest,$B67,d_Status,"Cancelled",d_Year,$P$4,d_City,$Q$4,d_Cuisine,$R$4,d_Pay,$S$4,d_Type,$T$4) -> 18 | F67: =IFERROR(E67/C67,0) -> 0.18181818 | G67: =SUMIFS(d_Net,d_Rest,$B67,d_Status,"Delivered",d_Year,$P$4,d_City,$Q$4,d_Cuisine,$R$4,d_Pay,$S$4,d_Type,$T$4) -> 60969 | H67: =IFERROR(AVERAGEIFS(d_OV,d_Rest,$B67,d_Year,$P$4,d_City,$Q$4,d_Cuisine,$R$4,d_Pay,$S$4,d_Type,$T$4),0) -> 876 | I67: =IFERROR(AVERAGEIFS(d_RRating,d_Rest,$B67,d_Year,$P$4,d_City,$Q$4,d_Cuisine,$R$4,d_Pay,$S$4,d_Type,$T$4),0) -> 3.8666667 | J67: =IFERROR(AVERAGEIFS(d_CRating,d_Rest,$B67,d_Year,$P$4,d_City,$Q$4,d_Cuisine,$R$4,d_Pay,$S$4,d_Type,$T$4),0) -> 4.1818182 | K67: =IFERROR(AVERAGEIFS(d_Time,d_Rest,$B67,d_Status,"Delivered",d_Year,$P$4,d_City,$Q$4,d_Cuisine,$R$4,d_Pay,$S$4,d_Type,$T$4),0) -> 42.054054 | L67: =RANK(G67,$G$61:$G$72) -> 4
B68: Green Bowl | C68: =COUNTIFS(d_Rest,$B68,d_Year,$P$4,d_City,$Q$4,d_Cuisine,$R$4,d_Pay,$S$4,d_Type,$T$4) -> 98 | D68: =COUNTIFS(d_Rest,$B68,d_Status,"Delivered",d_Year,$P$4,d_City,$Q$4,d_Cuisine,$R$4,d_Pay,$S$4,d_Type,$T$4) -> 60 | E68: =COUNTIFS(d_Rest,$B68,d_Status,"Cancelled",d_Year,$P$4,d_City,$Q$4,d_Cuisine,$R$4,d_Pay,$S$4,d_Type,$T$4) -> 14 | F68: =IFERROR(E68/C68,0) -> 0.14285714 | G68: =SUMIFS(d_Net,d_Rest,$B68,d_Status,"Delivered",d_Year,$P$4,d_City,$Q$4,d_Cuisine,$R$4,d_Pay,$S$4,d_Type,$T$4) -> 54523 | H68: =IFERROR(AVERAGEIFS(d_OV,d_Rest,$B68,d_Year,$P$4,d_City,$Q$4,d_Cuisine,$R$4,d_Pay,$S$4,d_Type,$T$4),0) -> 978.67347 | I68: =IFERROR(AVERAGEIFS(d_RRating,d_Rest,$B68,d_Year,$P$4,d_City,$Q$4,d_Cuisine,$R$4,d_Pay,$S$4,d_Type,$T$4),0) -> 3.7 | J68: =IFERROR(AVERAGEIFS(d_CRating,d_Rest,$B68,d_Year,$P$4,d_City,$Q$4,d_Cuisine,$R$4,d_Pay,$S$4,d_Type,$T$4),0) -> 4.1836735 | K68: =IFERROR(AVERAGEIFS(d_Time,d_Rest,$B68,d_Status,"Delivered",d_Year,$P$4,d_City,$Q$4,d_Cuisine,$R$4,d_Pay,$S$4,d_Type,$T$4),0) -> 43.5 | L68: =RANK(G68,$G$61:$G$72) -> 11
B69: The Food Corner | C69: =COUNTIFS(d_Rest,$B69,d_Year,$P$4,d_City,$Q$4,d_Cuisine,$R$4,d_Pay,$S$4,d_Type,$T$4) -> 97 | D69: =COUNTIFS(d_Rest,$B69,d_Status,"Delivered",d_Year,$P$4,d_City,$Q$4,d_Cuisine,$R$4,d_Pay,$S$4,d_Type,$T$4) -> 62 | E69: =COUNTIFS(d_Rest,$B69,d_Status,"Cancelled",d_Year,$P$4,d_City,$Q$4,d_Cuisine,$R$4,d_Pay,$S$4,d_Type,$T$4) -> 21 | F69: =IFERROR(E69/C69,0) -> 0.21649485 | G69: =SUMIFS(d_Net,d_Rest,$B69,d_Status,"Delivered",d_Year,$P$4,d_City,$Q$4,d_Cuisine,$R$4,d_Pay,$S$4,d_Type,$T$4) -> 56948 | H69: =IFERROR(AVERAGEIFS(d_OV,d_Rest,$B69,d_Year,$P$4,d_City,$Q$4,d_Cuisine,$R$4,d_Pay,$S$4,d_Type,$T$4),0) -> 957.08247 | I69: =IFERROR(AVERAGEIFS(d_RRating,d_Rest,$B69,d_Year,$P$4,d_City,$Q$4,d_Cuisine,$R$4,d_Pay,$S$4,d_Type,$T$4),0) -> 3.7618557 | J69: =IFERROR(AVERAGEIFS(d_CRating,d_Rest,$B69,d_Year,$P$4,d_City,$Q$4,d_Cuisine,$R$4,d_Pay,$S$4,d_Type,$T$4),0) -> 3.8556701 | K69: =IFERROR(AVERAGEIFS(d_Time,d_Rest,$B69,d_Status,"Delivered",d_Year,$P$4,d_City,$Q$4,d_Cuisine,$R$4,d_Pay,$S$4,d_Type,$T$4),0) -> 41.548387 | L69: =RANK(G69,$G$61:$G$72) -> 8
B70: Royal Biryani | C70: =COUNTIFS(d_Rest,$B70,d_Year,$P$4,d_City,$Q$4,d_Cuisine,$R$4,d_Pay,$S$4,d_Type,$T$4) -> 93 | D70: =COUNTIFS(d_Rest,$B70,d_Status,"Delivered",d_Year,$P$4,d_City,$Q$4,d_Cuisine,$R$4,d_Pay,$S$4,d_Type,$T$4) -> 54 | E70: =COUNTIFS(d_Rest,$B70,d_Status,"Cancelled",d_Year,$P$4,d_City,$Q$4,d_Cuisine,$R$4,d_Pay,$S$4,d_Type,$T$4) -> 15 | F70: =IFERROR(E70/C70,0) -> 0.16129032 | G70: =SUMIFS(d_Net,d_Rest,$B70,d_Status,"Delivered",d_Year,$P$4,d_City,$Q$4,d_Cuisine,$R$4,d_Pay,$S$4,d_Type,$T$4) -> 42448 | H70: =IFERROR(AVERAGEIFS(d_OV,d_Rest,$B70,d_Year,$P$4,d_City,$Q$4,d_Cuisine,$R$4,d_Pay,$S$4,d_Type,$T$4),0) -> 863.54839 | I70: =IFERROR(AVERAGEIFS(d_RRating,d_Rest,$B70,d_Year,$P$4,d_City,$Q$4,d_Cuisine,$R$4,d_Pay,$S$4,d_Type,$T$4),0) -> 3.7215054 | J70: =IFERROR(AVERAGEIFS(d_CRating,d_Rest,$B70,d_Year,$P$4,d_City,$Q$4,d_Cuisine,$R$4,d_Pay,$S$4,d_Type,$T$4),0) -> 4.0215054 | K70: =IFERROR(AVERAGEIFS(d_Time,d_Rest,$B70,d_Status,"Delivered",d_Year,$P$4,d_City,$Q$4,d_Cuisine,$R$4,d_Pay,$S$4,d_Type,$T$4),0) -> 40.481481 | L70: =RANK(G70,$G$61:$G$72) -> 12
B71: Food Street | C71: =COUNTIFS(d_Rest,$B71,d_Year,$P$4,d_City,$Q$4,d_Cuisine,$R$4,d_Pay,$S$4,d_Type,$T$4) -> 93 | D71: =COUNTIFS(d_Rest,$B71,d_Status,"Delivered",d_Year,$P$4,d_City,$Q$4,d_Cuisine,$R$4,d_Pay,$S$4,d_Type,$T$4) -> 57 | E71: =COUNTIFS(d_Rest,$B71,d_Status,"Cancelled",d_Year,$P$4,d_City,$Q$4,d_Cuisine,$R$4,d_Pay,$S$4,d_Type,$T$4) -> 22 | F71: =IFERROR(E71/C71,0) -> 0.23655914 | G71: =SUMIFS(d_Net,d_Rest,$B71,d_Status,"Delivered",d_Year,$P$4,d_City,$Q$4,d_Cuisine,$R$4,d_Pay,$S$4,d_Type,$T$4) -> 54955 | H71: =IFERROR(AVERAGEIFS(d_OV,d_Rest,$B71,d_Year,$P$4,d_City,$Q$4,d_Cuisine,$R$4,d_Pay,$S$4,d_Type,$T$4),0) -> 989.1828 | I71: =IFERROR(AVERAGEIFS(d_RRating,d_Rest,$B71,d_Year,$P$4,d_City,$Q$4,d_Cuisine,$R$4,d_Pay,$S$4,d_Type,$T$4),0) -> 3.6021505 | J71: =IFERROR(AVERAGEIFS(d_CRating,d_Rest,$B71,d_Year,$P$4,d_City,$Q$4,d_Cuisine,$R$4,d_Pay,$S$4,d_Type,$T$4),0) -> 3.9677419 | K71: =IFERROR(AVERAGEIFS(d_Time,d_Rest,$B71,d_Status,"Delivered",d_Year,$P$4,d_City,$Q$4,d_Cuisine,$R$4,d_Pay,$S$4,d_Type,$T$4),0) -> 39.877193 | L71: =RANK(G71,$G$61:$G$72) -> 10
B72: Momo Nation | C72: =COUNTIFS(d_Rest,$B72,d_Year,$P$4,d_City,$Q$4,d_Cuisine,$R$4,d_Pay,$S$4,d_Type,$T$4) -> 89 | D72: =COUNTIFS(d_Rest,$B72,d_Status,"Delivered",d_Year,$P$4,d_City,$Q$4,d_Cuisine,$R$4,d_Pay,$S$4,d_Type,$T$4) -> 57 | E72: =COUNTIFS(d_Rest,$B72,d_Status,"Cancelled",d_Year,$P$4,d_City,$Q$4,d_Cuisine,$R$4,d_Pay,$S$4,d_Type,$T$4) -> 14 | F72: =IFERROR(E72/C72,0) -> 0.15730337 | G72: =SUMIFS(d_Net,d_Rest,$B72,d_Status,"Delivered",d_Year,$P$4,d_City,$Q$4,d_Cuisine,$R$4,d_Pay,$S$4,d_Type,$T$4) -> 57330 | H72: =IFERROR(AVERAGEIFS(d_OV,d_Rest,$B72,d_Year,$P$4,d_City,$Q$4,d_Cuisine,$R$4,d_Pay,$S$4,d_Type,$T$4),0) -> 999.96629 | I72: =IFERROR(AVERAGEIFS(d_RRating,d_Rest,$B72,d_Year,$P$4,d_City,$Q$4,d_Cuisine,$R$4,d_Pay,$S$4,d_Type,$T$4),0) -> 3.6561798 | J72: =IFERROR(AVERAGEIFS(d_CRating,d_Rest,$B72,d_Year,$P$4,d_City,$Q$4,d_Cuisine,$R$4,d_Pay,$S$4,d_Type,$T$4),0) -> 4.0337079 | K72: =IFERROR(AVERAGEIFS(d_Time,d_Rest,$B72,d_Status,"Delivered",d_Year,$P$4,d_City,$Q$4,d_Cuisine,$R$4,d_Pay,$S$4,d_Type,$T$4),0) -> 40.631579 | L72: =RANK(G72,$G$61:$G$72) -> 7
B73: Total / Overall | C73: =SUM(C61:C72) -> 1200 | D73: =SUM(D61:D72) -> 791 | E73: =SUM(E61:E72) -> 202 | F73: =IFERROR(E73/C73,0) -> 0.16833333 | G73: =SUM(G61:G72) -> 699950 | H73: =AVERAGEIFS(d_OV,d_ID,"<>",d_Year,$P$4,d_City,$Q$4,d_Cuisine,$R$4,d_Pay,$S$4,d_Type,$T$4) -> 931.2875 | I73: =AVERAGEIFS(d_RRating,d_ID,"<>",d_Year,$P$4,d_City,$Q$4,d_Cuisine,$R$4,d_Pay,$S$4,d_Type,$T$4) -> 3.7175 | J73: =AVERAGEIFS(d_CRating,d_ID,"<>",d_Year,$P$4,d_City,$Q$4,d_Cuisine,$R$4,d_Pay,$S$4,d_Type,$T$4) -> 4.0183333 | K73: =IFERROR(AVERAGEIFS(d_Time,d_Status,"Delivered",d_Year,$P$4,d_City,$Q$4,d_Cuisine,$R$4,d_Pay,$S$4,d_Type,$T$4),0) -> 41.530973

Sheet Customer Analytics
B2: Customer Analytics
B3: Who orders, how often and how much. Customer-level metrics come from the Customers helper sheet. ▸ Use the yellow filters in row 4 – every KPI, chart and table updates. | L3: ← Back to Home
B4: Year: | C4: All | D4: City: | E4: All | F4: Cuisine: | G4: All | H4: Payment: | I4: All | J4: Order type: | K4: All | L4: ="Orders in view: "&TEXT(COUNTIFS(d_ID,"<>",d_Year,$P$4,d_City,$Q$4,d_Cuisine,$R$4,d_Pay,$S$4,d_Type,$T$4),"#,##0") -> Orders in view: 1,200 | P4: =IF(C4="All",">0",C4) -> >0 | Q4: =IF(E4="All","*",E4) -> * | R4: =IF(G4="All","*",G4) -> * | S4: =IF(I4="All","*",I4) -> * | T4: =IF(K4="All","*",K4) -> *
B5: UNIQUE CUSTOMERS | D5: REPEAT CUSTOMERS | F5: REPEAT RATE | H5: ORDERS / CUSTOMER | J5: AVG CUSTOMER AGE | L5: AVG SPEND / CUSTOMER
B6: =COUNTIF(Customers!$B$2:$B$351,">0") -> 350 | D6: =COUNTIF(Customers!$B$2:$B$351,">1") -> 350 | F6: =IFERROR(COUNTIF(Customers!$B$2:$B$351,">1")/COUNTIF(Customers!$B$2:$B$351,">0"),0) -> 1 | H6: =IFERROR(COUNTIFS(d_ID,"<>",d_Year,$P$4,d_City,$Q$4,d_Cuisine,$R$4,d_Pay,$S$4,d_Type,$T$4)/COUNTIF(Customers!$B$2:$B$351,">0"),0) -> 3.4285714 | J6: =AVERAGEIFS(d_Age,d_ID,"<>",d_Year,$P$4,d_City,$Q$4,d_Cuisine,$R$4,d_Pay,$S$4,d_Type,$T$4) -> 39.025 | L6: =IFERROR(SUM(Customers!$D$2:$D$351)/COUNTIF(Customers!$B$2:$B$351,">0"),0) -> 1999.8571
B7: Distinct Customer_IDs | D7: Ordered 2+ times | F7: Repeat ÷ unique | H7: Average frequency | J7: Years | L7: Net spend, delivered
B57: Supporting data (feeds the charts above)
B59: Age-group analysis
B60: Age group | C60: Min age | D60: Max age | E60: Orders | F60: Delivered | G60: Net revenue | H60: Avg order value | I60: Avg rating given
B61: 18–24 | C61: 18 | D61: 24 | E61: =COUNTIFS(d_Age,">="&$C61,d_Age,"<="&$D61,d_Year,$P$4,d_City,$Q$4,d_Cuisine,$R$4,d_Pay,$S$4,d_Type,$T$4) -> 186 | F61: =COUNTIFS(d_Age,">="&$C61,d_Age,"<="&$D61,d_Status,"Delivered",d_Year,$P$4,d_City,$Q$4,d_Cuisine,$R$4,d_Pay,$S$4,d_Type,$T$4) -> 130 | G61: =SUMIFS(d_Net,d_Age,">="&$C61,d_Age,"<="&$D61,d_Status,"Delivered",d_Year,$P$4,d_City,$Q$4,d_Cuisine,$R$4,d_Pay,$S$4,d_Type,$T$4) -> 105420 | H61: =IFERROR(AVERAGEIFS(d_OV,d_Age,">="&$C61,d_Age,"<="&$D61,d_Year,$P$4,d_City,$Q$4,d_Cuisine,$R$4,d_Pay,$S$4,d_Type,$T$4),0) -> 856.63978 | I61: =IFERROR(AVERAGEIFS(d_CRating,d_Age,">="&$C61,d_Age,"<="&$D61,d_Year,$P$4,d_City,$Q$4,d_Cuisine,$R$4,d_Pay,$S$4,d_Type,$T$4),0) -> 4.0537634
B62: 25–34 | C62: 25 | D62: 34 | E62: =COUNTIFS(d_Age,">="&$C62,d_Age,"<="&$D62,d_Year,$P$4,d_City,$Q$4,d_Cuisine,$R$4,d_Pay,$S$4,d_Type,$T$4) -> 285 | F62: =COUNTIFS(d_Age,">="&$C62,d_Age,"<="&$D62,d_Status,"Delivered",d_Year,$P$4,d_City,$Q$4,d_Cuisine,$R$4,d_Pay,$S$4,d_Type,$T$4) -> 181 | G62: =SUMIFS(d_Net,d_Age,">="&$C62,d_Age,"<="&$D62,d_Status,"Delivered",d_Year,$P$4,d_City,$Q$4,d_Cuisine,$R$4,d_Pay,$S$4,d_Type,$T$4) -> 160352 | H62: =IFERROR(AVERAGEIFS(d_OV,d_Age,">="&$C62,d_Age,"<="&$D62,d_Year,$P$4,d_City,$Q$4,d_Cuisine,$R$4,d_Pay,$S$4,d_Type,$T$4),0) -> 947.44211 | I62: =IFERROR(AVERAGEIFS(d_CRating,d_Age,">="&$C62,d_Age,"<="&$D62,d_Year,$P$4,d_City,$Q$4,d_Cuisine,$R$4,d_Pay,$S$4,d_Type,$T$4),0) -> 3.9438596
B63: 35–44 | C63: 35 | D63: 44 | E63: =COUNTIFS(d_Age,">="&$C63,d_Age,"<="&$D63,d_Year,$P$4,d_City,$Q$4,d_Cuisine,$R$4,d_Pay,$S$4,d_Type,$T$4) -> 279 | F63: =COUNTIFS(d_Age,">="&$C63,d_Age,"<="&$D63,d_Status,"Delivered",d_Year,$P$4,d_City,$Q$4,d_Cuisine,$R$4,d_Pay,$S$4,d_Type,$T$4) -> 180 | G63: =SUMIFS(d_Net,d_Age,">="&$C63,d_Age,"<="&$D63,d_Status,"Delivered",d_Year,$P$4,d_City,$Q$4,d_Cuisine,$R$4,d_Pay,$S$4,d_Type,$T$4) -> 167235 | H63: =IFERROR(AVERAGEIFS(d_OV,d_Age,">="&$C63,d_Age,"<="&$D63,d_Year,$P$4,d_City,$Q$4,d_Cuisine,$R$4,d_Pay,$S$4,d_Type,$T$4),0) -> 983.70968 | I63: =IFERROR(AVERAGEIFS(d_CRating,d_Age,">="&$C63,d_Age,"<="&$D63,d_Year,$P$4,d_City,$Q$4,d_Cuisine,$R$4,d_Pay,$S$4,d_Type,$T$4),0) -> 3.9318996
B64: 45–54 | C64: 45 | D64: 54 | E64: =COUNTIFS(d_Age,">="&$C64,d_Age,"<="&$D64,d_Year,$P$4,d_City,$Q$4,d_Cuisine,$R$4,d_Pay,$S$4,d_Type,$T$4) -> 294 | F64: =COUNTIFS(d_Age,">="&$C64,d_Age,"<="&$D64,d_Status,"Delivered",d_Year,$P$4,d_City,$Q$4,d_Cuisine,$R$4,d_Pay,$S$4,d_Type,$T$4) -> 197 | G64: =SUMIFS(d_Net,d_Age,">="&$C64,d_Age,"<="&$D64,d_Status,"Delivered",d_Year,$P$4,d_City,$Q$4,d_Cuisine,$R$4,d_Pay,$S$4,d_Type,$T$4) -> 173287 | H64: =IFERROR(AVERAGEIFS(d_OV,d_Age,">="&$C64,d_Age,"<="&$D64,d_Year,$P$4,d_City,$Q$4,d_Cuisine,$R$4,d_Pay,$S$4,d_Type,$T$4),0) -> 902.56463 | I64: =IFERROR(AVERAGEIFS(d_CRating,d_Age,">="&$C64,d_Age,"<="&$D64,d_Year,$P$4,d_City,$Q$4,d_Cuisine,$R$4,d_Pay,$S$4,d_Type,$T$4),0) -> 4.0816327
B65: 55–60 | C65: 55 | D65: 60 | E65: =COUNTIFS(d_Age,">="&$C65,d_Age,"<="&$D65,d_Year,$P$4,d_City,$Q$4,d_Cuisine,$R$4,d_Pay,$S$4,d_Type,$T$4) -> 156 | F65: =COUNTIFS(d_Age,">="&$C65,d_Age,"<="&$D65,d_Status,"Delivered",d_Year,$P$4,d_City,$Q$4,d_Cuisine,$R$4,d_Pay,$S$4,d_Type,$T$4) -> 103 | G65: =SUMIFS(d_Net,d_Age,">="&$C65,d_Age,"<="&$D65,d_Status,"Delivered",d_Year,$P$4,d_City,$Q$4,d_Cuisine,$R$4,d_Pay,$S$4,d_Type,$T$4) -> 93656 | H65: =IFERROR(AVERAGEIFS(d_OV,d_Age,">="&$C65,d_Age,"<="&$D65,d_Year,$P$4,d_City,$Q$4,d_Cuisine,$R$4,d_Pay,$S$4,d_Type,$T$4),0) -> 951.15385 | I65: =IFERROR(AVERAGEIFS(d_CRating,d_Age,">="&$C65,d_Age,"<="&$D65,d_Year,$P$4,d_City,$Q$4,d_Cuisine,$R$4,d_Pay,$S$4,d_Type,$T$4),0) -> 4.1474359
B66: Total / Overall | E66: =SUM(E61:E65) -> 1200 | F66: =SUM(F61:F65) -> 791 | G66: =SUM(G61:G65) -> 699950 | H66: =AVERAGEIFS(d_OV,d_ID,"<>",d_Year,$P$4,d_City,$Q$4,d_Cuisine,$R$4,d_Pay,$S$4,d_Type,$T$4) -> 931.2875 | I66: =AVERAGEIFS(d_CRating,d_ID,"<>",d_Year,$P$4,d_City,$Q$4,d_Cuisine,$R$4,d_Pay,$S$4,d_Type,$T$4) -> 4.0183333
B67: Age bounds are inputs (blue) – edit to re-band.
B70: Gender split
B71: Gender | C71: Orders | D71: % of orders | E71: Avg order value
B72: Female | C72: =COUNTIFS(d_Gender,$B72,d_Year,$P$4,d_City,$Q$4,d_Cuisine,$R$4,d_Pay,$S$4,d_Type,$T$4) -> 589 | D72: =IFERROR(C72/COUNTIFS(d_ID,"<>",d_Year,$P$4,d_City,$Q$4,d_Cuisine,$R$4,d_Pay,$S$4,d_Type,$T$4),0) -> 0.49083333 | E72: =IFERROR(AVERAGEIFS(d_OV,d_Gender,$B72,d_Year,$P$4,d_City,$Q$4,d_Cuisine,$R$4,d_Pay,$S$4,d_Type,$T$4),0) -> 928.77759
B73: Male | C73: =COUNTIFS(d_Gender,$B73,d_Year,$P$4,d_City,$Q$4,d_Cuisine,$R$4,d_Pay,$S$4,d_Type,$T$4) -> 576 | D73: =IFERROR(C73/COUNTIFS(d_ID,"<>",d_Year,$P$4,d_City,$Q$4,d_Cuisine,$R$4,d_Pay,$S$4,d_Type,$T$4),0) -> 0.48 | E73: =IFERROR(AVERAGEIFS(d_OV,d_Gender,$B73,d_Year,$P$4,d_City,$Q$4,d_Cuisine,$R$4,d_Pay,$S$4,d_Type,$T$4),0) -> 929.30035
B74: Other | C74: =COUNTIFS(d_Gender,$B74,d_Year,$P$4,d_City,$Q$4,d_Cuisine,$R$4,d_Pay,$S$4,d_Type,$T$4) -> 35 | D74: =IFERROR(C74/COUNTIFS(d_ID,"<>",d_Year,$P$4,d_City,$Q$4,d_Cuisine,$R$4,d_Pay,$S$4,d_Type,$T$4),0) -> 0.029166667 | E74: =IFERROR(AVERAGEIFS(d_OV,d_Gender,$B74,d_Year,$P$4,d_City,$Q$4,d_Cuisine,$R$4,d_Pay,$S$4,d_Type,$T$4),0) -> 1006.2286
B75: Total / Overall | C75: =SUM(C72:C74) -> 1200 | D75: =SUM(D72:D74) -> 1 | E75: =AVERAGEIFS(d_OV,d_ID,"<>",d_Year,$P$4,d_City,$Q$4,d_Cuisine,$R$4,d_Pay,$S$4,d_Type,$T$4) -> 931.2875
B78: Order-frequency distribution
B79: Orders per customer | C79: Customers | D79: % of customers
B80: 1 order | C80: =COUNTIF(Customers!$B$2:$B$351,1) -> 0 | D80: =IFERROR(C80/COUNTIF(Customers!$B$2:$B$351,">0"),0) -> 0
B81: 2 orders | C81: =COUNTIF(Customers!$B$2:$B$351,2) -> 0 | D81: =IFERROR(C81/COUNTIF(Customers!$B$2:$B$351,">0"),0) -> 0
B82: 3 orders | C82: =COUNTIF(Customers!$B$2:$B$351,3) -> 200 | D82: =IFERROR(C82/COUNTIF(Customers!$B$2:$B$351,">0"),0) -> 0.57142857
B83: 4 orders | C83: =COUNTIF(Customers!$B$2:$B$351,4) -> 150 | D83: =IFERROR(C83/COUNTIF(Customers!$B$2:$B$351,">0"),0) -> 0.42857143
B84: 5 orders | C84: =COUNTIF(Customers!$B$2:$B$351,5) -> 0 | D84: =IFERROR(C84/COUNTIF(Customers!$B$2:$B$351,">0"),0) -> 0
B85: 6+ orders | C85: =COUNTIF(Customers!$B$2:$B$351,">=6") -> 0 | D85: =IFERROR(C85/COUNTIF(Customers!$B$2:$B$351,">0"),0) -> 0
B86: Total / Overall | C86: =SUM(C80:C85) -> 350 | D86: =SUM(D80:D85) -> 1
B89: Top 10 customers by net spend
B90: Rank | C90: Customer ID | D90: Orders | E90: Net spend | F90: Avg rating given
B91: 1 | C91: =INDEX(Customers!$A$2:$A$351,MATCH($B91,Customers!$G$2:$G$351,0)) -> C1052 | D91: =INDEX(Customers!$B$2:$B$351,MATCH($B91,Customers!$G$2:$G$351,0)) -> 4 | E91: =INDEX(Customers!$D$2:$D$351,MATCH($B91,Customers!$G$2:$G$351,0)) -> 5485 | F91: =INDEX(Customers!$E$2:$E$351,MATCH($B91,Customers!$G$2:$G$351,0)) -> 4.25
B92: 2 | C92: =INDEX(Customers!$A$2:$A$351,MATCH($B92,Customers!$G$2:$G$351,0)) -> C1075 | D92: =INDEX(Customers!$B$2:$B$351,MATCH($B92,Customers!$G$2:$G$351,0)) -> 4 | E92: =INDEX(Customers!$D$2:$D$351,MATCH($B92,Customers!$G$2:$G$351,0)) -> 4940 | F92: =INDEX(Customers!$E$2:$E$351,MATCH($B92,Customers!$G$2:$G$351,0)) -> 4.5
B93: 3 | C93: =INDEX(Customers!$A$2:$A$351,MATCH($B93,Customers!$G$2:$G$351,0)) -> C1235 | D93: =INDEX(Customers!$B$2:$B$351,MATCH($B93,Customers!$G$2:$G$351,0)) -> 3 | E93: =INDEX(Customers!$D$2:$D$351,MATCH($B93,Customers!$G$2:$G$351,0)) -> 4806 | F93: =INDEX(Customers!$E$2:$E$351,MATCH($B93,Customers!$G$2:$G$351,0)) -> 3.6666667
B94: 4 | C94: =INDEX(Customers!$A$2:$A$351,MATCH($B94,Customers!$G$2:$G$351,0)) -> C1025 | D94: =INDEX(Customers!$B$2:$B$351,MATCH($B94,Customers!$G$2:$G$351,0)) -> 4 | E94: =INDEX(Customers!$D$2:$D$351,MATCH($B94,Customers!$G$2:$G$351,0)) -> 4768 | F94: =INDEX(Customers!$E$2:$E$351,MATCH($B94,Customers!$G$2:$G$351,0)) -> 4
B95: 5 | C95: =INDEX(Customers!$A$2:$A$351,MATCH($B95,Customers!$G$2:$G$351,0)) -> C1053 | D95: =INDEX(Customers!$B$2:$B$351,MATCH($B95,Customers!$G$2:$G$351,0)) -> 4 | E95: =INDEX(Customers!$D$2:$D$351,MATCH($B95,Customers!$G$2:$G$351,0)) -> 4682 | F95: =INDEX(Customers!$E$2:$E$351,MATCH($B95,Customers!$G$2:$G$351,0)) -> 4.5
B96: 6 | C96: =INDEX(Customers!$A$2:$A$351,MATCH($B96,Customers!$G$2:$G$351,0)) -> C1126 | D96: =INDEX(Customers!$B$2:$B$351,MATCH($B96,Customers!$G$2:$G$351,0)) -> 4 | E96: =INDEX(Customers!$D$2:$D$351,MATCH($B96,Customers!$G$2:$G$351,0)) -> 4548 | F96: =INDEX(Customers!$E$2:$E$351,MATCH($B96,Customers!$G$2:$G$351,0)) -> 4.5
B97: 7 | C97: =INDEX(Customers!$A$2:$A$351,MATCH($B97,Customers!$G$2:$G$351,0)) -> C1111 | D97: =INDEX(Customers!$B$2:$B$351,MATCH($B97,Customers!$G$2:$G$351,0)) -> 4 | E97: =INDEX(Customers!$D$2:$D$351,MATCH($B97,Customers!$G$2:$G$351,0)) -> 4505 | F97: =INDEX(Customers!$E$2:$E$351,MATCH($B97,Customers!$G$2:$G$351,0)) -> 5
B98: 8 | C98: =INDEX(Customers!$A$2:$A$351,MATCH($B98,Customers!$G$2:$G$351,0)) -> C1150 | D98: =INDEX(Customers!$B$2:$B$351,MATCH($B98,Customers!$G$2:$G$351,0)) -> 4 | E98: =INDEX(Customers!$D$2:$D$351,MATCH($B98,Customers!$G$2:$G$351,0)) -> 4235 | F98: =INDEX(Customers!$E$2:$E$351,MATCH($B98,Customers!$G$2:$G$351,0)) -> 4.25
B99: 9 | C99: =INDEX(Customers!$A$2:$A$351,MATCH($B99,Customers!$G$2:$G$351,0)) -> C1032 | D99: =INDEX(Customers!$B$2:$B$351,MATCH($B99,Customers!$G$2:$G$351,0)) -> 4 | E99: =INDEX(Customers!$D$2:$D$351,MATCH($B99,Customers!$G$2:$G$351,0)) -> 3938 | F99: =INDEX(Customers!$E$2:$E$351,MATCH($B99,Customers!$G$2:$G$351,0)) -> 3.75
B100: 10 | C100: =INDEX(Customers!$A$2:$A$351,MATCH($B100,Customers!$G$2:$G$351,0)) -> C1092 | D100: =INDEX(Customers!$B$2:$B$351,MATCH($B100,Customers!$G$2:$G$351,0)) -> 4 | E100: =INDEX(Customers!$D$2:$D$351,MATCH($B100,Customers!$G$2:$G$351,0)) -> 3894 | F100: =INDEX(Customers!$E$2:$E$351,MATCH($B100,Customers!$G$2:$G$351,0)) -> 4.75
B103: Customers by city (orders)
B104: City | C104: Orders | D104: Avg order value | E104: Avg rating given
B105: Delhi | C105: =COUNTIFS(d_City,$B105,d_Year,$P$4,d_City,$Q$4,d_Cuisine,$R$4,d_Pay,$S$4,d_Type,$T$4) -> 119 | D105: =IFERROR(AVERAGEIFS(d_OV,d_City,$B105,d_Year,$P$4,d_City,$Q$4,d_Cuisine,$R$4,d_Pay,$S$4,d_Type,$T$4),0) -> 943.82353 | E105: =IFERROR(AVERAGEIFS(d_CRating,d_City,$B105,d_Year,$P$4,d_City,$Q$4,d_Cuisine,$R$4,d_Pay,$S$4,d_Type,$T$4),0) -> 4.1344538
B106: Ahmedabad | C106: =COUNTIFS(d_City,$B106,d_Year,$P$4,d_City,$Q$4,d_Cuisine,$R$4,d_Pay,$S$4,d_Type,$T$4) -> 114 | D106: =IFERROR(AVERAGEIFS(d_OV,d_City,$B106,d_Year,$P$4,d_City,$Q$4,d_Cuisine,$R$4,d_Pay,$S$4,d_Type,$T$4),0) -> 868.15789 | E106: =IFERROR(AVERAGEIFS(d_CRating,d_City,$B106,d_Year,$P$4,d_City,$Q$4,d_Cuisine,$R$4,d_Pay,$S$4,d_Type,$T$4),0) -> 3.9912281
B107: Bengaluru | C107: =COUNTIFS(d_City,$B107,d_Year,$P$4,d_City,$Q$4,d_Cuisine,$R$4,d_Pay,$S$4,d_Type,$T$4) -> 110 | D107: =IFERROR(AVERAGEIFS(d_OV,d_City,$B107,d_Year,$P$4,d_City,$Q$4,d_Cuisine,$R$4,d_Pay,$S$4,d_Type,$T$4),0) -> 967.17273 | E107: =IFERROR(AVERAGEIFS(d_CRating,d_City,$B107,d_Year,$P$4,d_City,$Q$4,d_Cuisine,$R$4,d_Pay,$S$4,d_Type,$T$4),0) -> 4.1090909
B108: Chennai | C108: =COUNTIFS(d_City,$B108,d_Year,$P$4,d_City,$Q$4,d_Cuisine,$R$4,d_Pay,$S$4,d_Type,$T$4) -> 108 | D108: =IFERROR(AVERAGEIFS(d_OV,d_City,$B108,d_Year,$P$4,d_City,$Q$4,d_Cuisine,$R$4,d_Pay,$S$4,d_Type,$T$4),0) -> 942.82407 | E108: =IFERROR(AVERAGEIFS(d_CRating,d_City,$B108,d_Year,$P$4,d_City,$Q$4,d_Cuisine,$R$4,d_Pay,$S$4,d_Type,$T$4),0) -> 4
B109: Noida | C109: =COUNTIFS(d_City,$B109,d_Year,$P$4,d_City,$Q$4,d_Cuisine,$R$4,d_Pay,$S$4,d_Type,$T$4) -> 107 | D109: =IFERROR(AVERAGEIFS(d_OV,d_City,$B109,d_Year,$P$4,d_City,$Q$4,d_Cuisine,$R$4,d_Pay,$S$4,d_Type,$T$4),0) -> 961.84112 | E109: =IFERROR(AVERAGEIFS(d_CRating,d_City,$B109,d_Year,$P$4,d_City,$Q$4,d_Cuisine,$R$4,d_Pay,$S$4,d_Type,$T$4),0) -> 3.9439252
B110: Jaipur | C110: =COUNTIFS(d_City,$B110,d_Year,$P$4,d_City,$Q$4,d_Cuisine,$R$4,d_Pay,$S$4,d_Type,$T$4) -> 102 | D110: =IFERROR(AVERAGEIFS(d_OV,d_City,$B110,d_Year,$P$4,d_City,$Q$4,d_Cuisine,$R$4,d_Pay,$S$4,d_Type,$T$4),0) -> 839.84314 | E110: =IFERROR(AVERAGEIFS(d_CRating,d_City,$B110,d_Year,$P$4,d_City,$Q$4,d_Cuisine,$R$4,d_Pay,$S$4,d_Type,$T$4),0) -> 4
B111: Hyderabad | C111: =COUNTIFS(d_City,$B111,d_Year,$P$4,d_City,$Q$4,d_Cuisine,$R$4,d_Pay,$S$4,d_Type,$T$4) -> 96 | D111: =IFERROR(AVERAGEIFS(d_OV,d_City,$B111,d_Year,$P$4,d_City,$Q$4,d_Cuisine,$R$4,d_Pay,$S$4,d_Type,$T$4),0) -> 965.42708 | E111: =IFERROR(AVERAGEIFS(d_CRating,d_City,$B111,d_Year,$P$4,d_City,$Q$4,d_Cuisine,$R$4,d_Pay,$S$4,d_Type,$T$4),0) -> 4.03125
B112: Pune | C112: =COUNTIFS(d_City,$B112,d_Year,$P$4,d_City,$Q$4,d_Cuisine,$R$4,d_Pay,$S$4,d_Type,$T$4) -> 96 | D112: =IFERROR(AVERAGEIFS(d_OV,d_City,$B112,d_Year,$P$4,d_City,$Q$4,d_Cuisine,$R$4,d_Pay,$S$4,d_Type,$T$4),0) -> 929.5625 | E112: =IFERROR(AVERAGEIFS(d_CRating,d_City,$B112,d_Year,$P$4,d_City,$Q$4,d_Cuisine,$R$4,d_Pay,$S$4,d_Type,$T$4),0) -> 4.1979167
B113: Kolkata | C113: =COUNTIFS(d_City,$B113,d_Year,$P$4,d_City,$Q$4,d_Cuisine,$R$4,d_Pay,$S$4,d_Type,$T$4) -> 94 | D113: =IFERROR(AVERAGEIFS(d_OV,d_City,$B113,d_Year,$P$4,d_City,$Q$4,d_Cuisine,$R$4,d_Pay,$S$4,d_Type,$T$4),0) -> 891.73404 | E113: =IFERROR(AVERAGEIFS(d_CRating,d_City,$B113,d_Year,$P$4,d_City,$Q$4,d_Cuisine,$R$4,d_Pay,$S$4,d_Type,$T$4),0) -> 4.0531915
B114: Lucknow | C114: =COUNTIFS(d_City,$B114,d_Year,$P$4,d_City,$Q$4,d_Cuisine,$R$4,d_Pay,$S$4,d_Type,$T$4) -> 91 | D114: =IFERROR(AVERAGEIFS(d_OV,d_City,$B114,d_Year,$P$4,d_City,$Q$4,d_Cuisine,$R$4,d_Pay,$S$4,d_Type,$T$4),0) -> 991.30769 | E114: =IFERROR(AVERAGEIFS(d_CRating,d_City,$B114,d_Year,$P$4,d_City,$Q$4,d_Cuisine,$R$4,d_Pay,$S$4,d_Type,$T$4),0) -> 3.9120879
B115: Mumbai | C115: =COUNTIFS(d_City,$B115,d_Year,$P$4,d_City,$Q$4,d_Cuisine,$R$4,d_Pay,$S$4,d_Type,$T$4) -> 83 | D115: =IFERROR(AVERAGEIFS(d_OV,d_City,$B115,d_Year,$P$4,d_City,$Q$4,d_Cuisine,$R$4,d_Pay,$S$4,d_Type,$T$4),0) -> 891.86747 | E115: =IFERROR(AVERAGEIFS(d_CRating,d_City,$B115,d_Year,$P$4,d_City,$Q$4,d_Cuisine,$R$4,d_Pay,$S$4,d_Type,$T$4),0) -> 3.939759
B116: Gurugram | C116: =COUNTIFS(d_City,$B116,d_Year,$P$4,d_City,$Q$4,d_Cuisine,$R$4,d_Pay,$S$4,d_Type,$T$4) -> 80 | D116: =IFERROR(AVERAGEIFS(d_OV,d_City,$B116,d_Year,$P$4,d_City,$Q$4,d_Cuisine,$R$4,d_Pay,$S$4,d_Type,$T$4),0) -> 993.6125 | E116: =IFERROR(AVERAGEIFS(d_CRating,d_City,$B116,d_Year,$P$4,d_City,$Q$4,d_Cuisine,$R$4,d_Pay,$S$4,d_Type,$T$4),0) -> 3.8375

Sheet Delivery Partner Analytics
B2: Delivery Partner Analytics
B3: The data has no delivery-partner ID, so this view analyses the delivery fleet (Order_Type = Delivery) by city, distance and status. Add a Partner_ID column to unlock per-partner scorecards. ▸ Use the yellow filters in row 4 – every KPI, chart and table updates. | L3: ← Back to Home
B4: Year: | C4: All | D4: City: | E4: All | F4: Cuisine: | G4: All | H4: Payment: | I4: All | J4: Order type: | K4: All | L4: ="Orders in view: "&TEXT(COUNTIFS(d_ID,"<>",d_Year,$P$4,d_City,$Q$4,d_Cuisine,$R$4,d_Pay,$S$4,d_Type,$T$4),"#,##0") -> Orders in view: 1,200 | P4: =IF(C4="All",">0",C4) -> >0 | Q4: =IF(E4="All","*",E4) -> * | R4: =IF(G4="All","*",G4) -> * | S4: =IF(I4="All","*",I4) -> * | T4: =IF(K4="All","*",K4) -> *
B5: DELIVERY ORDERS | D5: DELIVERED | F5: SUCCESS RATE | H5: AVG DELIVERY TIME | J5: AVG DISTANCE | L5: DELIVERY FEES EARNED
B6: =COUNTIFS(d_Type,"Delivery",d_Year,$P$4,d_City,$Q$4,d_Cuisine,$R$4,d_Pay,$S$4,d_Type,$T$4) -> 881 | D6: =COUNTIFS(d_Type,"Delivery",d_Status,"Delivered",d_Year,$P$4,d_City,$Q$4,d_Cuisine,$R$4,d_Pay,$S$4,d_Type,$T$4) -> 592 | F6: =IFERROR(COUNTIFS(d_Type,"Delivery",d_Status,"Delivered",d_Year,$P$4,d_City,$Q$4,d_Cuisine,$R$4,d_Pay,$S$4,d_Type,$T$4)/COUNTIFS(d_Type,"Delivery",d_Year,$P$4,d_City,$Q$4,d_Cuisine,$R$4,d_Pay,$S$4,d_Type,$T$4),0) -> 0.67196368 | H6: =IFERROR(AVERAGEIFS(d_Time,d_Type,"Delivery",d_Status,"Delivered",d_Year,$P$4,d_City,$Q$4,d_Cuisine,$R$4,d_Pay,$S$4,d_Type,$T$4),0) -> 41.694257 | J6: =IFERROR(AVERAGEIFS(d_Dist,d_Type,"Delivery",d_Year,$P$4,d_City,$Q$4,d_Cuisine,$R$4,d_Pay,$S$4,d_Type,$T$4),0) -> 7.6994325 | L6: =SUMIFS(d_Fee,d_Type,"Delivery",d_Status,"Delivered",d_Year,$P$4,d_City,$Q$4,d_Cuisine,$R$4,d_Pay,$S$4,d_Type,$T$4) -> 18100
B7: Order_Type = Delivery | D7: Successfully delivered | F7: Delivered ÷ delivery orders | H7: Delivered deliveries | J7: All delivery orders | L7: Delivered deliveries
B57: Supporting data (feeds the charts above)
B59: Delivery fleet by city
B60: City | C60: Delivery orders | D60: Delivered | E60: Success rate | F60: Avg delivery time (min) | G60: Avg distance (km) | H60: Delivery fees earned
B61: Delhi | C61: =COUNTIFS(d_City,$B61,d_Type,"Delivery",d_Year,$P$4,d_City,$Q$4,d_Cuisine,$R$4,d_Pay,$S$4,d_Type,$T$4) -> 85 | D61: =COUNTIFS(d_City,$B61,d_Type,"Delivery",d_Status,"Delivered",d_Year,$P$4,d_City,$Q$4,d_Cuisine,$R$4,d_Pay,$S$4,d_Type,$T$4) -> 58 | E61: =IFERROR(D61/C61,0) -> 0.68235294 | F61: =IFERROR(AVERAGEIFS(d_Time,d_City,$B61,d_Type,"Delivery",d_Status,"Delivered",d_Year,$P$4,d_City,$Q$4,d_Cuisine,$R$4,d_Pay,$S$4,d_Type,$T$4),0) -> 40.068966 | G61: =IFERROR(AVERAGEIFS(d_Dist,d_City,$B61,d_Type,"Delivery",d_Year,$P$4,d_City,$Q$4,d_Cuisine,$R$4,d_Pay,$S$4,d_Type,$T$4),0) -> 7.3658824 | H61: =SUMIFS(d_Fee,d_City,$B61,d_Type,"Delivery",d_Status,"Delivered",d_Year,$P$4,d_City,$Q$4,d_Cuisine,$R$4,d_Pay,$S$4,d_Type,$T$4) -> 1500
B62: Ahmedabad | C62: =COUNTIFS(d_City,$B62,d_Type,"Delivery",d_Year,$P$4,d_City,$Q$4,d_Cuisine,$R$4,d_Pay,$S$4,d_Type,$T$4) -> 88 | D62: =COUNTIFS(d_City,$B62,d_Type,"Delivery",d_Status,"Delivered",d_Year,$P$4,d_City,$Q$4,d_Cuisine,$R$4,d_Pay,$S$4,d_Type,$T$4) -> 61 | E62: =IFERROR(D62/C62,0) -> 0.69318182 | F62: =IFERROR(AVERAGEIFS(d_Time,d_City,$B62,d_Type,"Delivery",d_Status,"Delivered",d_Year,$P$4,d_City,$Q$4,d_Cuisine,$R$4,d_Pay,$S$4,d_Type,$T$4),0) -> 42.393443 | G62: =IFERROR(AVERAGEIFS(d_Dist,d_City,$B62,d_Type,"Delivery",d_Year,$P$4,d_City,$Q$4,d_Cuisine,$R$4,d_Pay,$S$4,d_Type,$T$4),0) -> 7.6806818 | H62: =SUMIFS(d_Fee,d_City,$B62,d_Type,"Delivery",d_Status,"Delivered",d_Year,$P$4,d_City,$Q$4,d_Cuisine,$R$4,d_Pay,$S$4,d_Type,$T$4) -> 1620
B63: Bengaluru | C63: =COUNTIFS(d_City,$B63,d_Type,"Delivery",d_Year,$P$4,d_City,$Q$4,d_Cuisine,$R$4,d_Pay,$S$4,d_Type,$T$4) -> 78 | D63: =COUNTIFS(d_City,$B63,d_Type,"Delivery",d_Status,"Delivered",d_Year,$P$4,d_City,$Q$4,d_Cuisine,$R$4,d_Pay,$S$4,d_Type,$T$4) -> 54 | E63: =IFERROR(D63/C63,0) -> 0.69230769 | F63: =IFERROR(AVERAGEIFS(d_Time,d_City,$B63,d_Type,"Delivery",d_Status,"Delivered",d_Year,$P$4,d_City,$Q$4,d_Cuisine,$R$4,d_Pay,$S$4,d_Type,$T$4),0) -> 47.814815 | G63: =IFERROR(AVERAGEIFS(d_Dist,d_City,$B63,d_Type,"Delivery",d_Year,$P$4,d_City,$Q$4,d_Cuisine,$R$4,d_Pay,$S$4,d_Type,$T$4),0) -> 7.9666667 | H63: =SUMIFS(d_Fee,d_City,$B63,d_Type,"Delivery",d_Status,"Delivered",d_Year,$P$4,d_City,$Q$4,d_Cuisine,$R$4,d_Pay,$S$4,d_Type,$T$4) -> 1740
B64: Chennai | C64: =COUNTIFS(d_City,$B64,d_Type,"Delivery",d_Year,$P$4,d_City,$Q$4,d_Cuisine,$R$4,d_Pay,$S$4,d_Type,$T$4) -> 88 | D64: =COUNTIFS(d_City,$B64,d_Type,"Delivery",d_Status,"Delivered",d_Year,$P$4,d_City,$Q$4,d_Cuisine,$R$4,d_Pay,$S$4,d_Type,$T$4) -> 58 | E64: =IFERROR(D64/C64,0) -> 0.65909091 | F64: =IFERROR(AVERAGEIFS(d_Time,d_City,$B64,d_Type,"Delivery",d_Status,"Delivered",d_Year,$P$4,d_City,$Q$4,d_Cuisine,$R$4,d_Pay,$S$4,d_Type,$T$4),0) -> 38.913793 | G64: =IFERROR(AVERAGEIFS(d_Dist,d_City,$B64,d_Type,"Delivery",d_Year,$P$4,d_City,$Q$4,d_Cuisine,$R$4,d_Pay,$S$4,d_Type,$T$4),0) -> 8.275 | H64: =SUMIFS(d_Fee,d_City,$B64,d_Type,"Delivery",d_Status,"Delivered",d_Year,$P$4,d_City,$Q$4,d_Cuisine,$R$4,d_Pay,$S$4,d_Type,$T$4) -> 1950
B65: Noida | C65: =COUNTIFS(d_City,$B65,d_Type,"Delivery",d_Year,$P$4,d_City,$Q$4,d_Cuisine,$R$4,d_Pay,$S$4,d_Type,$T$4) -> 81 | D65: =COUNTIFS(d_City,$B65,d_Type,"Delivery",d_Status,"Delivered",d_Year,$P$4,d_City,$Q$4,d_Cuisine,$R$4,d_Pay,$S$4,d_Type,$T$4) -> 52 | E65: =IFERROR(D65/C65,0) -> 0.64197531 | F65: =IFERROR(AVERAGEIFS(d_Time,d_City,$B65,d_Type,"Delivery",d_Status,"Delivered",d_Year,$P$4,d_City,$Q$4,d_Cuisine,$R$4,d_Pay,$S$4,d_Type,$T$4),0) -> 43.730769 | G65: =IFERROR(AVERAGEIFS(d_Dist,d_City,$B65,d_Type,"Delivery",d_Year,$P$4,d_City,$Q$4,d_Cuisine,$R$4,d_Pay,$S$4,d_Type,$T$4),0) -> 7.5592593 | H65: =SUMIFS(d_Fee,d_City,$B65,d_Type,"Delivery",d_Status,"Delivered",d_Year,$P$4,d_City,$Q$4,d_Cuisine,$R$4,d_Pay,$S$4,d_Type,$T$4) -> 1500
B66: Jaipur | C66: =COUNTIFS(d_City,$B66,d_Type,"Delivery",d_Year,$P$4,d_City,$Q$4,d_Cuisine,$R$4,d_Pay,$S$4,d_Type,$T$4) -> 70 | D66: =COUNTIFS(d_City,$B66,d_Type,"Delivery",d_Status,"Delivered",d_Year,$P$4,d_City,$Q$4,d_Cuisine,$R$4,d_Pay,$S$4,d_Type,$T$4) -> 50 | E66: =IFERROR(D66/C66,0) -> 0.71428571 | F66: =IFERROR(AVERAGEIFS(d_Time,d_City,$B66,d_Type,"Delivery",d_Status,"Delivered",d_Year,$P$4,d_City,$Q$4,d_Cuisine,$R$4,d_Pay,$S$4,d_Type,$T$4),0) -> 40.82 | G66: =IFERROR(AVERAGEIFS(d_Dist,d_City,$B66,d_Type,"Delivery",d_Year,$P$4,d_City,$Q$4,d_Cuisine,$R$4,d_Pay,$S$4,d_Type,$T$4),0) -> 7.5757143 | H66: =SUMIFS(d_Fee,d_City,$B66,d_Type,"Delivery",d_Status,"Delivered",d_Year,$P$4,d_City,$Q$4,d_Cuisine,$R$4,d_Pay,$S$4,d_Type,$T$4) -> 1650
B67: Hyderabad | C67: =COUNTIFS(d_City,$B67,d_Type,"Delivery",d_Year,$P$4,d_City,$Q$4,d_Cuisine,$R$4,d_Pay,$S$4,d_Type,$T$4) -> 72 | D67: =COUNTIFS(d_City,$B67,d_Type,"Delivery",d_Status,"Delivered",d_Year,$P$4,d_City,$Q$4,d_Cuisine,$R$4,d_Pay,$S$4,d_Type,$T$4) -> 43 | E67: =IFERROR(D67/C67,0) -> 0.59722222 | F67: =IFERROR(AVERAGEIFS(d_Time,d_City,$B67,d_Type,"Delivery",d_Status,"Delivered",d_Year,$P$4,d_City,$Q$4,d_Cuisine,$R$4,d_Pay,$S$4,d_Type,$T$4),0) -> 41.744186 | G67: =IFERROR(AVERAGEIFS(d_Dist,d_City,$B67,d_Type,"Delivery",d_Year,$P$4,d_City,$Q$4,d_Cuisine,$R$4,d_Pay,$S$4,d_Type,$T$4),0) -> 6.8152778 | H67: =SUMIFS(d_Fee,d_City,$B67,d_Type,"Delivery",d_Status,"Delivered",d_Year,$P$4,d_City,$Q$4,d_Cuisine,$R$4,d_Pay,$S$4,d_Type,$T$4) -> 1320
B68: Pune | C68: =COUNTIFS(d_City,$B68,d_Type,"Delivery",d_Year,$P$4,d_City,$Q$4,d_Cuisine,$R$4,d_Pay,$S$4,d_Type,$T$4) -> 70 | D68: =COUNTIFS(d_City,$B68,d_Type,"Delivery",d_Status,"Delivered",d_Year,$P$4,d_City,$Q$4,d_Cuisine,$R$4,d_Pay,$S$4,d_Type,$T$4) -> 40 | E68: =IFERROR(D68/C68,0) -> 0.57142857 | F68: =IFERROR(AVERAGEIFS(d_Time,d_City,$B68,d_Type,"Delivery",d_Status,"Delivered",d_Year,$P$4,d_City,$Q$4,d_Cuisine,$R$4,d_Pay,$S$4,d_Type,$T$4),0) -> 40.475 | G68: =IFERROR(AVERAGEIFS(d_Dist,d_City,$B68,d_Type,"Delivery",d_Year,$P$4,d_City,$Q$4,d_Cuisine,$R$4,d_Pay,$S$4,d_Type,$T$4),0) -> 7.6671429 | H68: =SUMIFS(d_Fee,d_City,$B68,d_Type,"Delivery",d_Status,"Delivered",d_Year,$P$4,d_City,$Q$4,d_Cuisine,$R$4,d_Pay,$S$4,d_Type,$T$4) -> 1200
B69: Kolkata | C69: =COUNTIFS(d_City,$B69,d_Type,"Delivery",d_Year,$P$4,d_City,$Q$4,d_Cuisine,$R$4,d_Pay,$S$4,d_Type,$T$4) -> 73 | D69: =COUNTIFS(d_City,$B69,d_Type,"Delivery",d_Status,"Delivered",d_Year,$P$4,d_City,$Q$4,d_Cuisine,$R$4,d_Pay,$S$4,d_Type,$T$4) -> 52 | E69: =IFERROR(D69/C69,0) -> 0.71232877 | F69: =IFERROR(AVERAGEIFS(d_Time,d_City,$B69,d_Type,"Delivery",d_Status,"Delivered",d_Year,$P$4,d_City,$Q$4,d_Cuisine,$R$4,d_Pay,$S$4,d_Type,$T$4),0) -> 40.942308 | G69: =IFERROR(AVERAGEIFS(d_Dist,d_City,$B69,d_Type,"Delivery",d_Year,$P$4,d_City,$Q$4,d_Cuisine,$R$4,d_Pay,$S$4,d_Type,$T$4),0) -> 8.3589041 | H69: =SUMIFS(d_Fee,d_City,$B69,d_Type,"Delivery",d_Status,"Delivered",d_Year,$P$4,d_City,$Q$4,d_Cuisine,$R$4,d_Pay,$S$4,d_Type,$T$4) -> 1770
B70: Lucknow | C70: =COUNTIFS(d_City,$B70,d_Type,"Delivery",d_Year,$P$4,d_City,$Q$4,d_Cuisine,$R$4,d_Pay,$S$4,d_Type,$T$4) -> 64 | D70: =COUNTIFS(d_City,$B70,d_Type,"Delivery",d_Status,"Delivered",d_Year,$P$4,d_City,$Q$4,d_Cuisine,$R$4,d_Pay,$S$4,d_Type,$T$4) -> 44 | E70: =IFERROR(D70/C70,0) -> 0.6875 | F70: =IFERROR(AVERAGEIFS(d_Time,d_City,$B70,d_Type,"Delivery",d_Status,"Delivered",d_Year,$P$4,d_City,$Q$4,d_Cuisine,$R$4,d_Pay,$S$4,d_Type,$T$4),0) -> 40.545455 | G70: =IFERROR(AVERAGEIFS(d_Dist,d_City,$B70,d_Type,"Delivery",d_Year,$P$4,d_City,$Q$4,d_Cuisine,$R$4,d_Pay,$S$4,d_Type,$T$4),0) -> 7.23125 | H70: =SUMIFS(d_Fee,d_City,$B70,d_Type,"Delivery",d_Status,"Delivered",d_Year,$P$4,d_City,$Q$4,d_Cuisine,$R$4,d_Pay,$S$4,d_Type,$T$4) -> 1330
B71: Mumbai | C71: =COUNTIFS(d_City,$B71,d_Type,"Delivery",d_Year,$P$4,d_City,$Q$4,d_Cuisine,$R$4,d_Pay,$S$4,d_Type,$T$4) -> 55 | D71: =COUNTIFS(d_City,$B71,d_Type,"Delivery",d_Status,"Delivered",d_Year,$P$4,d_City,$Q$4,d_Cuisine,$R$4,d_Pay,$S$4,d_Type,$T$4) -> 40 | E71: =IFERROR(D71/C71,0) -> 0.72727273 | F71: =IFERROR(AVERAGEIFS(d_Time,d_City,$B71,d_Type,"Delivery",d_Status,"Delivered",d_Year,$P$4,d_City,$Q$4,d_Cuisine,$R$4,d_Pay,$S$4,d_Type,$T$4),0) -> 39.25 | G71: =IFERROR(AVERAGEIFS(d_Dist,d_City,$B71,d_Type,"Delivery",d_Year,$P$4,d_City,$Q$4,d_Cuisine,$R$4,d_Pay,$S$4,d_Type,$T$4),0) -> 7.7836364 | H71: =SUMIFS(d_Fee,d_City,$B71,d_Type,"Delivery",d_Status,"Delivered",d_Year,$P$4,d_City,$Q$4,d_Cuisine,$R$4,d_Pay,$S$4,d_Type,$T$4) -> 1310
B72: Gurugram | C72: =COUNTIFS(d_City,$B72,d_Type,"Delivery",d_Year,$P$4,d_City,$Q$4,d_Cuisine,$R$4,d_Pay,$S$4,d_Type,$T$4) -> 57 | D72: =COUNTIFS(d_City,$B72,d_Type,"Delivery",d_Status,"Delivered",d_Year,$P$4,d_City,$Q$4,d_Cuisine,$R$4,d_Pay,$S$4,d_Type,$T$4) -> 40 | E72: =IFERROR(D72/C72,0) -> 0.70175439 | F72: =IFERROR(AVERAGEIFS(d_Time,d_City,$B72,d_Type,"Delivery",d_Status,"Delivered",d_Year,$P$4,d_City,$Q$4,d_Cuisine,$R$4,d_Pay,$S$4,d_Type,$T$4),0) -> 43.05 | G72: =IFERROR(AVERAGEIFS(d_Dist,d_City,$B72,d_Type,"Delivery",d_Year,$P$4,d_City,$Q$4,d_Cuisine,$R$4,d_Pay,$S$4,d_Type,$T$4),0) -> 8.0789474 | H72: =SUMIFS(d_Fee,d_City,$B72,d_Type,"Delivery",d_Status,"Delivered",d_Year,$P$4,d_City,$Q$4,d_Cuisine,$R$4,d_Pay,$S$4,d_Type,$T$4) -> 1210
B73: Total / Overall | C73: =SUM(C61:C72) -> 881 | D73: =SUM(D61:D72) -> 592 | E73: =IFERROR(D73/C73,0) -> 0.67196368 | F73: =IFERROR(AVERAGEIFS(d_Time,d_Type,"Delivery",d_Status,"Delivered",d_Year,$P$4,d_City,$Q$4,d_Cuisine,$R$4,d_Pay,$S$4,d_Type,$T$4),0) -> 41.694257 | G73: =IFERROR(AVERAGEIFS(d_Dist,d_Type,"Delivery",d_Year,$P$4,d_City,$Q$4,d_Cuisine,$R$4,d_Pay,$S$4,d_Type,$T$4),0) -> 7.6994325 | H73: =SUM(H61:H72) -> 18100
B74: Avg delivery time and fees are for Delivered orders only; distance is for all delivery orders.
B77: Delivery fleet by distance band
B78: Distance band | C78: Min km (>) | D78: Max km (<=) | E78: Delivery orders | F78: Delivered | G78: Avg delivery time (min) | H78: Avg fee (₹)
B79: 0–3 km | C79: 0 | D79: 3 | E79: =COUNTIFS(d_Dist,">"&$C79,d_Dist,"<="&$D79,d_Type,"Delivery",d_Year,$P$4,d_City,$Q$4,d_Cuisine,$R$4,d_Pay,$S$4,d_Type,$T$4) -> 165 | F79: =COUNTIFS(d_Dist,">"&$C79,d_Dist,"<="&$D79,d_Type,"Delivery",d_Status,"Delivered",d_Year,$P$4,d_City,$Q$4,d_Cuisine,$R$4,d_Pay,$S$4,d_Type,$T$4) -> 112 | G79: =IFERROR(AVERAGEIFS(d_Time,d_Dist,">"&$C79,d_Dist,"<="&$D79,d_Type,"Delivery",d_Status,"Delivered",d_Year,$P$4,d_City,$Q$4,d_Cuisine,$R$4,d_Pay,$S$4,d_Type,$T$4),0) -> 41.116071 | H79: =IFERROR(AVERAGEIFS(d_Fee,d_Dist,">"&$C79,d_Dist,"<="&$D79,d_Type,"Delivery",d_Year,$P$4,d_City,$Q$4,d_Cuisine,$R$4,d_Pay,$S$4,d_Type,$T$4),0) -> 33.212121
B80: 3–6 km | C80: 3 | D80: 6 | E80: =COUNTIFS(d_Dist,">"&$C80,d_Dist,"<="&$D80,d_Type,"Delivery",d_Year,$P$4,d_City,$Q$4,d_Cuisine,$R$4,d_Pay,$S$4,d_Type,$T$4) -> 185 | F80: =COUNTIFS(d_Dist,">"&$C80,d_Dist,"<="&$D80,d_Type,"Delivery",d_Status,"Delivered",d_Year,$P$4,d_City,$Q$4,d_Cuisine,$R$4,d_Pay,$S$4,d_Type,$T$4) -> 121 | G80: =IFERROR(AVERAGEIFS(d_Time,d_Dist,">"&$C80,d_Dist,"<="&$D80,d_Type,"Delivery",d_Status,"Delivered",d_Year,$P$4,d_City,$Q$4,d_Cuisine,$R$4,d_Pay,$S$4,d_Type,$T$4),0) -> 43.355372 | H80: =IFERROR(AVERAGEIFS(d_Fee,d_Dist,">"&$C80,d_Dist,"<="&$D80,d_Type,"Delivery",d_Year,$P$4,d_City,$Q$4,d_Cuisine,$R$4,d_Pay,$S$4,d_Type,$T$4),0) -> 34.054054
B81: 6–9 km | C81: 6 | D81: 9 | E81: =COUNTIFS(d_Dist,">"&$C81,d_Dist,"<="&$D81,d_Type,"Delivery",d_Year,$P$4,d_City,$Q$4,d_Cuisine,$R$4,d_Pay,$S$4,d_Type,$T$4) -> 172 | F81: =COUNTIFS(d_Dist,">"&$C81,d_Dist,"<="&$D81,d_Type,"Delivery",d_Status,"Delivered",d_Year,$P$4,d_City,$Q$4,d_Cuisine,$R$4,d_Pay,$S$4,d_Type,$T$4) -> 123 | G81: =IFERROR(AVERAGEIFS(d_Time,d_Dist,">"&$C81,d_Dist,"<="&$D81,d_Type,"Delivery",d_Status,"Delivered",d_Year,$P$4,d_City,$Q$4,d_Cuisine,$R$4,d_Pay,$S$4,d_Type,$T$4),0) -> 40.837398 | H81: =IFERROR(AVERAGEIFS(d_Fee,d_Dist,">"&$C81,d_Dist,"<="&$D81,d_Type,"Delivery",d_Year,$P$4,d_City,$Q$4,d_Cuisine,$R$4,d_Pay,$S$4,d_Type,$T$4),0) -> 30.05814
B82: 9–12 km | C82: 9 | D82: 12 | E82: =COUNTIFS(d_Dist,">"&$C82,d_Dist,"<="&$D82,d_Type,"Delivery",d_Year,$P$4,d_City,$Q$4,d_Cuisine,$R$4,d_Pay,$S$4,d_Type,$T$4) -> 172 | F82: =COUNTIFS(d_Dist,">"&$C82,d_Dist,"<="&$D82,d_Type,"Delivery",d_Status,"Delivered",d_Year,$P$4,d_City,$Q$4,d_Cuisine,$R$4,d_Pay,$S$4,d_Type,$T$4) -> 115 | G82: =IFERROR(AVERAGEIFS(d_Time,d_Dist,">"&$C82,d_Dist,"<="&$D82,d_Type,"Delivery",d_Status,"Delivered",d_Year,$P$4,d_City,$Q$4,d_Cuisine,$R$4,d_Pay,$S$4,d_Type,$T$4),0) -> 40.469565 | H82: =IFERROR(AVERAGEIFS(d_Fee,d_Dist,">"&$C82,d_Dist,"<="&$D82,d_Type,"Delivery",d_Year,$P$4,d_City,$Q$4,d_Cuisine,$R$4,d_Pay,$S$4,d_Type,$T$4),0) -> 31.802326
B83: 12–15 km | C83: 12 | D83: 15 | E83: =COUNTIFS(d_Dist,">"&$C83,d_Dist,"<="&$D83,d_Type,"Delivery",d_Year,$P$4,d_City,$Q$4,d_Cuisine,$R$4,d_Pay,$S$4,d_Type,$T$4) -> 187 | F83: =COUNTIFS(d_Dist,">"&$C83,d_Dist,"<="&$D83,d_Type,"Delivery",d_Status,"Delivered",d_Year,$P$4,d_City,$Q$4,d_Cuisine,$R$4,d_Pay,$S$4,d_Type,$T$4) -> 121 | G83: =IFERROR(AVERAGEIFS(d_Time,d_Dist,">"&$C83,d_Dist,"<="&$D83,d_Type,"Delivery",d_Status,"Delivered",d_Year,$P$4,d_City,$Q$4,d_Cuisine,$R$4,d_Pay,$S$4,d_Type,$T$4),0) -> 42.603306 | H83: =IFERROR(AVERAGEIFS(d_Fee,d_Dist,">"&$C83,d_Dist,"<="&$D83,d_Type,"Delivery",d_Year,$P$4,d_City,$Q$4,d_Cuisine,$R$4,d_Pay,$S$4,d_Type,$T$4),0) -> 31.497326
B84: Total / Overall | E84: =SUM(E79:E83) -> 881 | F84: =SUM(F79:F83) -> 592
B85: Distance bounds are inputs (blue).
B88: Delivery-order status
B89: Status | C89: Delivery orders | D89: % of delivery orders
B90: Delivered | C90: =COUNTIFS(d_Status,$B90,d_Type,"Delivery",d_Year,$P$4,d_City,$Q$4,d_Cuisine,$R$4,d_Pay,$S$4,d_Type,$T$4) -> 592 | D90: =IFERROR(C90/COUNTIFS(d_Type,"Delivery",d_Year,$P$4,d_City,$Q$4,d_Cuisine,$R$4,d_Pay,$S$4,d_Type,$T$4),0) -> 0.67196368
B91: Pending | C91: =COUNTIFS(d_Status,$B91,d_Type,"Delivery",d_Year,$P$4,d_City,$Q$4,d_Cuisine,$R$4,d_Pay,$S$4,d_Type,$T$4) -> 146 | D91: =IFERROR(C91/COUNTIFS(d_Type,"Delivery",d_Year,$P$4,d_City,$Q$4,d_Cuisine,$R$4,d_Pay,$S$4,d_Type,$T$4),0) -> 0.16572077
B92: Cancelled | C92: =COUNTIFS(d_Status,$B92,d_Type,"Delivery",d_Year,$P$4,d_City,$Q$4,d_Cuisine,$R$4,d_Pay,$S$4,d_Type,$T$4) -> 143 | D92: =IFERROR(C92/COUNTIFS(d_Type,"Delivery",d_Year,$P$4,d_City,$Q$4,d_Cuisine,$R$4,d_Pay,$S$4,d_Type,$T$4),0) -> 0.16231555
B93: Total / Overall | C93: =SUM(C90:C92) -> 881 | D93: =SUM(D90:D92) -> 1
B96: Monthly delivery orders
B97: Month | C97: Month start | D97: Delivery orders | E97: Delivered | F97: Avg delivery time (min)
B98: =TEXT(C98,"mmm-yy") -> Jan-25 | C98: 45658 | D98: =COUNTIFS(d_Date,">="&$C98,d_Date,"<"&EDATE($C98,1),d_Type,"Delivery",d_Year,$P$4,d_City,$Q$4,d_Cuisine,$R$4,d_Pay,$S$4,d_Type,$T$4) -> 58 | E98: =COUNTIFS(d_Date,">="&$C98,d_Date,"<"&EDATE($C98,1),d_Type,"Delivery",d_Status,"Delivered",d_Year,$P$4,d_City,$Q$4,d_Cuisine,$R$4,d_Pay,$S$4,d_Type,$T$4) -> 40 | F98: =IFERROR(AVERAGEIFS(d_Time,d_Date,">="&$C98,d_Date,"<"&EDATE($C98,1),d_Type,"Delivery",d_Status,"Delivered",d_Year,$P$4,d_City,$Q$4,d_Cuisine,$R$4,d_Pay,$S$4,d_Type,$T$4),0) -> 42.775
B99: =TEXT(C99,"mmm-yy") -> Feb-25 | C99: 45689 | D99: =COUNTIFS(d_Date,">="&$C99,d_Date,"<"&EDATE($C99,1),d_Type,"Delivery",d_Year,$P$4,d_City,$Q$4,d_Cuisine,$R$4,d_Pay,$S$4,d_Type,$T$4) -> 60 | E99: =COUNTIFS(d_Date,">="&$C99,d_Date,"<"&EDATE($C99,1),d_Type,"Delivery",d_Status,"Delivered",d_Year,$P$4,d_City,$Q$4,d_Cuisine,$R$4,d_Pay,$S$4,d_Type,$T$4) -> 31 | F99: =IFERROR(AVERAGEIFS(d_Time,d_Date,">="&$C99,d_Date,"<"&EDATE($C99,1),d_Type,"Delivery",d_Status,"Delivered",d_Year,$P$4,d_City,$Q$4,d_Cuisine,$R$4,d_Pay,$S$4,d_Type,$T$4),0) -> 42.870968
B100: =TEXT(C100,"mmm-yy") -> Mar-25 | C100: 45717 | D100: =COUNTIFS(d_Date,">="&$C100,d_Date,"<"&EDATE($C100,1),d_Type,"Delivery",d_Year,$P$4,d_City,$Q$4,d_Cuisine,$R$4,d_Pay,$S$4,d_Type,$T$4) -> 73 | E100: =COUNTIFS(d_Date,">="&$C100,d_Date,"<"&EDATE($C100,1),d_Type,"Delivery",d_Status,"Delivered",d_Year,$P$4,d_City,$Q$4,d_Cuisine,$R$4,d_Pay,$S$4,d_Type,$T$4) -> 47 | F100: =IFERROR(AVERAGEIFS(d_Time,d_Date,">="&$C100,d_Date,"<"&EDATE($C100,1),d_Type,"Delivery",d_Status,"Delivered",d_Year,$P$4,d_City,$Q$4,d_Cuisine,$R$4,d_Pay,$S$4,d_Type,$T$4),0) -> 41.680851
B101: =TEXT(C101,"mmm-yy") -> Apr-25 | C101: 45748 | D101: =COUNTIFS(d_Date,">="&$C101,d_Date,"<"&EDATE($C101,1),d_Type,"Delivery",d_Year,$P$4,d_City,$Q$4,d_Cuisine,$R$4,d_Pay,$S$4,d_Type,$T$4) -> 72 | E101: =COUNTIFS(d_Date,">="&$C101,d_Date,"<"&EDATE($C101,1),d_Type,"Delivery",d_Status,"Delivered",d_Year,$P$4,d_City,$Q$4,d_Cuisine,$R$4,d_Pay,$S$4,d_Type,$T$4) -> 50 | F101: =IFERROR(AVERAGEIFS(d_Time,d_Date,">="&$C101,d_Date,"<"&EDATE($C101,1),d_Type,"Delivery",d_Status,"Delivered",d_Year,$P$4,d_City,$Q$4,d_Cuisine,$R$4,d_Pay,$S$4,d_Type,$T$4),0) -> 45.16
B102: =TEXT(C102,"mmm-yy") -> May-25 | C102: 45778 | D102: =COUNTIFS(d_Date,">="&$C102,d_Date,"<"&EDATE($C102,1),d_Type,"Delivery",d_Year,$P$4,d_City,$Q$4,d_Cuisine,$R$4,d_Pay,$S$4,d_Type,$T$4) -> 66 | E102: =COUNTIFS(d_Date,">="&$C102,d_Date,"<"&EDATE($C102,1),d_Type,"Delivery",d_Status,"Delivered",d_Year,$P$4,d_City,$Q$4,d_Cuisine,$R$4,d_Pay,$S$4,d_Type,$T$4) -> 40 | F102: =IFERROR(AVERAGEIFS(d_Time,d_Date,">="&$C102,d_Date,"<"&EDATE($C102,1),d_Type,"Delivery",d_Status,"Delivered",d_Year,$P$4,d_City,$Q$4,d_Cuisine,$R$4,d_Pay,$S$4,d_Type,$T$4),0) -> 39.125
B103: =TEXT(C103,"mmm-yy") -> Jun-25 | C103: 45809 | D103: =COUNTIFS(d_Date,">="&$C103,d_Date,"<"&EDATE($C103,1),d_Type,"Delivery",d_Year,$P$4,d_City,$Q$4,d_Cuisine,$R$4,d_Pay,$S$4,d_Type,$T$4) -> 63 | E103: =COUNTIFS(d_Date,">="&$C103,d_Date,"<"&EDATE($C103,1),d_Type,"Delivery",d_Status,"Delivered",d_Year,$P$4,d_City,$Q$4,d_Cuisine,$R$4,d_Pay,$S$4,d_Type,$T$4) -> 41 | F103: =IFERROR(AVERAGEIFS(d_Time,d_Date,">="&$C103,d_Date,"<"&EDATE($C103,1),d_Type,"Delivery",d_Status,"Delivered",d_Year,$P$4,d_City,$Q$4,d_Cuisine,$R$4,d_Pay,$S$4,d_Type,$T$4),0) -> 38.121951
B104: =TEXT(C104,"mmm-yy") -> Jul-25 | C104: 45839 | D104: =COUNTIFS(d_Date,">="&$C104,d_Date,"<"&EDATE($C104,1),d_Type,"Delivery",d_Year,$P$4,d_City,$Q$4,d_Cuisine,$R$4,d_Pay,$S$4,d_Type,$T$4) -> 67 | E104: =COUNTIFS(d_Date,">="&$C104,d_Date,"<"&EDATE($C104,1),d_Type,"Delivery",d_Status,"Delivered",d_Year,$P$4,d_City,$Q$4,d_Cuisine,$R$4,d_Pay,$S$4,d_Type,$T$4) -> 45 | F104: =IFERROR(AVERAGEIFS(d_Time,d_Date,">="&$C104,d_Date,"<"&EDATE($C104,1),d_Type,"Delivery",d_Status,"Delivered",d_Year,$P$4,d_City,$Q$4,d_Cuisine,$R$4,d_Pay,$S$4,d_Type,$T$4),0) -> 42.488889
B105: =TEXT(C105,"mmm-yy") -> Aug-25 | C105: 45870 | D105: =COUNTIFS(d_Date,">="&$C105,d_Date,"<"&EDATE($C105,1),d_Type,"Delivery",d_Year,$P$4,d_City,$Q$4,d_Cuisine,$R$4,d_Pay,$S$4,d_Type,$T$4) -> 77 | E105: =COUNTIFS(d_Date,">="&$C105,d_Date,"<"&EDATE($C105,1),d_Type,"Delivery",d_Status,"Delivered",d_Year,$P$4,d_City,$Q$4,d_Cuisine,$R$4,d_Pay,$S$4,d_Type,$T$4) -> 59 | F105: =IFERROR(AVERAGEIFS(d_Time,d_Date,">="&$C105,d_Date,"<"&EDATE($C105,1),d_Type,"Delivery",d_Status,"Delivered",d_Year,$P$4,d_City,$Q$4,d_Cuisine,$R$4,d_Pay,$S$4,d_Type,$T$4),0) -> 39.067797
B106: =TEXT(C106,"mmm-yy") -> Sep-25 | C106: 45901 | D106: =COUNTIFS(d_Date,">="&$C106,d_Date,"<"&EDATE($C106,1),d_Type,"Delivery",d_Year,$P$4,d_City,$Q$4,d_Cuisine,$R$4,d_Pay,$S$4,d_Type,$T$4) -> 70 | E106: =COUNTIFS(d_Date,">="&$C106,d_Date,"<"&EDATE($C106,1),d_Type,"Delivery",d_Status,"Delivered",d_Year,$P$4,d_City,$Q$4,d_Cuisine,$R$4,d_Pay,$S$4,d_Type,$T$4) -> 49 | F106: =IFERROR(AVERAGEIFS(d_Time,d_Date,">="&$C106,d_Date,"<"&EDATE($C106,1),d_Type,"Delivery",d_Status,"Delivered",d_Year,$P$4,d_City,$Q$4,d_Cuisine,$R$4,d_Pay,$S$4,d_Type,$T$4),0) -> 40.591837
B107: =TEXT(C107,"mmm-yy") -> Oct-25 | C107: 45931 | D107: =COUNTIFS(d_Date,">="&$C107,d_Date,"<"&EDATE($C107,1),d_Type,"Delivery",d_Year,$P$4,d_City,$Q$4,d_Cuisine,$R$4,d_Pay,$S$4,d_Type,$T$4) -> 66 | E107: =COUNTIFS(d_Date,">="&$C107,d_Date,"<"&EDATE($C107,1),d_Type,"Delivery",d_Status,"Delivered",d_Year,$P$4,d_City,$Q$4,d_Cuisine,$R$4,d_Pay,$S$4,d_Type,$T$4) -> 44 | F107: =IFERROR(AVERAGEIFS(d_Time,d_Date,">="&$C107,d_Date,"<"&EDATE($C107,1),d_Type,"Delivery",d_Status,"Delivered",d_Year,$P$4,d_City,$Q$4,d_Cuisine,$R$4,d_Pay,$S$4,d_Type,$T$4),0) -> 42.090909
B108: =TEXT(C108,"mmm-yy") -> Nov-25 | C108: 45962 | D108: =COUNTIFS(d_Date,">="&$C108,d_Date,"<"&EDATE($C108,1),d_Type,"Delivery",d_Year,$P$4,d_City,$Q$4,d_Cuisine,$R$4,d_Pay,$S$4,d_Type,$T$4) -> 64 | E108: =COUNTIFS(d_Date,">="&$C108,d_Date,"<"&EDATE($C108,1),d_Type,"Delivery",d_Status,"Delivered",d_Year,$P$4,d_City,$Q$4,d_Cuisine,$R$4,d_Pay,$S$4,d_Type,$T$4) -> 43 | F108: =IFERROR(AVERAGEIFS(d_Time,d_Date,">="&$C108,d_Date,"<"&EDATE($C108,1),d_Type,"Delivery",d_Status,"Delivered",d_Year,$P$4,d_City,$Q$4,d_Cuisine,$R$4,d_Pay,$S$4,d_Type,$T$4),0) -> 47
B109: =TEXT(C109,"mmm-yy") -> Dec-25 | C109: 45992 | D109: =COUNTIFS(d_Date,">="&$C109,d_Date,"<"&EDATE($C109,1),d_Type,"Delivery",d_Year,$P$4,d_City,$Q$4,d_Cuisine,$R$4,d_Pay,$S$4,d_Type,$T$4) -> 70 | E109: =COUNTIFS(d_Date,">="&$C109,d_Date,"<"&EDATE($C109,1),d_Type,"Delivery",d_Status,"Delivered",d_Year,$P$4,d_City,$Q$4,d_Cuisine,$R$4,d_Pay,$S$4,d_Type,$T$4) -> 47 | F109: =IFERROR(AVERAGEIFS(d_Time,d_Date,">="&$C109,d_Date,"<"&EDATE($C109,1),d_Type,"Delivery",d_Status,"Delivered",d_Year,$P$4,d_City,$Q$4,d_Cuisine,$R$4,d_Pay,$S$4,d_Type,$T$4),0) -> 43.06383
... B111: =TEXT(C111,"mmm-yy") -> Feb-26 | C111: 46054 | D111: =COUNTIFS(d_Date,">="&$C111,d_Date,"<"&EDATE($C111,1),d_Type,"Delivery",d_Year,$P$4,d_City,$Q$4,d_Cuisine,$R$4,d_Pay,$S$4,d_Type,$T$4) -> 8 | E111: =COUNTIFS(d_Date,">="&$C111,d_Date,"<"&EDATE($C111,1),d_Type,"Delivery",d_Status,"Delivered",d_Year,$P$4,d_City,$Q$4,d_Cuisine,$R$4,d_Pay,$S$4,d_Type,$T$4) -> 4 | F111: =IFERROR(AVERAGEIFS(d_Time,d_Date,">="&$C111,d_Date,"<"&EDATE($C111,1),d_Type,"Delivery",d_Status,"Delivered",d_Year,$P$4,d_City,$Q$4,d_Cuisine,$R$4,d_Pay,$S$4,d_Type,$T$4),0) -> 30.75

Sheet Delivery Time
B2: Delivery Time Analysis
B3: Speed of delivered orders (Order_Status = Delivered). Change the SLA target (blue cell M4) to re-score on-time performance. ▸ Use the yellow filters in row 4 – every KPI, chart and table updates. | L3: ← Back to Home
B4: Year: | C4: All | D4: City: | E4: All | F4: Cuisine: | G4: All | H4: Payment: | I4: All | J4: Order type: | K4: All | L4: SLA target (min): | M4: 45 | P4: =IF(C4="All",">0",C4) -> >0 | Q4: =IF(E4="All","*",E4) -> * | R4: =IF(G4="All","*",G4) -> * | S4: =IF(I4="All","*",I4) -> * | T4: =IF(K4="All","*",K4) -> *
B5: AVG DELIVERY TIME | D5: FASTEST | F5: SLOWEST | H5: ON-TIME RATE | J5: AVG DISTANCE | L5: AVG MIN PER KM
B6: =IFERROR(AVERAGEIFS(d_Time,d_Status,"Delivered",d_Year,$P$4,d_City,$Q$4,d_Cuisine,$R$4,d_Pay,$S$4,d_Type,$T$4),0) -> 41.530973 | D6: =_xlfn.MINIFS(d_Time,d_Status,"Delivered",d_Year,$P$4,d_City,$Q$4,d_Cuisine,$R$4,d_Pay,$S$4,d_Type,$T$4) -> 15 | F6: =_xlfn.MAXIFS(d_Time,d_Status,"Delivered",d_Year,$P$4,d_City,$Q$4,d_Cuisine,$R$4,d_Pay,$S$4,d_Type,$T$4) -> 70 | H6: =IFERROR(COUNTIFS(d_Status,"Delivered",d_Time,"<="&$M$4,d_Year,$P$4,d_City,$Q$4,d_Cuisine,$R$4,d_Pay,$S$4,d_Type,$T$4)/COUNTIFS(d_Status,"Delivered",d_Year,$P$4,d_City,$Q$4,d_Cuisine,$R$4,d_Pay,$S$4,d_Type,$T$4),0) -> 0.57395702 | J6: =IFERROR(AVERAGEIFS(d_Dist,d_Status,"Delivered",d_Year,$P$4,d_City,$Q$4,d_Cuisine,$R$4,d_Pay,$S$4,d_Type,$T$4),0) -> 7.7174463 | L6: =IFERROR(IFERROR(AVERAGEIFS(d_Time,d_Status,"Delivered",d_Year,$P$4,d_City,$Q$4,d_Cuisine,$R$4,d_Pay,$S$4,d_Type,$T$4),0)/IFERROR(AVERAGEIFS(d_Dist,d_Status,"Delivered",d_Year,$P$4,d_City,$Q$4,d_Cuisine,$R$4,d_Pay,$S$4,d_Type,$T$4),0),0) -> 5.3814399
B7: Delivered orders | D7: Shortest delivery | F7: Longest delivery | H7: Within SLA target | J7: Delivered orders | L7: Avg time ÷ avg distance
B57: Supporting data (feeds the charts above)
B59: Delivery-time distribution (Delivered orders)
B60: Time band | C60: Min (min) | D60: Max (min) | E60: Orders | F60: % of delivered | G60: Avg customer rating
B61: 15–20 min | C61: 0 | D61: 20 | E61: =COUNTIFS(d_Time,">="&$C61,d_Time,"<="&$D61,d_Status,"Delivered",d_Year,$P$4,d_City,$Q$4,d_Cuisine,$R$4,d_Pay,$S$4,d_Type,$T$4) -> 86 | F61: =IFERROR(E61/COUNTIFS(d_Status,"Delivered",d_Year,$P$4,d_City,$Q$4,d_Cuisine,$R$4,d_Pay,$S$4,d_Type,$T$4),0) -> 0.10872314 | G61: =IFERROR(AVERAGEIFS(d_CRating,d_Time,">="&$C61,d_Time,"<="&$D61,d_Status,"Delivered",d_Year,$P$4,d_City,$Q$4,d_Cuisine,$R$4,d_Pay,$S$4,d_Type,$T$4),0) -> 4.0581395
B62: 21–30 min | C62: 21 | D62: 30 | E62: =COUNTIFS(d_Time,">="&$C62,d_Time,"<="&$D62,d_Status,"Delivered",d_Year,$P$4,d_City,$Q$4,d_Cuisine,$R$4,d_Pay,$S$4,d_Type,$T$4) -> 162 | F62: =IFERROR(E62/COUNTIFS(d_Status,"Delivered",d_Year,$P$4,d_City,$Q$4,d_Cuisine,$R$4,d_Pay,$S$4,d_Type,$T$4),0) -> 0.20480405 | G62: =IFERROR(AVERAGEIFS(d_CRating,d_Time,">="&$C62,d_Time,"<="&$D62,d_Status,"Delivered",d_Year,$P$4,d_City,$Q$4,d_Cuisine,$R$4,d_Pay,$S$4,d_Type,$T$4),0) -> 4.0740741
B63: 31–40 min | C63: 31 | D63: 40 | E63: =COUNTIFS(d_Time,">="&$C63,d_Time,"<="&$D63,d_Status,"Delivered",d_Year,$P$4,d_City,$Q$4,d_Cuisine,$R$4,d_Pay,$S$4,d_Type,$T$4) -> 133 | F63: =IFERROR(E63/COUNTIFS(d_Status,"Delivered",d_Year,$P$4,d_City,$Q$4,d_Cuisine,$R$4,d_Pay,$S$4,d_Type,$T$4),0) -> 0.16814159 | G63: =IFERROR(AVERAGEIFS(d_CRating,d_Time,">="&$C63,d_Time,"<="&$D63,d_Status,"Delivered",d_Year,$P$4,d_City,$Q$4,d_Cuisine,$R$4,d_Pay,$S$4,d_Type,$T$4),0) -> 4.0827068
B64: 41–50 min | C64: 41 | D64: 50 | E64: =COUNTIFS(d_Time,">="&$C64,d_Time,"<="&$D64,d_Status,"Delivered",d_Year,$P$4,d_City,$Q$4,d_Cuisine,$R$4,d_Pay,$S$4,d_Type,$T$4) -> 143 | F64: =IFERROR(E64/COUNTIFS(d_Status,"Delivered",d_Year,$P$4,d_City,$Q$4,d_Cuisine,$R$4,d_Pay,$S$4,d_Type,$T$4),0) -> 0.18078382 | G64: =IFERROR(AVERAGEIFS(d_CRating,d_Time,">="&$C64,d_Time,"<="&$D64,d_Status,"Delivered",d_Year,$P$4,d_City,$Q$4,d_Cuisine,$R$4,d_Pay,$S$4,d_Type,$T$4),0) -> 3.9090909
B65: 51–60 min | C65: 51 | D65: 60 | E65: =COUNTIFS(d_Time,">="&$C65,d_Time,"<="&$D65,d_Status,"Delivered",d_Year,$P$4,d_City,$Q$4,d_Cuisine,$R$4,d_Pay,$S$4,d_Type,$T$4) -> 142 | F65: =IFERROR(E65/COUNTIFS(d_Status,"Delivered",d_Year,$P$4,d_City,$Q$4,d_Cuisine,$R$4,d_Pay,$S$4,d_Type,$T$4),0) -> 0.1795196 | G65: =IFERROR(AVERAGEIFS(d_CRating,d_Time,">="&$C65,d_Time,"<="&$D65,d_Status,"Delivered",d_Year,$P$4,d_City,$Q$4,d_Cuisine,$R$4,d_Pay,$S$4,d_Type,$T$4),0) -> 4.0070423
B66: 61–70 min | C66: 61 | D66: 70 | E66: =COUNTIFS(d_Time,">="&$C66,d_Time,"<="&$D66,d_Status,"Delivered",d_Year,$P$4,d_City,$Q$4,d_Cuisine,$R$4,d_Pay,$S$4,d_Type,$T$4) -> 125 | F66: =IFERROR(E66/COUNTIFS(d_Status,"Delivered",d_Year,$P$4,d_City,$Q$4,d_Cuisine,$R$4,d_Pay,$S$4,d_Type,$T$4),0) -> 0.15802781 | G66: =IFERROR(AVERAGEIFS(d_CRating,d_Time,">="&$C66,d_Time,"<="&$D66,d_Status,"Delivered",d_Year,$P$4,d_City,$Q$4,d_Cuisine,$R$4,d_Pay,$S$4,d_Type,$T$4),0) -> 3.976
B67: Total / Overall | E67: =SUM(E61:E66) -> 791 | F67: =SUM(F61:F66) -> 1
B68: Band limits are inputs (blue). Lowest delivery time in data is 15 min, so the first band starts at 15.
B71: Avg delivery time by city
B72: City | C72: Delivered | D72: Avg time (min) | E72: On-time % (≤ SLA)
B73: Delhi | C73: =COUNTIFS(d_City,$B73,d_Status,"Delivered",d_Year,$P$4,d_City,$Q$4,d_Cuisine,$R$4,d_Pay,$S$4,d_Type,$T$4) -> 81 | D73: =IFERROR(AVERAGEIFS(d_Time,d_City,$B73,d_Status,"Delivered",d_Year,$P$4,d_City,$Q$4,d_Cuisine,$R$4,d_Pay,$S$4,d_Type,$T$4),0) -> 40.37037 | E73: =IFERROR(COUNTIFS(d_City,$B73,d_Status,"Delivered",d_Time,"<="&$M$4,d_Year,$P$4,d_City,$Q$4,d_Cuisine,$R$4,d_Pay,$S$4,d_Type,$T$4)/C73,0) -> 0.56790123
B74: Ahmedabad | C74: =COUNTIFS(d_City,$B74,d_Status,"Delivered",d_Year,$P$4,d_City,$Q$4,d_Cuisine,$R$4,d_Pay,$S$4,d_Type,$T$4) -> 80 | D74: =IFERROR(AVERAGEIFS(d_Time,d_City,$B74,d_Status,"Delivered",d_Year,$P$4,d_City,$Q$4,d_Cuisine,$R$4,d_Pay,$S$4,d_Type,$T$4),0) -> 42.8625 | E74: =IFERROR(COUNTIFS(d_City,$B74,d_Status,"Delivered",d_Time,"<="&$M$4,d_Year,$P$4,d_City,$Q$4,d_Cuisine,$R$4,d_Pay,$S$4,d_Type,$T$4)/C74,0) -> 0.575
B75: Bengaluru | C75: =COUNTIFS(d_City,$B75,d_Status,"Delivered",d_Year,$P$4,d_City,$Q$4,d_Cuisine,$R$4,d_Pay,$S$4,d_Type,$T$4) -> 71 | D75: =IFERROR(AVERAGEIFS(d_Time,d_City,$B75,d_Status,"Delivered",d_Year,$P$4,d_City,$Q$4,d_Cuisine,$R$4,d_Pay,$S$4,d_Type,$T$4),0) -> 45.746479 | E75: =IFERROR(COUNTIFS(d_City,$B75,d_Status,"Delivered",d_Time,"<="&$M$4,d_Year,$P$4,d_City,$Q$4,d_Cuisine,$R$4,d_Pay,$S$4,d_Type,$T$4)/C75,0) -> 0.43661972
B76: Chennai | C76: =COUNTIFS(d_City,$B76,d_Status,"Delivered",d_Year,$P$4,d_City,$Q$4,d_Cuisine,$R$4,d_Pay,$S$4,d_Type,$T$4) -> 72 | D76: =IFERROR(AVERAGEIFS(d_Time,d_City,$B76,d_Status,"Delivered",d_Year,$P$4,d_City,$Q$4,d_Cuisine,$R$4,d_Pay,$S$4,d_Type,$T$4),0) -> 39.458333 | E76: =IFERROR(COUNTIFS(d_City,$B76,d_Status,"Delivered",d_Time,"<="&$M$4,d_Year,$P$4,d_City,$Q$4,d_Cuisine,$R$4,d_Pay,$S$4,d_Type,$T$4)/C76,0) -> 0.61111111
B77: Noida | C77: =COUNTIFS(d_City,$B77,d_Status,"Delivered",d_Year,$P$4,d_City,$Q$4,d_Cuisine,$R$4,d_Pay,$S$4,d_Type,$T$4) -> 67 | D77: =IFERROR(AVERAGEIFS(d_Time,d_City,$B77,d_Status,"Delivered",d_Year,$P$4,d_City,$Q$4,d_Cuisine,$R$4,d_Pay,$S$4,d_Type,$T$4),0) -> 43.80597 | E77: =IFERROR(COUNTIFS(d_City,$B77,d_Status,"Delivered",d_Time,"<="&$M$4,d_Year,$P$4,d_City,$Q$4,d_Cuisine,$R$4,d_Pay,$S$4,d_Type,$T$4)/C77,0) -> 0.50746269
B78: Jaipur | C78: =COUNTIFS(d_City,$B78,d_Status,"Delivered",d_Year,$P$4,d_City,$Q$4,d_Cuisine,$R$4,d_Pay,$S$4,d_Type,$T$4) -> 71 | D78: =IFERROR(AVERAGEIFS(d_Time,d_City,$B78,d_Status,"Delivered",d_Year,$P$4,d_City,$Q$4,d_Cuisine,$R$4,d_Pay,$S$4,d_Type,$T$4),0) -> 39.690141 | E78: =IFERROR(COUNTIFS(d_City,$B78,d_Status,"Delivered",d_Time,"<="&$M$4,d_Year,$P$4,d_City,$Q$4,d_Cuisine,$R$4,d_Pay,$S$4,d_Type,$T$4)/C78,0) -> 0.5915493
B79: Hyderabad | C79: =COUNTIFS(d_City,$B79,d_Status,"Delivered",d_Year,$P$4,d_City,$Q$4,d_Cuisine,$R$4,d_Pay,$S$4,d_Type,$T$4) -> 57 | D79: =IFERROR(AVERAGEIFS(d_Time,d_City,$B79,d_Status,"Delivered",d_Year,$P$4,d_City,$Q$4,d_Cuisine,$R$4,d_Pay,$S$4,d_Type,$T$4),0) -> 40.052632 | E79: =IFERROR(COUNTIFS(d_City,$B79,d_Status,"Delivered",d_Time,"<="&$M$4,d_Year,$P$4,d_City,$Q$4,d_Cuisine,$R$4,d_Pay,$S$4,d_Type,$T$4)/C79,0) -> 0.59649123
B80: Pune | C80: =COUNTIFS(d_City,$B80,d_Status,"Delivered",d_Year,$P$4,d_City,$Q$4,d_Cuisine,$R$4,d_Pay,$S$4,d_Type,$T$4) -> 61 | D80: =IFERROR(AVERAGEIFS(d_Time,d_City,$B80,d_Status,"Delivered",d_Year,$P$4,d_City,$Q$4,d_Cuisine,$R$4,d_Pay,$S$4,d_Type,$T$4),0) -> 40.016393 | E80: =IFERROR(COUNTIFS(d_City,$B80,d_Status,"Delivered",d_Time,"<="&$M$4,d_Year,$P$4,d_City,$Q$4,d_Cuisine,$R$4,d_Pay,$S$4,d_Type,$T$4)/C80,0) -> 0.63934426
B81: Kolkata | C81: =COUNTIFS(d_City,$B81,d_Status,"Delivered",d_Year,$P$4,d_City,$Q$4,d_Cuisine,$R$4,d_Pay,$S$4,d_Type,$T$4) -> 62 | D81: =IFERROR(AVERAGEIFS(d_Time,d_City,$B81,d_Status,"Delivered",d_Year,$P$4,d_City,$Q$4,d_Cuisine,$R$4,d_Pay,$S$4,d_Type,$T$4),0) -> 41.806452 | E81: =IFERROR(COUNTIFS(d_City,$B81,d_Status,"Delivered",d_Time,"<="&$M$4,d_Year,$P$4,d_City,$Q$4,d_Cuisine,$R$4,d_Pay,$S$4,d_Type,$T$4)/C81,0) -> 0.64516129
B82: Lucknow | C82: =COUNTIFS(d_City,$B82,d_Status,"Delivered",d_Year,$P$4,d_City,$Q$4,d_Cuisine,$R$4,d_Pay,$S$4,d_Type,$T$4) -> 61 | D82: =IFERROR(AVERAGEIFS(d_Time,d_City,$B82,d_Status,"Delivered",d_Year,$P$4,d_City,$Q$4,d_Cuisine,$R$4,d_Pay,$S$4,d_Type,$T$4),0) -> 41.311475 | E82: =IFERROR(COUNTIFS(d_City,$B82,d_Status,"Delivered",d_Time,"<="&$M$4,d_Year,$P$4,d_City,$Q$4,d_Cuisine,$R$4,d_Pay,$S$4,d_Type,$T$4)/C82,0) -> 0.54098361
B83: Mumbai | C83: =COUNTIFS(d_City,$B83,d_Status,"Delivered",d_Year,$P$4,d_City,$Q$4,d_Cuisine,$R$4,d_Pay,$S$4,d_Type,$T$4) -> 53 | D83: =IFERROR(AVERAGEIFS(d_Time,d_City,$B83,d_Status,"Delivered",d_Year,$P$4,d_City,$Q$4,d_Cuisine,$R$4,d_Pay,$S$4,d_Type,$T$4),0) -> 39.849057 | E83: =IFERROR(COUNTIFS(d_City,$B83,d_Status,"Delivered",d_Time,"<="&$M$4,d_Year,$P$4,d_City,$Q$4,d_Cuisine,$R$4,d_Pay,$S$4,d_Type,$T$4)/C83,0) -> 0.66037736
B84: Gurugram | C84: =COUNTIFS(d_City,$B84,d_Status,"Delivered",d_Year,$P$4,d_City,$Q$4,d_Cuisine,$R$4,d_Pay,$S$4,d_Type,$T$4) -> 55 | D84: =IFERROR(AVERAGEIFS(d_Time,d_City,$B84,d_Status,"Delivered",d_Year,$P$4,d_City,$Q$4,d_Cuisine,$R$4,d_Pay,$S$4,d_Type,$T$4),0) -> 42.945455 | E84: =IFERROR(COUNTIFS(d_City,$B84,d_Status,"Delivered",d_Time,"<="&$M$4,d_Year,$P$4,d_City,$Q$4,d_Cuisine,$R$4,d_Pay,$S$4,d_Type,$T$4)/C84,0) -> 0.54545455
B87: Avg delivery time by distance band
B88: Distance band | C88: Min km (>) | D88: Max km (<=) | E88: Delivered | F88: Avg time (min) | G88: Min per km
B89: 0–3 km | C89: 0 | D89: 3 | E89: =COUNTIFS(d_Dist,">"&$C89,d_Dist,"<="&$D89,d_Status,"Delivered",d_Year,$P$4,d_City,$Q$4,d_Cuisine,$R$4,d_Pay,$S$4,d_Type,$T$4) -> 146 | F89: =IFERROR(AVERAGEIFS(d_Time,d_Dist,">"&$C89,d_Dist,"<="&$D89,d_Status,"Delivered",d_Year,$P$4,d_City,$Q$4,d_Cuisine,$R$4,d_Pay,$S$4,d_Type,$T$4),0) -> 40.239726 | G89: =IFERROR(F89/((C89+D89)/2),0) -> 26.826484
B90: 3–6 km | C90: 3 | D90: 6 | E90: =COUNTIFS(d_Dist,">"&$C90,d_Dist,"<="&$D90,d_Status,"Delivered",d_Year,$P$4,d_City,$Q$4,d_Cuisine,$R$4,d_Pay,$S$4,d_Type,$T$4) -> 164 | F90: =IFERROR(AVERAGEIFS(d_Time,d_Dist,">"&$C90,d_Dist,"<="&$D90,d_Status,"Delivered",d_Year,$P$4,d_City,$Q$4,d_Cuisine,$R$4,d_Pay,$S$4,d_Type,$T$4),0) -> 41.823171 | G90: =IFERROR(F90/((C90+D90)/2),0) -> 9.2940379
B91: 6–9 km | C91: 6 | D91: 9 | E91: =COUNTIFS(d_Dist,">"&$C91,d_Dist,"<="&$D91,d_Status,"Delivered",d_Year,$P$4,d_City,$Q$4,d_Cuisine,$R$4,d_Pay,$S$4,d_Type,$T$4) -> 158 | F91: =IFERROR(AVERAGEIFS(d_Time,d_Dist,">"&$C91,d_Dist,"<="&$D91,d_Status,"Delivered",d_Year,$P$4,d_City,$Q$4,d_Cuisine,$R$4,d_Pay,$S$4,d_Type,$T$4),0) -> 40.443038 | G91: =IFERROR(F91/((C91+D91)/2),0) -> 5.3924051
B92: 9–12 km | C92: 9 | D92: 12 | E92: =COUNTIFS(d_Dist,">"&$C92,d_Dist,"<="&$D92,d_Status,"Delivered",d_Year,$P$4,d_City,$Q$4,d_Cuisine,$R$4,d_Pay,$S$4,d_Type,$T$4) -> 155 | F92: =IFERROR(AVERAGEIFS(d_Time,d_Dist,">"&$C92,d_Dist,"<="&$D92,d_Status,"Delivered",d_Year,$P$4,d_City,$Q$4,d_Cuisine,$R$4,d_Pay,$S$4,d_Type,$T$4),0) -> 41.187097 | G92: =IFERROR(F92/((C92+D92)/2),0) -> 3.9225806
B93: 12–15 km | C93: 12 | D93: 15 | E93: =COUNTIFS(d_Dist,">"&$C93,d_Dist,"<="&$D93,d_Status,"Delivered",d_Year,$P$4,d_City,$Q$4,d_Cuisine,$R$4,d_Pay,$S$4,d_Type,$T$4) -> 168 | F93: =IFERROR(AVERAGEIFS(d_Time,d_Dist,">"&$C93,d_Dist,"<="&$D93,d_Status,"Delivered",d_Year,$P$4,d_City,$Q$4,d_Cuisine,$R$4,d_Pay,$S$4,d_Type,$T$4),0) -> 43.708333 | G93: =IFERROR(F93/((C93+D93)/2),0) -> 3.2376543
B94: Min per km uses the band mid-point distance.
B97: Monthly avg delivery time
B98: Month | C98: Month start | D98: Delivered | E98: Avg time (min) | F98: On-time %
B99: =TEXT(C99,"mmm-yy") -> Jan-25 | C99: 45658 | D99: =COUNTIFS(d_Date,">="&$C99,d_Date,"<"&EDATE($C99,1),d_Status,"Delivered",d_Year,$P$4,d_City,$Q$4,d_Cuisine,$R$4,d_Pay,$S$4,d_Type,$T$4) -> 66 | E99: =IFERROR(AVERAGEIFS(d_Time,d_Date,">="&$C99,d_Date,"<"&EDATE($C99,1),d_Status,"Delivered",d_Year,$P$4,d_City,$Q$4,d_Cuisine,$R$4,d_Pay,$S$4,d_Type,$T$4),0) -> 41.984848 | F99: =IFERROR(COUNTIFS(d_Date,">="&$C99,d_Date,"<"&EDATE($C99,1),d_Status,"Delivered",d_Time,"<="&$M$4,d_Year,$P$4,d_City,$Q$4,d_Cuisine,$R$4,d_Pay,$S$4,d_Type,$T$4)/D99,0) -> 0.54545455
B100: =TEXT(C100,"mmm-yy") -> Feb-25 | C100: 45689 | D100: =COUNTIFS(d_Date,">="&$C100,d_Date,"<"&EDATE($C100,1),d_Status,"Delivered",d_Year,$P$4,d_City,$Q$4,d_Cuisine,$R$4,d_Pay,$S$4,d_Type,$T$4) -> 48 | E100: =IFERROR(AVERAGEIFS(d_Time,d_Date,">="&$C100,d_Date,"<"&EDATE($C100,1),d_Status,"Delivered",d_Year,$P$4,d_City,$Q$4,d_Cuisine,$R$4,d_Pay,$S$4,d_Type,$T$4),0) -> 44.104167 | F100: =IFERROR(COUNTIFS(d_Date,">="&$C100,d_Date,"<"&EDATE($C100,1),d_Status,"Delivered",d_Time,"<="&$M$4,d_Year,$P$4,d_City,$Q$4,d_Cuisine,$R$4,d_Pay,$S$4,d_Type,$T$4)/D100,0) -> 0.47916667
B101: =TEXT(C101,"mmm-yy") -> Mar-25 | C101: 45717 | D101: =COUNTIFS(d_Date,">="&$C101,d_Date,"<"&EDATE($C101,1),d_Status,"Delivered",d_Year,$P$4,d_City,$Q$4,d_Cuisine,$R$4,d_Pay,$S$4,d_Type,$T$4) -> 55 | E101: =IFERROR(AVERAGEIFS(d_Time,d_Date,">="&$C101,d_Date,"<"&EDATE($C101,1),d_Status,"Delivered",d_Year,$P$4,d_City,$Q$4,d_Cuisine,$R$4,d_Pay,$S$4,d_Type,$T$4),0) -> 40.418182 | F101: =IFERROR(COUNTIFS(d_Date,">="&$C101,d_Date,"<"&EDATE($C101,1),d_Status,"Delivered",d_Time,"<="&$M$4,d_Year,$P$4,d_City,$Q$4,d_Cuisine,$R$4,d_Pay,$S$4,d_Type,$T$4)/D101,0) -> 0.58181818
B102: =TEXT(C102,"mmm-yy") -> Apr-25 | C102: 45748 | D102: =COUNTIFS(d_Date,">="&$C102,d_Date,"<"&EDATE($C102,1),d_Status,"Delivered",d_Year,$P$4,d_City,$Q$4,d_Cuisine,$R$4,d_Pay,$S$4,d_Type,$T$4) -> 61 | E102: =IFERROR(AVERAGEIFS(d_Time,d_Date,">="&$C102,d_Date,"<"&EDATE($C102,1),d_Status,"Delivered",d_Year,$P$4,d_City,$Q$4,d_Cuisine,$R$4,d_Pay,$S$4,d_Type,$T$4),0) -> 43.57377 | F102: =IFERROR(COUNTIFS(d_Date,">="&$C102,d_Date,"<"&EDATE($C102,1),d_Status,"Delivered",d_Time,"<="&$M$4,d_Year,$P$4,d_City,$Q$4,d_Cuisine,$R$4,d_Pay,$S$4,d_Type,$T$4)/D102,0) -> 0.50819672
B103: =TEXT(C103,"mmm-yy") -> May-25 | C103: 45778 | D103: =COUNTIFS(d_Date,">="&$C103,d_Date,"<"&EDATE($C103,1),d_Status,"Delivered",d_Year,$P$4,d_City,$Q$4,d_Cuisine,$R$4,d_Pay,$S$4,d_Type,$T$4) -> 59 | E103: =IFERROR(AVERAGEIFS(d_Time,d_Date,">="&$C103,d_Date,"<"&EDATE($C103,1),d_Status,"Delivered",d_Year,$P$4,d_City,$Q$4,d_Cuisine,$R$4,d_Pay,$S$4,d_Type,$T$4),0) -> 39.915254 | F103: =IFERROR(COUNTIFS(d_Date,">="&$C103,d_Date,"<"&EDATE($C103,1),d_Status,"Delivered",d_Time,"<="&$M$4,d_Year,$P$4,d_City,$Q$4,d_Cuisine,$R$4,d_Pay,$S$4,d_Type,$T$4)/D103,0) -> 0.66101695
B104: =TEXT(C104,"mmm-yy") -> Jun-25 | C104: 45809 | D104: =COUNTIFS(d_Date,">="&$C104,d_Date,"<"&EDATE($C104,1),d_Status,"Delivered",d_Year,$P$4,d_City,$Q$4,d_Cuisine,$R$4,d_Pay,$S$4,d_Type,$T$4) -> 58 | E104: =IFERROR(AVERAGEIFS(d_Time,d_Date,">="&$C104,d_Date,"<"&EDATE($C104,1),d_Status,"Delivered",d_Year,$P$4,d_City,$Q$4,d_Cuisine,$R$4,d_Pay,$S$4,d_Type,$T$4),0) -> 39.172414 | F104: =IFERROR(COUNTIFS(d_Date,">="&$C104,d_Date,"<"&EDATE($C104,1),d_Status,"Delivered",d_Time,"<="&$M$4,d_Year,$P$4,d_City,$Q$4,d_Cuisine,$R$4,d_Pay,$S$4,d_Type,$T$4)/D104,0) -> 0.68965517
B105: =TEXT(C105,"mmm-yy") -> Jul-25 | C105: 45839 | D105: =COUNTIFS(d_Date,">="&$C105,d_Date,"<"&EDATE($C105,1),d_Status,"Delivered",d_Year,$P$4,d_City,$Q$4,d_Cuisine,$R$4,d_Pay,$S$4,d_Type,$T$4) -> 59 | E105: =IFERROR(AVERAGEIFS(d_Time,d_Date,">="&$C105,d_Date,"<"&EDATE($C105,1),d_Status,"Delivered",d_Year,$P$4,d_City,$Q$4,d_Cuisine,$R$4,d_Pay,$S$4,d_Type,$T$4),0) -> 42.338983 | F105: =IFERROR(COUNTIFS(d_Date,">="&$C105,d_Date,"<"&EDATE($C105,1),d_Status,"Delivered",d_Time,"<="&$M$4,d_Year,$P$4,d_City,$Q$4,d_Cuisine,$R$4,d_Pay,$S$4,d_Type,$T$4)/D105,0) -> 0.49152542
B106: =TEXT(C106,"mmm-yy") -> Aug-25 | C106: 45870 | D106: =COUNTIFS(d_Date,">="&$C106,d_Date,"<"&EDATE($C106,1),d_Status,"Delivered",d_Year,$P$4,d_City,$Q$4,d_Cuisine,$R$4,d_Pay,$S$4,d_Type,$T$4) -> 70 | E106: =IFERROR(AVERAGEIFS(d_Time,d_Date,">="&$C106,d_Date,"<"&EDATE($C106,1),d_Status,"Delivered",d_Year,$P$4,d_City,$Q$4,d_Cuisine,$R$4,d_Pay,$S$4,d_Type,$T$4),0) -> 38.914286 | F106: =IFERROR(COUNTIFS(d_Date,">="&$C106,d_Date,"<"&EDATE($C106,1),d_Status,"Delivered",d_Time,"<="&$M$4,d_Year,$P$4,d_City,$Q$4,d_Cuisine,$R$4,d_Pay,$S$4,d_Type,$T$4)/D106,0) -> 0.62857143
B107: =TEXT(C107,"mmm-yy") -> Sep-25 | C107: 45901 | D107: =COUNTIFS(d_Date,">="&$C107,d_Date,"<"&EDATE($C107,1),d_Status,"Delivered",d_Year,$P$4,d_City,$Q$4,d_Cuisine,$R$4,d_Pay,$S$4,d_Type,$T$4) -> 60 | E107: =IFERROR(AVERAGEIFS(d_Time,d_Date,">="&$C107,d_Date,"<"&EDATE($C107,1),d_Status,"Delivered",d_Year,$P$4,d_City,$Q$4,d_Cuisine,$R$4,d_Pay,$S$4,d_Type,$T$4),0) -> 40.85 | F107: =IFERROR(COUNTIFS(d_Date,">="&$C107,d_Date,"<"&EDATE($C107,1),d_Status,"Delivered",d_Time,"<="&$M$4,d_Year,$P$4,d_City,$Q$4,d_Cuisine,$R$4,d_Pay,$S$4,d_Type,$T$4)/D107,0) -> 0.58333333
B108: =TEXT(C108,"mmm-yy") -> Oct-25 | C108: 45931 | D108: =COUNTIFS(d_Date,">="&$C108,d_Date,"<"&EDATE($C108,1),d_Status,"Delivered",d_Year,$P$4,d_City,$Q$4,d_Cuisine,$R$4,d_Pay,$S$4,d_Type,$T$4) -> 63 | E108: =IFERROR(AVERAGEIFS(d_Time,d_Date,">="&$C108,d_Date,"<"&EDATE($C108,1),d_Status,"Delivered",d_Year,$P$4,d_City,$Q$4,d_Cuisine,$R$4,d_Pay,$S$4,d_Type,$T$4),0) -> 41.349206 | F108: =IFERROR(COUNTIFS(d_Date,">="&$C108,d_Date,"<"&EDATE($C108,1),d_Status,"Delivered",d_Time,"<="&$M$4,d_Year,$P$4,d_City,$Q$4,d_Cuisine,$R$4,d_Pay,$S$4,d_Type,$T$4)/D108,0) -> 0.63492063
B109: =TEXT(C109,"mmm-yy") -> Nov-25 | C109: 45962 | D109: =COUNTIFS(d_Date,">="&$C109,d_Date,"<"&EDATE($C109,1),d_Status,"Delivered",d_Year,$P$4,d_City,$Q$4,d_Cuisine,$R$4,d_Pay,$S$4,d_Type,$T$4) -> 61 | E109: =IFERROR(AVERAGEIFS(d_Time,d_Date,">="&$C109,d_Date,"<"&EDATE($C109,1),d_Status,"Delivered",d_Year,$P$4,d_City,$Q$4,d_Cuisine,$R$4,d_Pay,$S$4,d_Type,$T$4),0) -> 45.770492 | F109: =IFERROR(COUNTIFS(d_Date,">="&$C109,d_Date,"<"&EDATE($C109,1),d_Status,"Delivered",d_Time,"<="&$M$4,d_Year,$P$4,d_City,$Q$4,d_Cuisine,$R$4,d_Pay,$S$4,d_Type,$T$4)/D109,0) -> 0.47540984
B110: =TEXT(C110,"mmm-yy") -> Dec-25 | C110: 45992 | D110: =COUNTIFS(d_Date,">="&$C110,d_Date,"<"&EDATE($C110,1),d_Status,"Delivered",d_Year,$P$4,d_City,$Q$4,d_Cuisine,$R$4,d_Pay,$S$4,d_Type,$T$4) -> 61 | E110: =IFERROR(AVERAGEIFS(d_Time,d_Date,">="&$C110,d_Date,"<"&EDATE($C110,1),d_Status,"Delivered",d_Year,$P$4,d_City,$Q$4,d_Cuisine,$R$4,d_Pay,$S$4,d_Type,$T$4),0) -> 42.737705 | F110: =IFERROR(COUNTIFS(d_Date,">="&$C110,d_Date,"<"&EDATE($C110,1),d_Status,"Delivered",d_Time,"<="&$M$4,d_Year,$P$4,d_City,$Q$4,d_Cuisine,$R$4,d_Pay,$S$4,d_Type,$T$4)/D110,0) -> 0.52459016
... B112: =TEXT(C112,"mmm-yy") -> Feb-26 | C112: 46054 | D112: =COUNTIFS(d_Date,">="&$C112,d_Date,"<"&EDATE($C112,1),d_Status,"Delivered",d_Year,$P$4,d_City,$Q$4,d_Cuisine,$R$4,d_Pay,$S$4,d_Type,$T$4) -> 7 | E112: =IFERROR(AVERAGEIFS(d_Time,d_Date,">="&$C112,d_Date,"<"&EDATE($C112,1),d_Status,"Delivered",d_Year,$P$4,d_City,$Q$4,d_Cuisine,$R$4,d_Pay,$S$4,d_Type,$T$4),0) -> 35 | F112: =IFERROR(COUNTIFS(d_Date,">="&$C112,d_Date,"<"&EDATE($C112,1),d_Status,"Delivered",d_Time,"<="&$M$4,d_Year,$P$4,d_City,$Q$4,d_Cuisine,$R$4,d_Pay,$S$4,d_Type,$T$4)/D112,0) -> 0.57142857
B115: Delivery time by order type
B116: Order type | C116: Delivered | D116: Avg time (min) | E116: Avg distance (km)
B117: Delivery | C117: =COUNTIFS(d_Type,$B117,d_Status,"Delivered",d_Year,$P$4,d_City,$Q$4,d_Cuisine,$R$4,d_Pay,$S$4,d_Type,$T$4) -> 592 | D117: =IFERROR(AVERAGEIFS(d_Time,d_Type,$B117,d_Status,"Delivered",d_Year,$P$4,d_City,$Q$4,d_Cuisine,$R$4,d_Pay,$S$4,d_Type,$T$4),0) -> 41.694257 | E117: =IFERROR(AVERAGEIFS(d_Dist,d_Type,$B117,d_Status,"Delivered",d_Year,$P$4,d_City,$Q$4,d_Cuisine,$R$4,d_Pay,$S$4,d_Type,$T$4),0) -> 7.6695946
B118: Pickup | C118: =COUNTIFS(d_Type,$B118,d_Status,"Delivered",d_Year,$P$4,d_City,$Q$4,d_Cuisine,$R$4,d_Pay,$S$4,d_Type,$T$4) -> 199 | D118: =IFERROR(AVERAGEIFS(d_Time,d_Type,$B118,d_Status,"Delivered",d_Year,$P$4,d_City,$Q$4,d_Cuisine,$R$4,d_Pay,$S$4,d_Type,$T$4),0) -> 41.045226 | E118: =IFERROR(AVERAGEIFS(d_Dist,d_Type,$B118,d_Status,"Delivered",d_Year,$P$4,d_City,$Q$4,d_Cuisine,$R$4,d_Pay,$S$4,d_Type,$T$4),0) -> 7.859799

Sheet Cancellation Analysis
B2: Cancellation Analysis
B3: Where and when orders get cancelled. Cancel rate = Cancelled ÷ all orders in the group. Lost value = Gross_Amount of cancelled orders. ▸ Use the yellow filters in row 4 – every KPI, chart and table updates. | L3: ← Back to Home
B4: Year: | C4: All | D4: City: | E4: All | F4: Cuisine: | G4: All | H4: Payment: | I4: All | J4: Order type: | K4: All | L4: ="Orders in view: "&TEXT(COUNTIFS(d_ID,"<>",d_Year,$P$4,d_City,$Q$4,d_Cuisine,$R$4,d_Pay,$S$4,d_Type,$T$4),"#,##0") -> Orders in view: 1,200 | P4: =IF(C4="All",">0",C4) -> >0 | Q4: =IF(E4="All","*",E4) -> * | R4: =IF(G4="All","*",G4) -> * | S4: =IF(I4="All","*",I4) -> * | T4: =IF(K4="All","*",K4) -> *
B5: CANCELLED ORDERS | D5: CANCELLATION RATE | F5: LOST ORDER VALUE | H5: AVG CANCELLED ORDER | J5: HIGHEST-RATE CITY | L5: PENDING ORDERS
B6: =COUNTIFS(d_Status,"Cancelled",d_Year,$P$4,d_City,$Q$4,d_Cuisine,$R$4,d_Pay,$S$4,d_Type,$T$4) -> 202 | D6: =IFERROR(COUNTIFS(d_Status,"Cancelled",d_Year,$P$4,d_City,$Q$4,d_Cuisine,$R$4,d_Pay,$S$4,d_Type,$T$4)/COUNTIFS(d_ID,"<>",d_Year,$P$4,d_City,$Q$4,d_Cuisine,$R$4,d_Pay,$S$4,d_Type,$T$4),0) -> 0.16833333 | F6: =SUMIFS(d_Gross,d_Status,"Cancelled",d_Year,$P$4,d_City,$Q$4,d_Cuisine,$R$4,d_Pay,$S$4,d_Type,$T$4) -> 192229 | H6: =IFERROR(AVERAGEIFS(d_Gross,d_Status,"Cancelled",d_Year,$P$4,d_City,$Q$4,d_Cuisine,$R$4,d_Pay,$S$4,d_Type,$T$4),0) -> 951.62871 | J6: =INDEX(B80:B91,MATCH(MAX(E80:E91),E80:E91,0)) -> Noida | L6: =COUNTIFS(d_Status,"Pending",d_Year,$P$4,d_City,$Q$4,d_Cuisine,$R$4,d_Pay,$S$4,d_Type,$T$4) -> 207
B7: Total cancelled | D7: Cancelled ÷ all orders | F7: Gross value cancelled | H7: Gross value per order | J7: Highest cancel rate | L7: Could still convert / cancel
B57: Supporting data (feeds the charts above)
B59: Monthly cancellations
B60: Month | C60: Month start | D60: Orders | E60: Cancelled | F60: Cancel rate | G60: Lost value
B61: =TEXT(C61,"mmm-yy") -> Jan-25 | C61: 45658 | D61: =COUNTIFS(d_Date,">="&$C61,d_Date,"<"&EDATE($C61,1),d_Year,$P$4,d_City,$Q$4,d_Cuisine,$R$4,d_Pay,$S$4,d_Type,$T$4) -> 93 | E61: =COUNTIFS(d_Date,">="&$C61,d_Date,"<"&EDATE($C61,1),d_Status,"Cancelled",d_Year,$P$4,d_City,$Q$4,d_Cuisine,$R$4,d_Pay,$S$4,d_Type,$T$4) -> 15 | F61: =IFERROR(E61/D61,0) -> 0.16129032 | G61: =SUMIFS(d_Gross,d_Date,">="&$C61,d_Date,"<"&EDATE($C61,1),d_Status,"Cancelled",d_Year,$P$4,d_City,$Q$4,d_Cuisine,$R$4,d_Pay,$S$4,d_Type,$T$4) -> 12591
B62: =TEXT(C62,"mmm-yy") -> Feb-25 | C62: 45689 | D62: =COUNTIFS(d_Date,">="&$C62,d_Date,"<"&EDATE($C62,1),d_Year,$P$4,d_City,$Q$4,d_Cuisine,$R$4,d_Pay,$S$4,d_Type,$T$4) -> 84 | E62: =COUNTIFS(d_Date,">="&$C62,d_Date,"<"&EDATE($C62,1),d_Status,"Cancelled",d_Year,$P$4,d_City,$Q$4,d_Cuisine,$R$4,d_Pay,$S$4,d_Type,$T$4) -> 15 | F62: =IFERROR(E62/D62,0) -> 0.17857143 | G62: =SUMIFS(d_Gross,d_Date,">="&$C62,d_Date,"<"&EDATE($C62,1),d_Status,"Cancelled",d_Year,$P$4,d_City,$Q$4,d_Cuisine,$R$4,d_Pay,$S$4,d_Type,$T$4) -> 12544
B63: =TEXT(C63,"mmm-yy") -> Mar-25 | C63: 45717 | D63: =COUNTIFS(d_Date,">="&$C63,d_Date,"<"&EDATE($C63,1),d_Year,$P$4,d_City,$Q$4,d_Cuisine,$R$4,d_Pay,$S$4,d_Type,$T$4) -> 93 | E63: =COUNTIFS(d_Date,">="&$C63,d_Date,"<"&EDATE($C63,1),d_Status,"Cancelled",d_Year,$P$4,d_City,$Q$4,d_Cuisine,$R$4,d_Pay,$S$4,d_Type,$T$4) -> 19 | F63: =IFERROR(E63/D63,0) -> 0.20430108 | G63: =SUMIFS(d_Gross,d_Date,">="&$C63,d_Date,"<"&EDATE($C63,1),d_Status,"Cancelled",d_Year,$P$4,d_City,$Q$4,d_Cuisine,$R$4,d_Pay,$S$4,d_Type,$T$4) -> 17642
B64: =TEXT(C64,"mmm-yy") -> Apr-25 | C64: 45748 | D64: =COUNTIFS(d_Date,">="&$C64,d_Date,"<"&EDATE($C64,1),d_Year,$P$4,d_City,$Q$4,d_Cuisine,$R$4,d_Pay,$S$4,d_Type,$T$4) -> 90 | E64: =COUNTIFS(d_Date,">="&$C64,d_Date,"<"&EDATE($C64,1),d_Status,"Cancelled",d_Year,$P$4,d_City,$Q$4,d_Cuisine,$R$4,d_Pay,$S$4,d_Type,$T$4) -> 17 | F64: =IFERROR(E64/D64,0) -> 0.18888889 | G64: =SUMIFS(d_Gross,d_Date,">="&$C64,d_Date,"<"&EDATE($C64,1),d_Status,"Cancelled",d_Year,$P$4,d_City,$Q$4,d_Cuisine,$R$4,d_Pay,$S$4,d_Type,$T$4) -> 16746
B65: =TEXT(C65,"mmm-yy") -> May-25 | C65: 45778 | D65: =COUNTIFS(d_Date,">="&$C65,d_Date,"<"&EDATE($C65,1),d_Year,$P$4,d_City,$Q$4,d_Cuisine,$R$4,d_Pay,$S$4,d_Type,$T$4) -> 93 | E65: =COUNTIFS(d_Date,">="&$C65,d_Date,"<"&EDATE($C65,1),d_Status,"Cancelled",d_Year,$P$4,d_City,$Q$4,d_Cuisine,$R$4,d_Pay,$S$4,d_Type,$T$4) -> 16 | F65: =IFERROR(E65/D65,0) -> 0.17204301 | G65: =SUMIFS(d_Gross,d_Date,">="&$C65,d_Date,"<"&EDATE($C65,1),d_Status,"Cancelled",d_Year,$P$4,d_City,$Q$4,d_Cuisine,$R$4,d_Pay,$S$4,d_Type,$T$4) -> 12109
B66: =TEXT(C66,"mmm-yy") -> Jun-25 | C66: 45809 | D66: =COUNTIFS(d_Date,">="&$C66,d_Date,"<"&EDATE($C66,1),d_Year,$P$4,d_City,$Q$4,d_Cuisine,$R$4,d_Pay,$S$4,d_Type,$T$4) -> 90 | E66: =COUNTIFS(d_Date,">="&$C66,d_Date,"<"&EDATE($C66,1),d_Status,"Cancelled",d_Year,$P$4,d_City,$Q$4,d_Cuisine,$R$4,d_Pay,$S$4,d_Type,$T$4) -> 19 | F66: =IFERROR(E66/D66,0) -> 0.21111111 | G66: =SUMIFS(d_Gross,d_Date,">="&$C66,d_Date,"<"&EDATE($C66,1),d_Status,"Cancelled",d_Year,$P$4,d_City,$Q$4,d_Cuisine,$R$4,d_Pay,$S$4,d_Type,$T$4) -> 21943
B67: =TEXT(C67,"mmm-yy") -> Jul-25 | C67: 45839 | D67: =COUNTIFS(d_Date,">="&$C67,d_Date,"<"&EDATE($C67,1),d_Year,$P$4,d_City,$Q$4,d_Cuisine,$R$4,d_Pay,$S$4,d_Type,$T$4) -> 93 | E67: =COUNTIFS(d_Date,">="&$C67,d_Date,"<"&EDATE($C67,1),d_Status,"Cancelled",d_Year,$P$4,d_City,$Q$4,d_Cuisine,$R$4,d_Pay,$S$4,d_Type,$T$4) -> 16 | F67: =IFERROR(E67/D67,0) -> 0.17204301 | G67: =SUMIFS(d_Gross,d_Date,">="&$C67,d_Date,"<"&EDATE($C67,1),d_Status,"Cancelled",d_Year,$P$4,d_City,$Q$4,d_Cuisine,$R$4,d_Pay,$S$4,d_Type,$T$4) -> 13821
B68: =TEXT(C68,"mmm-yy") -> Aug-25 | C68: 45870 | D68: =COUNTIFS(d_Date,">="&$C68,d_Date,"<"&EDATE($C68,1),d_Year,$P$4,d_City,$Q$4,d_Cuisine,$R$4,d_Pay,$S$4,d_Type,$T$4) -> 93 | E68: =COUNTIFS(d_Date,">="&$C68,d_Date,"<"&EDATE($C68,1),d_Status,"Cancelled",d_Year,$P$4,d_City,$Q$4,d_Cuisine,$R$4,d_Pay,$S$4,d_Type,$T$4) -> 12 | F68: =IFERROR(E68/D68,0) -> 0.12903226 | G68: =SUMIFS(d_Gross,d_Date,">="&$C68,d_Date,"<"&EDATE($C68,1),d_Status,"Cancelled",d_Year,$P$4,d_City,$Q$4,d_Cuisine,$R$4,d_Pay,$S$4,d_Type,$T$4) -> 12289
B69: =TEXT(C69,"mmm-yy") -> Sep-25 | C69: 45901 | D69: =COUNTIFS(d_Date,">="&$C69,d_Date,"<"&EDATE($C69,1),d_Year,$P$4,d_City,$Q$4,d_Cuisine,$R$4,d_Pay,$S$4,d_Type,$T$4) -> 90 | E69: =COUNTIFS(d_Date,">="&$C69,d_Date,"<"&EDATE($C69,1),d_Status,"Cancelled",d_Year,$P$4,d_City,$Q$4,d_Cuisine,$R$4,d_Pay,$S$4,d_Type,$T$4) -> 16 | F69: =IFERROR(E69/D69,0) -> 0.17777778 | G69: =SUMIFS(d_Gross,d_Date,">="&$C69,d_Date,"<"&EDATE($C69,1),d_Status,"Cancelled",d_Year,$P$4,d_City,$Q$4,d_Cuisine,$R$4,d_Pay,$S$4,d_Type,$T$4) -> 14909
B70: =TEXT(C70,"mmm-yy") -> Oct-25 | C70: 45931 | D70: =COUNTIFS(d_Date,">="&$C70,d_Date,"<"&EDATE($C70,1),d_Year,$P$4,d_City,$Q$4,d_Cuisine,$R$4,d_Pay,$S$4,d_Type,$T$4) -> 93 | E70: =COUNTIFS(d_Date,">="&$C70,d_Date,"<"&EDATE($C70,1),d_Status,"Cancelled",d_Year,$P$4,d_City,$Q$4,d_Cuisine,$R$4,d_Pay,$S$4,d_Type,$T$4) -> 15 | F70: =IFERROR(E70/D70,0) -> 0.16129032 | G70: =SUMIFS(d_Gross,d_Date,">="&$C70,d_Date,"<"&EDATE($C70,1),d_Status,"Cancelled",d_Year,$P$4,d_City,$Q$4,d_Cuisine,$R$4,d_Pay,$S$4,d_Type,$T$4) -> 13840
B71: =TEXT(C71,"mmm-yy") -> Nov-25 | C71: 45962 | D71: =COUNTIFS(d_Date,">="&$C71,d_Date,"<"&EDATE($C71,1),d_Year,$P$4,d_City,$Q$4,d_Cuisine,$R$4,d_Pay,$S$4,d_Type,$T$4) -> 90 | E71: =COUNTIFS(d_Date,">="&$C71,d_Date,"<"&EDATE($C71,1),d_Status,"Cancelled",d_Year,$P$4,d_City,$Q$4,d_Cuisine,$R$4,d_Pay,$S$4,d_Type,$T$4) -> 15 | F71: =IFERROR(E71/D71,0) -> 0.16666667 | G71: =SUMIFS(d_Gross,d_Date,">="&$C71,d_Date,"<"&EDATE($C71,1),d_Status,"Cancelled",d_Year,$P$4,d_City,$Q$4,d_Cuisine,$R$4,d_Pay,$S$4,d_Type,$T$4) -> 13546
B72: =TEXT(C72,"mmm-yy") -> Dec-25 | C72: 45992 | D72: =COUNTIFS(d_Date,">="&$C72,d_Date,"<"&EDATE($C72,1),d_Year,$P$4,d_City,$Q$4,d_Cuisine,$R$4,d_Pay,$S$4,d_Type,$T$4) -> 93 | E72: =COUNTIFS(d_Date,">="&$C72,d_Date,"<"&EDATE($C72,1),d_Status,"Cancelled",d_Year,$P$4,d_City,$Q$4,d_Cuisine,$R$4,d_Pay,$S$4,d_Type,$T$4) -> 16 | F72: =IFERROR(E72/D72,0) -> 0.17204301 | G72: =SUMIFS(d_Gross,d_Date,">="&$C72,d_Date,"<"&EDATE($C72,1),d_Status,"Cancelled",d_Year,$P$4,d_City,$Q$4,d_Cuisine,$R$4,d_Pay,$S$4,d_Type,$T$4) -> 19121
... B74: =TEXT(C74,"mmm-yy") -> Feb-26 | C74: 46054 | D74: =COUNTIFS(d_Date,">="&$C74,d_Date,"<"&EDATE($C74,1),d_Year,$P$4,d_City,$Q$4,d_Cuisine,$R$4,d_Pay,$S$4,d_Type,$T$4) -> 12 | E74: =COUNTIFS(d_Date,">="&$C74,d_Date,"<"&EDATE($C74,1),d_Status,"Cancelled",d_Year,$P$4,d_City,$Q$4,d_Cuisine,$R$4,d_Pay,$S$4,d_Type,$T$4) -> 1 | F74: =IFERROR(E74/D74,0) -> 0.083333333 | G74: =SUMIFS(d_Gross,d_Date,">="&$C74,d_Date,"<"&EDATE($C74,1),d_Status,"Cancelled",d_Year,$P$4,d_City,$Q$4,d_Cuisine,$R$4,d_Pay,$S$4,d_Type,$T$4) -> 1658
B75: Total / Overall | D75: =SUM(D61:D74) -> 1200 | E75: =SUM(E61:E74) -> 202 | F75: =IFERROR(E75/D75,0) -> 0.16833333 | G75: =SUM(G61:G74) -> 192229
B78: Cancellations by city
B79: City | C79: Orders | D79: Cancelled | E79: Cancel rate | F79: Lost value
B80: Delhi | C80: =COUNTIFS(d_City,$B80,d_Year,$P$4,d_City,$Q$4,d_Cuisine,$R$4,d_Pay,$S$4,d_Type,$T$4) -> 119 | D80: =COUNTIFS(d_City,$B80,d_Status,"Cancelled",d_Year,$P$4,d_City,$Q$4,d_Cuisine,$R$4,d_Pay,$S$4,d_Type,$T$4) -> 12 | E80: =IFERROR(D80/C80,0) -> 0.10084034 | F80: =SUMIFS(d_Gross,d_City,$B80,d_Status,"Cancelled",d_Year,$P$4,d_City,$Q$4,d_Cuisine,$R$4,d_Pay,$S$4,d_Type,$T$4) -> 11326
B81: Ahmedabad | C81: =COUNTIFS(d_City,$B81,d_Year,$P$4,d_City,$Q$4,d_Cuisine,$R$4,d_Pay,$S$4,d_Type,$T$4) -> 114 | D81: =COUNTIFS(d_City,$B81,d_Status,"Cancelled",d_Year,$P$4,d_City,$Q$4,d_Cuisine,$R$4,d_Pay,$S$4,d_Type,$T$4) -> 18 | E81: =IFERROR(D81/C81,0) -> 0.15789474 | F81: =SUMIFS(d_Gross,d_City,$B81,d_Status,"Cancelled",d_Year,$P$4,d_City,$Q$4,d_Cuisine,$R$4,d_Pay,$S$4,d_Type,$T$4) -> 16057
B82: Bengaluru | C82: =COUNTIFS(d_City,$B82,d_Year,$P$4,d_City,$Q$4,d_Cuisine,$R$4,d_Pay,$S$4,d_Type,$T$4) -> 110 | D82: =COUNTIFS(d_City,$B82,d_Status,"Cancelled",d_Year,$P$4,d_City,$Q$4,d_Cuisine,$R$4,d_Pay,$S$4,d_Type,$T$4) -> 22 | E82: =IFERROR(D82/C82,0) -> 0.2 | F82: =SUMIFS(d_Gross,d_City,$B82,d_Status,"Cancelled",d_Year,$P$4,d_City,$Q$4,d_Cuisine,$R$4,d_Pay,$S$4,d_Type,$T$4) -> 22012
B83: Chennai | C83: =COUNTIFS(d_City,$B83,d_Year,$P$4,d_City,$Q$4,d_Cuisine,$R$4,d_Pay,$S$4,d_Type,$T$4) -> 108 | D83: =COUNTIFS(d_City,$B83,d_Status,"Cancelled",d_Year,$P$4,d_City,$Q$4,d_Cuisine,$R$4,d_Pay,$S$4,d_Type,$T$4) -> 25 | E83: =IFERROR(D83/C83,0) -> 0.23148148 | F83: =SUMIFS(d_Gross,d_City,$B83,d_Status,"Cancelled",d_Year,$P$4,d_City,$Q$4,d_Cuisine,$R$4,d_Pay,$S$4,d_Type,$T$4) -> 27012
B84: Noida | C84: =COUNTIFS(d_City,$B84,d_Year,$P$4,d_City,$Q$4,d_Cuisine,$R$4,d_Pay,$S$4,d_Type,$T$4) -> 107 | D84: =COUNTIFS(d_City,$B84,d_Status,"Cancelled",d_Year,$P$4,d_City,$Q$4,d_Cuisine,$R$4,d_Pay,$S$4,d_Type,$T$4) -> 25 | E84: =IFERROR(D84/C84,0) -> 0.23364486 | F84: =SUMIFS(d_Gross,d_City,$B84,d_Status,"Cancelled",d_Year,$P$4,d_City,$Q$4,d_Cuisine,$R$4,d_Pay,$S$4,d_Type,$T$4) -> 21261
B85: Jaipur | C85: =COUNTIFS(d_City,$B85,d_Year,$P$4,d_City,$Q$4,d_Cuisine,$R$4,d_Pay,$S$4,d_Type,$T$4) -> 102 | D85: =COUNTIFS(d_City,$B85,d_Status,"Cancelled",d_Year,$P$4,d_City,$Q$4,d_Cuisine,$R$4,d_Pay,$S$4,d_Type,$T$4) -> 21 | E85: =IFERROR(D85/C85,0) -> 0.20588235 | F85: =SUMIFS(d_Gross,d_City,$B85,d_Status,"Cancelled",d_Year,$P$4,d_City,$Q$4,d_Cuisine,$R$4,d_Pay,$S$4,d_Type,$T$4) -> 14057
B86: Hyderabad | C86: =COUNTIFS(d_City,$B86,d_Year,$P$4,d_City,$Q$4,d_Cuisine,$R$4,d_Pay,$S$4,d_Type,$T$4) -> 96 | D86: =COUNTIFS(d_City,$B86,d_Status,"Cancelled",d_Year,$P$4,d_City,$Q$4,d_Cuisine,$R$4,d_Pay,$S$4,d_Type,$T$4) -> 13 | E86: =IFERROR(D86/C86,0) -> 0.13541667 | F86: =SUMIFS(d_Gross,d_City,$B86,d_Status,"Cancelled",d_Year,$P$4,d_City,$Q$4,d_Cuisine,$R$4,d_Pay,$S$4,d_Type,$T$4) -> 15951
B87: Pune | C87: =COUNTIFS(d_City,$B87,d_Year,$P$4,d_City,$Q$4,d_Cuisine,$R$4,d_Pay,$S$4,d_Type,$T$4) -> 96 | D87: =COUNTIFS(d_City,$B87,d_Status,"Cancelled",d_Year,$P$4,d_City,$Q$4,d_Cuisine,$R$4,d_Pay,$S$4,d_Type,$T$4) -> 17 | E87: =IFERROR(D87/C87,0) -> 0.17708333 | F87: =SUMIFS(d_Gross,d_City,$B87,d_Status,"Cancelled",d_Year,$P$4,d_City,$Q$4,d_Cuisine,$R$4,d_Pay,$S$4,d_Type,$T$4) -> 16863
B88: Kolkata | C88: =COUNTIFS(d_City,$B88,d_Year,$P$4,d_City,$Q$4,d_Cuisine,$R$4,d_Pay,$S$4,d_Type,$T$4) -> 94 | D88: =COUNTIFS(d_City,$B88,d_Status,"Cancelled",d_Year,$P$4,d_City,$Q$4,d_Cuisine,$R$4,d_Pay,$S$4,d_Type,$T$4) -> 14 | E88: =IFERROR(D88/C88,0) -> 0.14893617 | F88: =SUMIFS(d_Gross,d_City,$B88,d_Status,"Cancelled",d_Year,$P$4,d_City,$Q$4,d_Cuisine,$R$4,d_Pay,$S$4,d_Type,$T$4) -> 12823
B89: Lucknow | C89: =COUNTIFS(d_City,$B89,d_Year,$P$4,d_City,$Q$4,d_Cuisine,$R$4,d_Pay,$S$4,d_Type,$T$4) -> 91 | D89: =COUNTIFS(d_City,$B89,d_Status,"Cancelled",d_Year,$P$4,d_City,$Q$4,d_Cuisine,$R$4,d_Pay,$S$4,d_Type,$T$4) -> 11 | E89: =IFERROR(D89/C89,0) -> 0.12087912 | F89: =SUMIFS(d_Gross,d_City,$B89,d_Status,"Cancelled",d_Year,$P$4,d_City,$Q$4,d_Cuisine,$R$4,d_Pay,$S$4,d_Type,$T$4) -> 10501
B90: Mumbai | C90: =COUNTIFS(d_City,$B90,d_Year,$P$4,d_City,$Q$4,d_Cuisine,$R$4,d_Pay,$S$4,d_Type,$T$4) -> 83 | D90: =COUNTIFS(d_City,$B90,d_Status,"Cancelled",d_Year,$P$4,d_City,$Q$4,d_Cuisine,$R$4,d_Pay,$S$4,d_Type,$T$4) -> 15 | E90: =IFERROR(D90/C90,0) -> 0.18072289 | F90: =SUMIFS(d_Gross,d_City,$B90,d_Status,"Cancelled",d_Year,$P$4,d_City,$Q$4,d_Cuisine,$R$4,d_Pay,$S$4,d_Type,$T$4) -> 13296
B91: Gurugram | C91: =COUNTIFS(d_City,$B91,d_Year,$P$4,d_City,$Q$4,d_Cuisine,$R$4,d_Pay,$S$4,d_Type,$T$4) -> 80 | D91: =COUNTIFS(d_City,$B91,d_Status,"Cancelled",d_Year,$P$4,d_City,$Q$4,d_Cuisine,$R$4,d_Pay,$S$4,d_Type,$T$4) -> 9 | E91: =IFERROR(D91/C91,0) -> 0.1125 | F91: =SUMIFS(d_Gross,d_City,$B91,d_Status,"Cancelled",d_Year,$P$4,d_City,$Q$4,d_Cuisine,$R$4,d_Pay,$S$4,d_Type,$T$4) -> 11070
B92: Total / Overall | C92: =SUM(C80:C91) -> 1200 | D92: =SUM(D80:D91) -> 202 | E92: =IFERROR(D92/C92,0) -> 0.16833333 | F92: =SUM(F80:F91) -> 192229
B95: Cancellations by restaurant
B96: Restaurant | C96: Orders | D96: Cancelled | E96: Cancel rate | F96: Lost value
B97: Urban Tadka | C97: =COUNTIFS(d_Rest,$B97,d_Year,$P$4,d_City,$Q$4,d_Cuisine,$R$4,d_Pay,$S$4,d_Type,$T$4) -> 117 | D97: =COUNTIFS(d_Rest,$B97,d_Status,"Cancelled",d_Year,$P$4,d_City,$Q$4,d_Cuisine,$R$4,d_Pay,$S$4,d_Type,$T$4) -> 16 | E97: =IFERROR(D97/C97,0) -> 0.13675214 | F97: =SUMIFS(d_Gross,d_Rest,$B97,d_Status,"Cancelled",d_Year,$P$4,d_City,$Q$4,d_Cuisine,$R$4,d_Pay,$S$4,d_Type,$T$4) -> 16338
B98: Taste Junction | C98: =COUNTIFS(d_Rest,$B98,d_Year,$P$4,d_City,$Q$4,d_Cuisine,$R$4,d_Pay,$S$4,d_Type,$T$4) -> 107 | D98: =COUNTIFS(d_Rest,$B98,d_Status,"Cancelled",d_Year,$P$4,d_City,$Q$4,d_Cuisine,$R$4,d_Pay,$S$4,d_Type,$T$4) -> 15 | E98: =IFERROR(D98/C98,0) -> 0.14018692 | F98: =SUMIFS(d_Gross,d_Rest,$B98,d_Status,"Cancelled",d_Year,$P$4,d_City,$Q$4,d_Cuisine,$R$4,d_Pay,$S$4,d_Type,$T$4) -> 11343
B99: Cafe Aroma | C99: =COUNTIFS(d_Rest,$B99,d_Year,$P$4,d_City,$Q$4,d_Cuisine,$R$4,d_Pay,$S$4,d_Type,$T$4) -> 104 | D99: =COUNTIFS(d_Rest,$B99,d_Status,"Cancelled",d_Year,$P$4,d_City,$Q$4,d_Cuisine,$R$4,d_Pay,$S$4,d_Type,$T$4) -> 22 | E99: =IFERROR(D99/C99,0) -> 0.21153846 | F99: =SUMIFS(d_Gross,d_Rest,$B99,d_Status,"Cancelled",d_Year,$P$4,d_City,$Q$4,d_Cuisine,$R$4,d_Pay,$S$4,d_Type,$T$4) -> 21725
B100: Delhi Zaika | C100: =COUNTIFS(d_Rest,$B100,d_Year,$P$4,d_City,$Q$4,d_Cuisine,$R$4,d_Pay,$S$4,d_Type,$T$4) -> 102 | D100: =COUNTIFS(d_Rest,$B100,d_Status,"Cancelled",d_Year,$P$4,d_City,$Q$4,d_Cuisine,$R$4,d_Pay,$S$4,d_Type,$T$4) -> 17 | E100: =IFERROR(D100/C100,0) -> 0.16666667 | F100: =SUMIFS(d_Gross,d_Rest,$B100,d_Status,"Cancelled",d_Year,$P$4,d_City,$Q$4,d_Cuisine,$R$4,d_Pay,$S$4,d_Type,$T$4) -> 16988
B101: Burger House | C101: =COUNTIFS(d_Rest,$B101,d_Year,$P$4,d_City,$Q$4,d_Cuisine,$R$4,d_Pay,$S$4,d_Type,$T$4) -> 101 | D101: =COUNTIFS(d_Rest,$B101,d_Status,"Cancelled",d_Year,$P$4,d_City,$Q$4,d_Cuisine,$R$4,d_Pay,$S$4,d_Type,$T$4) -> 17 | E101: =IFERROR(D101/C101,0) -> 0.16831683 | F101: =SUMIFS(d_Gross,d_Rest,$B101,d_Status,"Cancelled",d_Year,$P$4,d_City,$Q$4,d_Cuisine,$R$4,d_Pay,$S$4,d_Type,$T$4) -> 15542
B102: Spice Hub | C102: =COUNTIFS(d_Rest,$B102,d_Year,$P$4,d_City,$Q$4,d_Cuisine,$R$4,d_Pay,$S$4,d_Type,$T$4) -> 100 | D102: =COUNTIFS(d_Rest,$B102,d_Status,"Cancelled",d_Year,$P$4,d_City,$Q$4,d_Cuisine,$R$4,d_Pay,$S$4,d_Type,$T$4) -> 11 | E102: =IFERROR(D102/C102,0) -> 0.11 | F102: =SUMIFS(d_Gross,d_Rest,$B102,d_Status,"Cancelled",d_Year,$P$4,d_City,$Q$4,d_Cuisine,$R$4,d_Pay,$S$4,d_Type,$T$4) -> 9436
B103: Pizza Point | C103: =COUNTIFS(d_Rest,$B103,d_Year,$P$4,d_City,$Q$4,d_Cuisine,$R$4,d_Pay,$S$4,d_Type,$T$4) -> 99 | D103: =COUNTIFS(d_Rest,$B103,d_Status,"Cancelled",d_Year,$P$4,d_City,$Q$4,d_Cuisine,$R$4,d_Pay,$S$4,d_Type,$T$4) -> 18 | E103: =IFERROR(D103/C103,0) -> 0.18181818 | F103: =SUMIFS(d_Gross,d_Rest,$B103,d_Status,"Cancelled",d_Year,$P$4,d_City,$Q$4,d_Cuisine,$R$4,d_Pay,$S$4,d_Type,$T$4) -> 15943
B104: Green Bowl | C104: =COUNTIFS(d_Rest,$B104,d_Year,$P$4,d_City,$Q$4,d_Cuisine,$R$4,d_Pay,$S$4,d_Type,$T$4) -> 98 | D104: =COUNTIFS(d_Rest,$B104,d_Status,"Cancelled",d_Year,$P$4,d_City,$Q$4,d_Cuisine,$R$4,d_Pay,$S$4,d_Type,$T$4) -> 14 | E104: =IFERROR(D104/C104,0) -> 0.14285714 | F104: =SUMIFS(d_Gross,d_Rest,$B104,d_Status,"Cancelled",d_Year,$P$4,d_City,$Q$4,d_Cuisine,$R$4,d_Pay,$S$4,d_Type,$T$4) -> 15322
B105: The Food Corner | C105: =COUNTIFS(d_Rest,$B105,d_Year,$P$4,d_City,$Q$4,d_Cuisine,$R$4,d_Pay,$S$4,d_Type,$T$4) -> 97 | D105: =COUNTIFS(d_Rest,$B105,d_Status,"Cancelled",d_Year,$P$4,d_City,$Q$4,d_Cuisine,$R$4,d_Pay,$S$4,d_Type,$T$4) -> 21 | E105: =IFERROR(D105/C105,0) -> 0.21649485 | F105: =SUMIFS(d_Gross,d_Rest,$B105,d_Status,"Cancelled",d_Year,$P$4,d_City,$Q$4,d_Cuisine,$R$4,d_Pay,$S$4,d_Type,$T$4) -> 21554
B106: Royal Biryani | C106: =COUNTIFS(d_Rest,$B106,d_Year,$P$4,d_City,$Q$4,d_Cuisine,$R$4,d_Pay,$S$4,d_Type,$T$4) -> 93 | D106: =COUNTIFS(d_Rest,$B106,d_Status,"Cancelled",d_Year,$P$4,d_City,$Q$4,d_Cuisine,$R$4,d_Pay,$S$4,d_Type,$T$4) -> 15 | E106: =IFERROR(D106/C106,0) -> 0.16129032 | F106: =SUMIFS(d_Gross,d_Rest,$B106,d_Status,"Cancelled",d_Year,$P$4,d_City,$Q$4,d_Cuisine,$R$4,d_Pay,$S$4,d_Type,$T$4) -> 14288
B107: Food Street | C107: =COUNTIFS(d_Rest,$B107,d_Year,$P$4,d_City,$Q$4,d_Cuisine,$R$4,d_Pay,$S$4,d_Type,$T$4) -> 93 | D107: =COUNTIFS(d_Rest,$B107,d_Status,"Cancelled",d_Year,$P$4,d_City,$Q$4,d_Cuisine,$R$4,d_Pay,$S$4,d_Type,$T$4) -> 22 | E107: =IFERROR(D107/C107,0) -> 0.23655914 | F107: =SUMIFS(d_Gross,d_Rest,$B107,d_Status,"Cancelled",d_Year,$P$4,d_City,$Q$4,d_Cuisine,$R$4,d_Pay,$S$4,d_Type,$T$4) -> 22060
B108: Momo Nation | C108: =COUNTIFS(d_Rest,$B108,d_Year,$P$4,d_City,$Q$4,d_Cuisine,$R$4,d_Pay,$S$4,d_Type,$T$4) -> 89 | D108: =COUNTIFS(d_Rest,$B108,d_Status,"Cancelled",d_Year,$P$4,d_City,$Q$4,d_Cuisine,$R$4,d_Pay,$S$4,d_Type,$T$4) -> 14 | E108: =IFERROR(D108/C108,0) -> 0.15730337 | F108: =SUMIFS(d_Gross,d_Rest,$B108,d_Status,"Cancelled",d_Year,$P$4,d_City,$Q$4,d_Cuisine,$R$4,d_Pay,$S$4,d_Type,$T$4) -> 11690
B109: Total / Overall | C109: =SUM(C97:C108) -> 1200 | D109: =SUM(D97:D108) -> 202 | E109: =IFERROR(D109/C109,0) -> 0.16833333 | F109: =SUM(F97:F108) -> 192229
B112: Cancellations by payment method
B113: Payment method | C113: Orders | D113: Cancelled | E113: Cancel rate | F113: Lost value
B114: UPI | C114: =COUNTIFS(d_Pay,$B114,d_Year,$P$4,d_City,$Q$4,d_Cuisine,$R$4,d_Pay,$S$4,d_Type,$T$4) -> 496 | D114: =COUNTIFS(d_Pay,$B114,d_Status,"Cancelled",d_Year,$P$4,d_City,$Q$4,d_Cuisine,$R$4,d_Pay,$S$4,d_Type,$T$4) -> 94 | E114: =IFERROR(D114/C114,0) -> 0.18951613 | F114: =SUMIFS(d_Gross,d_Pay,$B114,d_Status,"Cancelled",d_Year,$P$4,d_City,$Q$4,d_Cuisine,$R$4,d_Pay,$S$4,d_Type,$T$4) -> 79403
B115: Credit Card | C115: =COUNTIFS(d_Pay,$B115,d_Year,$P$4,d_City,$Q$4,d_Cuisine,$R$4,d_Pay,$S$4,d_Type,$T$4) -> 239 | D115: =COUNTIFS(d_Pay,$B115,d_Status,"Cancelled",d_Year,$P$4,d_City,$Q$4,d_Cuisine,$R$4,d_Pay,$S$4,d_Type,$T$4) -> 34 | E115: =IFERROR(D115/C115,0) -> 0.14225941 | F115: =SUMIFS(d_Gross,d_Pay,$B115,d_Status,"Cancelled",d_Year,$P$4,d_City,$Q$4,d_Cuisine,$R$4,d_Pay,$S$4,d_Type,$T$4) -> 38536
B116: Debit Card | C116: =COUNTIFS(d_Pay,$B116,d_Year,$P$4,d_City,$Q$4,d_Cuisine,$R$4,d_Pay,$S$4,d_Type,$T$4) -> 232 | D116: =COUNTIFS(d_Pay,$B116,d_Status,"Cancelled",d_Year,$P$4,d_City,$Q$4,d_Cuisine,$R$4,d_Pay,$S$4,d_Type,$T$4) -> 38 | E116: =IFERROR(D116/C116,0) -> 0.1637931 | F116: =SUMIFS(d_Gross,d_Pay,$B116,d_Status,"Cancelled",d_Year,$P$4,d_City,$Q$4,d_Cuisine,$R$4,d_Pay,$S$4,d_Type,$T$4) -> 37469
B117: Cash | C117: =COUNTIFS(d_Pay,$B117,d_Year,$P$4,d_City,$Q$4,d_Cuisine,$R$4,d_Pay,$S$4,d_Type,$T$4) -> 138 | D117: =COUNTIFS(d_Pay,$B117,d_Status,"Cancelled",d_Year,$P$4,d_City,$Q$4,d_Cuisine,$R$4,d_Pay,$S$4,d_Type,$T$4) -> 22 | E117: =IFERROR(D117/C117,0) -> 0.15942029 | F117: =SUMIFS(d_Gross,d_Pay,$B117,d_Status,"Cancelled",d_Year,$P$4,d_City,$Q$4,d_Cuisine,$R$4,d_Pay,$S$4,d_Type,$T$4) -> 20519
B118: Wallet | C118: =COUNTIFS(d_Pay,$B118,d_Year,$P$4,d_City,$Q$4,d_Cuisine,$R$4,d_Pay,$S$4,d_Type,$T$4) -> 95 | D118: =COUNTIFS(d_Pay,$B118,d_Status,"Cancelled",d_Year,$P$4,d_City,$Q$4,d_Cuisine,$R$4,d_Pay,$S$4,d_Type,$T$4) -> 14 | E118: =IFERROR(D118/C118,0) -> 0.14736842 | F118: =SUMIFS(d_Gross,d_Pay,$B118,d_Status,"Cancelled",d_Year,$P$4,d_City,$Q$4,d_Cuisine,$R$4,d_Pay,$S$4,d_Type,$T$4) -> 16302
B119: Total / Overall | C119: =SUM(C114:C118) -> 1200 | D119: =SUM(D114:D118) -> 202 | E119: =IFERROR(D119/C119,0) -> 0.16833333 | F119: =SUM(F114:F118) -> 192229
B122: Cancellations by cuisine
B123: Cuisine | C123: Orders | D123: Cancelled | E123: Cancel rate | F123: Lost value
B124: Burgers | C124: =COUNTIFS(d_Cuisine,$B124,d_Year,$P$4,d_City,$Q$4,d_Cuisine,$R$4,d_Pay,$S$4,d_Type,$T$4) -> 138 | D124: =COUNTIFS(d_Cuisine,$B124,d_Status,"Cancelled",d_Year,$P$4,d_City,$Q$4,d_Cuisine,$R$4,d_Pay,$S$4,d_Type,$T$4) -> 14 | E124: =IFERROR(D124/C124,0) -> 0.10144928 | F124: =SUMIFS(d_Gross,d_Cuisine,$B124,d_Status,"Cancelled",d_Year,$P$4,d_City,$Q$4,d_Cuisine,$R$4,d_Pay,$S$4,d_Type,$T$4) -> 15991
B125: North Indian | C125: =COUNTIFS(d_Cuisine,$B125,d_Year,$P$4,d_City,$Q$4,d_Cuisine,$R$4,d_Pay,$S$4,d_Type,$T$4) -> 136 | D125: =COUNTIFS(d_Cuisine,$B125,d_Status,"Cancelled",d_Year,$P$4,d_City,$Q$4,d_Cuisine,$R$4,d_Pay,$S$4,d_Type,$T$4) -> 30 | E125: =IFERROR(D125/C125,0) -> 0.22058824 | F125: =SUMIFS(d_Gross,d_Cuisine,$B125,d_Status,"Cancelled",d_Year,$P$4,d_City,$Q$4,d_Cuisine,$R$4,d_Pay,$S$4,d_Type,$T$4) -> 25039
B126: Desserts | C126: =COUNTIFS(d_Cuisine,$B126,d_Year,$P$4,d_City,$Q$4,d_Cuisine,$R$4,d_Pay,$S$4,d_Type,$T$4) -> 128 | D126: =COUNTIFS(d_Cuisine,$B126,d_Status,"Cancelled",d_Year,$P$4,d_City,$Q$4,d_Cuisine,$R$4,d_Pay,$S$4,d_Type,$T$4) -> 21 | E126: =IFERROR(D126/C126,0) -> 0.1640625 | F126: =SUMIFS(d_Gross,d_Cuisine,$B126,d_Status,"Cancelled",d_Year,$P$4,d_City,$Q$4,d_Cuisine,$R$4,d_Pay,$S$4,d_Type,$T$4) -> 19807
B127: Fast Food | C127: =COUNTIFS(d_Cuisine,$B127,d_Year,$P$4,d_City,$Q$4,d_Cuisine,$R$4,d_Pay,$S$4,d_Type,$T$4) -> 122 | D127: =COUNTIFS(d_Cuisine,$B127,d_Status,"Cancelled",d_Year,$P$4,d_City,$Q$4,d_Cuisine,$R$4,d_Pay,$S$4,d_Type,$T$4) -> 20 | E127: =IFERROR(D127/C127,0) -> 0.16393443 | F127: =SUMIFS(d_Gross,d_Cuisine,$B127,d_Status,"Cancelled",d_Year,$P$4,d_City,$Q$4,d_Cuisine,$R$4,d_Pay,$S$4,d_Type,$T$4) -> 18674
B128: Chinese | C128: =COUNTIFS(d_Cuisine,$B128,d_Year,$P$4,d_City,$Q$4,d_Cuisine,$R$4,d_Pay,$S$4,d_Type,$T$4) -> 121 | D128: =COUNTIFS(d_Cuisine,$B128,d_Status,"Cancelled",d_Year,$P$4,d_City,$Q$4,d_Cuisine,$R$4,d_Pay,$S$4,d_Type,$T$4) -> 17 | E128: =IFERROR(D128/C128,0) -> 0.14049587 | F128: =SUMIFS(d_Gross,d_Cuisine,$B128,d_Status,"Cancelled",d_Year,$P$4,d_City,$Q$4,d_Cuisine,$R$4,d_Pay,$S$4,d_Type,$T$4) -> 17519
B129: Momos | C129: =COUNTIFS(d_Cuisine,$B129,d_Year,$P$4,d_City,$Q$4,d_Cuisine,$R$4,d_Pay,$S$4,d_Type,$T$4) -> 116 | D129: =COUNTIFS(d_Cuisine,$B129,d_Status,"Cancelled",d_Year,$P$4,d_City,$Q$4,d_Cuisine,$R$4,d_Pay,$S$4,d_Type,$T$4) -> 21 | E129: =IFERROR(D129/C129,0) -> 0.18103448 | F129: =SUMIFS(d_Gross,d_Cuisine,$B129,d_Status,"Cancelled",d_Year,$P$4,d_City,$Q$4,d_Cuisine,$R$4,d_Pay,$S$4,d_Type,$T$4) -> 21450
B130: Biryani | C130: =COUNTIFS(d_Cuisine,$B130,d_Year,$P$4,d_City,$Q$4,d_Cuisine,$R$4,d_Pay,$S$4,d_Type,$T$4) -> 115 | D130: =COUNTIFS(d_Cuisine,$B130,d_Status,"Cancelled",d_Year,$P$4,d_City,$Q$4,d_Cuisine,$R$4,d_Pay,$S$4,d_Type,$T$4) -> 19 | E130: =IFERROR(D130/C130,0) -> 0.16521739 | F130: =SUMIFS(d_Gross,d_Cuisine,$B130,d_Status,"Cancelled",d_Year,$P$4,d_City,$Q$4,d_Cuisine,$R$4,d_Pay,$S$4,d_Type,$T$4) -> 16894
B131: Healthy | C131: =COUNTIFS(d_Cuisine,$B131,d_Year,$P$4,d_City,$Q$4,d_Cuisine,$R$4,d_Pay,$S$4,d_Type,$T$4) -> 114 | D131: =COUNTIFS(d_Cuisine,$B131,d_Status,"Cancelled",d_Year,$P$4,d_City,$Q$4,d_Cuisine,$R$4,d_Pay,$S$4,d_Type,$T$4) -> 17 | E131: =IFERROR(D131/C131,0) -> 0.14912281 | F131: =SUMIFS(d_Gross,d_Cuisine,$B131,d_Status,"Cancelled",d_Year,$P$4,d_City,$Q$4,d_Cuisine,$R$4,d_Pay,$S$4,d_Type,$T$4) -> 15818
B132: Pizza | C132: =COUNTIFS(d_Cuisine,$B132,d_Year,$P$4,d_City,$Q$4,d_Cuisine,$R$4,d_Pay,$S$4,d_Type,$T$4) -> 109 | D132: =COUNTIFS(d_Cuisine,$B132,d_Status,"Cancelled",d_Year,$P$4,d_City,$Q$4,d_Cuisine,$R$4,d_Pay,$S$4,d_Type,$T$4) -> 25 | E132: =IFERROR(D132/C132,0) -> 0.2293578 | F132: =SUMIFS(d_Gross,d_Cuisine,$B132,d_Status,"Cancelled",d_Year,$P$4,d_City,$Q$4,d_Cuisine,$R$4,d_Pay,$S$4,d_Type,$T$4) -> 24960
B133: South Indian | C133: =COUNTIFS(d_Cuisine,$B133,d_Year,$P$4,d_City,$Q$4,d_Cuisine,$R$4,d_Pay,$S$4,d_Type,$T$4) -> 101 | D133: =COUNTIFS(d_Cuisine,$B133,d_Status,"Cancelled",d_Year,$P$4,d_City,$Q$4,d_Cuisine,$R$4,d_Pay,$S$4,d_Type,$T$4) -> 18 | E133: =IFERROR(D133/C133,0) -> 0.17821782 | F133: =SUMIFS(d_Gross,d_Cuisine,$B133,d_Status,"Cancelled",d_Year,$P$4,d_City,$Q$4,d_Cuisine,$R$4,d_Pay,$S$4,d_Type,$T$4) -> 16077
B134: Total / Overall | C134: =SUM(C124:C133) -> 1200 | D134: =SUM(D124:D133) -> 202 | E134: =IFERROR(D134/C134,0) -> 0.16833333 | F134: =SUM(F124:F133) -> 192229
B137: Cancellations by order type
B138: Order type | C138: Orders | D138: Cancelled | E138: Cancel rate | F138: Lost value
B139: Delivery | C139: =COUNTIFS(d_Type,$B139,d_Year,$P$4,d_City,$Q$4,d_Cuisine,$R$4,d_Pay,$S$4,d_Type,$T$4) -> 881 | D139: =COUNTIFS(d_Type,$B139,d_Status,"Cancelled",d_Year,$P$4,d_City,$Q$4,d_Cuisine,$R$4,d_Pay,$S$4,d_Type,$T$4) -> 143 | E139: =IFERROR(D139/C139,0) -> 0.16231555 | F139: =SUMIFS(d_Gross,d_Type,$B139,d_Status,"Cancelled",d_Year,$P$4,d_City,$Q$4,d_Cuisine,$R$4,d_Pay,$S$4,d_Type,$T$4) -> 131593
B140: Pickup | C140: =COUNTIFS(d_Type,$B140,d_Year,$P$4,d_City,$Q$4,d_Cuisine,$R$4,d_Pay,$S$4,d_Type,$T$4) -> 319 | D140: =COUNTIFS(d_Type,$B140,d_Status,"Cancelled",d_Year,$P$4,d_City,$Q$4,d_Cuisine,$R$4,d_Pay,$S$4,d_Type,$T$4) -> 59 | E140: =IFERROR(D140/C140,0) -> 0.18495298 | F140: =SUMIFS(d_Gross,d_Type,$B140,d_Status,"Cancelled",d_Year,$P$4,d_City,$Q$4,d_Cuisine,$R$4,d_Pay,$S$4,d_Type,$T$4) -> 60636
B141: Total / Overall | C141: =SUM(C139:C140) -> 1200 | D141: =SUM(D139:D140) -> 202 | E141: =IFERROR(D141/C141,0) -> 0.16833333 | F141: =SUM(F139:F140) -> 192229

Sheet Rating & Review
B2: Rating & Review Analysis
B3: Customer ratings (1–5 stars per order) and restaurant ratings (2.5–5.0). The data has star ratings only – no written review text. ▸ Use the yellow filters in row 4 – every KPI, chart and table updates. | L3: ← Back to Home
B4: Year: | C4: All | D4: City: | E4: All | F4: Cuisine: | G4: All | H4: Payment: | I4: All | J4: Order type: | K4: All | L4: ="Orders in view: "&TEXT(COUNTIFS(d_ID,"<>",d_Year,$P$4,d_City,$Q$4,d_Cuisine,$R$4,d_Pay,$S$4,d_Type,$T$4),"#,##0") -> Orders in view: 1,200 | P4: =IF(C4="All",">0",C4) -> >0 | Q4: =IF(E4="All","*",E4) -> * | R4: =IF(G4="All","*",G4) -> * | S4: =IF(I4="All","*",I4) -> * | T4: =IF(K4="All","*",K4) -> *
B5: AVG CUSTOMER RATING | D5: AVG RESTAURANT RATING | F5: 5-STAR SHARE | H5: SATISFIED (4–5★) | J5: LOW RATINGS (1–2★) | L5: RATINGS COLLECTED
B6: =AVERAGEIFS(d_CRating,d_ID,"<>",d_Year,$P$4,d_City,$Q$4,d_Cuisine,$R$4,d_Pay,$S$4,d_Type,$T$4) -> 4.0183333 | D6: =AVERAGEIFS(d_RRating,d_ID,"<>",d_Year,$P$4,d_City,$Q$4,d_Cuisine,$R$4,d_Pay,$S$4,d_Type,$T$4) -> 3.7175 | F6: =IFERROR(COUNTIFS(d_CRating,5,d_Year,$P$4,d_City,$Q$4,d_Cuisine,$R$4,d_Pay,$S$4,d_Type,$T$4)/COUNTIFS(d_ID,"<>",d_Year,$P$4,d_City,$Q$4,d_Cuisine,$R$4,d_Pay,$S$4,d_Type,$T$4),0) -> 0.4375 | H6: =IFERROR(COUNTIFS(d_CRating,">=4",d_Year,$P$4,d_City,$Q$4,d_Cuisine,$R$4,d_Pay,$S$4,d_Type,$T$4)/COUNTIFS(d_ID,"<>",d_Year,$P$4,d_City,$Q$4,d_Cuisine,$R$4,d_Pay,$S$4,d_Type,$T$4),0) -> 0.7325 | J6: =IFERROR(COUNTIFS(d_CRating,"<=2",d_Year,$P$4,d_City,$Q$4,d_Cuisine,$R$4,d_Pay,$S$4,d_Type,$T$4)/COUNTIFS(d_ID,"<>",d_Year,$P$4,d_City,$Q$4,d_Cuisine,$R$4,d_Pay,$S$4,d_Type,$T$4),0) -> 0.11083333 | L6: =COUNTIFS(d_CRating,">0",d_Year,$P$4,d_City,$Q$4,d_Cuisine,$R$4,d_Pay,$S$4,d_Type,$T$4) -> 1200
B7: Out of 5 stars | D7: Out of 5 | F7: Orders rated 5 | H7: Orders rated 4 or 5 | J7: Orders rated 1 or 2 | L7: Orders with a rating
B57: Supporting data (feeds the charts above)
B59: Customer rating distribution
B60: Stars | C60: Orders | D60: % of orders
B61: 1 star | C61: =COUNTIFS(d_CRating,1,d_Year,$P$4,d_City,$Q$4,d_Cuisine,$R$4,d_Pay,$S$4,d_Type,$T$4) -> 49 | D61: =IFERROR(C61/COUNTIFS(d_ID,"<>",d_Year,$P$4,d_City,$Q$4,d_Cuisine,$R$4,d_Pay,$S$4,d_Type,$T$4),0) -> 0.040833333
B62: 2 stars | C62: =COUNTIFS(d_CRating,2,d_Year,$P$4,d_City,$Q$4,d_Cuisine,$R$4,d_Pay,$S$4,d_Type,$T$4) -> 84 | D62: =IFERROR(C62/COUNTIFS(d_ID,"<>",d_Year,$P$4,d_City,$Q$4,d_Cuisine,$R$4,d_Pay,$S$4,d_Type,$T$4),0) -> 0.07
B63: 3 stars | C63: =COUNTIFS(d_CRating,3,d_Year,$P$4,d_City,$Q$4,d_Cuisine,$R$4,d_Pay,$S$4,d_Type,$T$4) -> 188 | D63: =IFERROR(C63/COUNTIFS(d_ID,"<>",d_Year,$P$4,d_City,$Q$4,d_Cuisine,$R$4,d_Pay,$S$4,d_Type,$T$4),0) -> 0.15666667
B64: 4 stars | C64: =COUNTIFS(d_CRating,4,d_Year,$P$4,d_City,$Q$4,d_Cuisine,$R$4,d_Pay,$S$4,d_Type,$T$4) -> 354 | D64: =IFERROR(C64/COUNTIFS(d_ID,"<>",d_Year,$P$4,d_City,$Q$4,d_Cuisine,$R$4,d_Pay,$S$4,d_Type,$T$4),0) -> 0.295
B65: 5 stars | C65: =COUNTIFS(d_CRating,5,d_Year,$P$4,d_City,$Q$4,d_Cuisine,$R$4,d_Pay,$S$4,d_Type,$T$4) -> 525 | D65: =IFERROR(C65/COUNTIFS(d_ID,"<>",d_Year,$P$4,d_City,$Q$4,d_Cuisine,$R$4,d_Pay,$S$4,d_Type,$T$4),0) -> 0.4375
B66: Total / Overall | C66: =SUM(C61:C65) -> 1200 | D66: =SUM(D61:D65) -> 1
B69: Restaurant rating bands
B70: Rating band | C70: Min (>=) | D70: Max (<) | E70: Orders | F70: % of orders
B71: 2.5–2.9 | C71: 2.5 | D71: 3 | E71: =COUNTIFS(d_RRating,">="&$C71,d_RRating,"<"&$D71,d_Year,$P$4,d_City,$Q$4,d_Cuisine,$R$4,d_Pay,$S$4,d_Type,$T$4) -> 225 | F71: =IFERROR(E71/COUNTIFS(d_ID,"<>",d_Year,$P$4,d_City,$Q$4,d_Cuisine,$R$4,d_Pay,$S$4,d_Type,$T$4),0) -> 0.1875
B72: 3.0–3.4 | C72: 3 | D72: 3.5 | E72: =COUNTIFS(d_RRating,">="&$C72,d_RRating,"<"&$D72,d_Year,$P$4,d_City,$Q$4,d_Cuisine,$R$4,d_Pay,$S$4,d_Type,$T$4) -> 256 | F72: =IFERROR(E72/COUNTIFS(d_ID,"<>",d_Year,$P$4,d_City,$Q$4,d_Cuisine,$R$4,d_Pay,$S$4,d_Type,$T$4),0) -> 0.21333333
B73: 3.5–3.9 | C73: 3.5 | D73: 4 | E73: =COUNTIFS(d_RRating,">="&$C73,d_RRating,"<"&$D73,d_Year,$P$4,d_City,$Q$4,d_Cuisine,$R$4,d_Pay,$S$4,d_Type,$T$4) -> 230 | F73: =IFERROR(E73/COUNTIFS(d_ID,"<>",d_Year,$P$4,d_City,$Q$4,d_Cuisine,$R$4,d_Pay,$S$4,d_Type,$T$4),0) -> 0.19166667
B74: 4.0–4.4 | C74: 4 | D74: 4.5 | E74: =COUNTIFS(d_RRating,">="&$C74,d_RRating,"<"&$D74,d_Year,$P$4,d_City,$Q$4,d_Cuisine,$R$4,d_Pay,$S$4,d_Type,$T$4) -> 233 | F74: =IFERROR(E74/COUNTIFS(d_ID,"<>",d_Year,$P$4,d_City,$Q$4,d_Cuisine,$R$4,d_Pay,$S$4,d_Type,$T$4),0) -> 0.19416667
B75: 4.5–5.0 | C75: 4.5 | D75: 5.01 | E75: =COUNTIFS(d_RRating,">="&$C75,d_RRating,"<"&$D75,d_Year,$P$4,d_City,$Q$4,d_Cuisine,$R$4,d_Pay,$S$4,d_Type,$T$4) -> 256 | F75: =IFERROR(E75/COUNTIFS(d_ID,"<>",d_Year,$P$4,d_City,$Q$4,d_Cuisine,$R$4,d_Pay,$S$4,d_Type,$T$4),0) -> 0.21333333
B76: Total / Overall | E76: =SUM(E71:E75) -> 1200 | F76: =SUM(F71:F75) -> 1
B77: Band limits are inputs (blue).
B80: Ratings by restaurant
B81: Restaurant | C81: Orders | D81: Avg customer rating | E81: Avg restaurant rating | F81: % 4–5 stars | G81: % 1–2 stars
B82: Urban Tadka | C82: =COUNTIFS(d_Rest,$B82,d_Year,$P$4,d_City,$Q$4,d_Cuisine,$R$4,d_Pay,$S$4,d_Type,$T$4) -> 117 | D82: =IFERROR(AVERAGEIFS(d_CRating,d_Rest,$B82,d_Year,$P$4,d_City,$Q$4,d_Cuisine,$R$4,d_Pay,$S$4,d_Type,$T$4),0) -> 4.0854701 | E82: =IFERROR(AVERAGEIFS(d_RRating,d_Rest,$B82,d_Year,$P$4,d_City,$Q$4,d_Cuisine,$R$4,d_Pay,$S$4,d_Type,$T$4),0) -> 3.7042735 | F82: =IFERROR(COUNTIFS(d_Rest,$B82,d_CRating,">=4",d_Year,$P$4,d_City,$Q$4,d_Cuisine,$R$4,d_Pay,$S$4,d_Type,$T$4)/C82,0) -> 0.73504274 | G82: =IFERROR(COUNTIFS(d_Rest,$B82,d_CRating,"<=2",d_Year,$P$4,d_City,$Q$4,d_Cuisine,$R$4,d_Pay,$S$4,d_Type,$T$4)/C82,0) -> 0.094017094
B83: Taste Junction | C83: =COUNTIFS(d_Rest,$B83,d_Year,$P$4,d_City,$Q$4,d_Cuisine,$R$4,d_Pay,$S$4,d_Type,$T$4) -> 107 | D83: =IFERROR(AVERAGEIFS(d_CRating,d_Rest,$B83,d_Year,$P$4,d_City,$Q$4,d_Cuisine,$R$4,d_Pay,$S$4,d_Type,$T$4),0) -> 3.9065421 | E83: =IFERROR(AVERAGEIFS(d_RRating,d_Rest,$B83,d_Year,$P$4,d_City,$Q$4,d_Cuisine,$R$4,d_Pay,$S$4,d_Type,$T$4),0) -> 3.7626168 | F83: =IFERROR(COUNTIFS(d_Rest,$B83,d_CRating,">=4",d_Year,$P$4,d_City,$Q$4,d_Cuisine,$R$4,d_Pay,$S$4,d_Type,$T$4)/C83,0) -> 0.71962617 | G83: =IFERROR(COUNTIFS(d_Rest,$B83,d_CRating,"<=2",d_Year,$P$4,d_City,$Q$4,d_Cuisine,$R$4,d_Pay,$S$4,d_Type,$T$4)/C83,0) -> 0.13084112
B84: Cafe Aroma | C84: =COUNTIFS(d_Rest,$B84,d_Year,$P$4,d_City,$Q$4,d_Cuisine,$R$4,d_Pay,$S$4,d_Type,$T$4) -> 104 | D84: =IFERROR(AVERAGEIFS(d_CRating,d_Rest,$B84,d_Year,$P$4,d_City,$Q$4,d_Cuisine,$R$4,d_Pay,$S$4,d_Type,$T$4),0) -> 4.2403846 | E84: =IFERROR(AVERAGEIFS(d_RRating,d_Rest,$B84,d_Year,$P$4,d_City,$Q$4,d_Cuisine,$R$4,d_Pay,$S$4,d_Type,$T$4),0) -> 3.7586538 | F84: =IFERROR(COUNTIFS(d_Rest,$B84,d_CRating,">=4",d_Year,$P$4,d_City,$Q$4,d_Cuisine,$R$4,d_Pay,$S$4,d_Type,$T$4)/C84,0) -> 0.83653846 | G84: =IFERROR(COUNTIFS(d_Rest,$B84,d_CRating,"<=2",d_Year,$P$4,d_City,$Q$4,d_Cuisine,$R$4,d_Pay,$S$4,d_Type,$T$4)/C84,0) -> 0.096153846
B85: Delhi Zaika | C85: =COUNTIFS(d_Rest,$B85,d_Year,$P$4,d_City,$Q$4,d_Cuisine,$R$4,d_Pay,$S$4,d_Type,$T$4) -> 102 | D85: =IFERROR(AVERAGEIFS(d_CRating,d_Rest,$B85,d_Year,$P$4,d_City,$Q$4,d_Cuisine,$R$4,d_Pay,$S$4,d_Type,$T$4),0) -> 3.8333333 | E85: =IFERROR(AVERAGEIFS(d_RRating,d_Rest,$B85,d_Year,$P$4,d_City,$Q$4,d_Cuisine,$R$4,d_Pay,$S$4,d_Type,$T$4),0) -> 3.7617647 | F85: =IFERROR(COUNTIFS(d_Rest,$B85,d_CRating,">=4",d_Year,$P$4,d_City,$Q$4,d_Cuisine,$R$4,d_Pay,$S$4,d_Type,$T$4)/C85,0) -> 0.69607843 | G85: =IFERROR(COUNTIFS(d_Rest,$B85,d_CRating,"<=2",d_Year,$P$4,d_City,$Q$4,d_Cuisine,$R$4,d_Pay,$S$4,d_Type,$T$4)/C85,0) -> 0.12745098
B86: Burger House | C86: =COUNTIFS(d_Rest,$B86,d_Year,$P$4,d_City,$Q$4,d_Cuisine,$R$4,d_Pay,$S$4,d_Type,$T$4) -> 101 | D86: =IFERROR(AVERAGEIFS(d_CRating,d_Rest,$B86,d_Year,$P$4,d_City,$Q$4,d_Cuisine,$R$4,d_Pay,$S$4,d_Type,$T$4),0) -> 3.9009901 | E86: =IFERROR(AVERAGEIFS(d_RRating,d_Rest,$B86,d_Year,$P$4,d_City,$Q$4,d_Cuisine,$R$4,d_Pay,$S$4,d_Type,$T$4),0) -> 3.6237624 | F86: =IFERROR(COUNTIFS(d_Rest,$B86,d_CRating,">=4",d_Year,$P$4,d_City,$Q$4,d_Cuisine,$R$4,d_Pay,$S$4,d_Type,$T$4)/C86,0) -> 0.68316832 | G86: =IFERROR(COUNTIFS(d_Rest,$B86,d_CRating,"<=2",d_Year,$P$4,d_City,$Q$4,d_Cuisine,$R$4,d_Pay,$S$4,d_Type,$T$4)/C86,0) -> 0.12871287
B87: Spice Hub | C87: =COUNTIFS(d_Rest,$B87,d_Year,$P$4,d_City,$Q$4,d_Cuisine,$R$4,d_Pay,$S$4,d_Type,$T$4) -> 100 | D87: =IFERROR(AVERAGEIFS(d_CRating,d_Rest,$B87,d_Year,$P$4,d_City,$Q$4,d_Cuisine,$R$4,d_Pay,$S$4,d_Type,$T$4),0) -> 4 | E87: =IFERROR(AVERAGEIFS(d_RRating,d_Rest,$B87,d_Year,$P$4,d_City,$Q$4,d_Cuisine,$R$4,d_Pay,$S$4,d_Type,$T$4),0) -> 3.676 | F87: =IFERROR(COUNTIFS(d_Rest,$B87,d_CRating,">=4",d_Year,$P$4,d_City,$Q$4,d_Cuisine,$R$4,d_Pay,$S$4,d_Type,$T$4)/C87,0) -> 0.73 | G87: =IFERROR(COUNTIFS(d_Rest,$B87,d_CRating,"<=2",d_Year,$P$4,d_City,$Q$4,d_Cuisine,$R$4,d_Pay,$S$4,d_Type,$T$4)/C87,0) -> 0.11
B88: Pizza Point | C88: =COUNTIFS(d_Rest,$B88,d_Year,$P$4,d_City,$Q$4,d_Cuisine,$R$4,d_Pay,$S$4,d_Type,$T$4) -> 99 | D88: =IFERROR(AVERAGEIFS(d_CRating,d_Rest,$B88,d_Year,$P$4,d_City,$Q$4,d_Cuisine,$R$4,d_Pay,$S$4,d_Type,$T$4),0) -> 4.1818182 | E88: =IFERROR(AVERAGEIFS(d_RRating,d_Rest,$B88,d_Year,$P$4,d_City,$Q$4,d_Cuisine,$R$4,d_Pay,$S$4,d_Type,$T$4),0) -> 3.8666667 | F88: =IFERROR(COUNTIFS(d_Rest,$B88,d_CRating,">=4",d_Year,$P$4,d_City,$Q$4,d_Cuisine,$R$4,d_Pay,$S$4,d_Type,$T$4)/C88,0) -> 0.81818182 | G88: =IFERROR(COUNTIFS(d_Rest,$B88,d_CRating,"<=2",d_Year,$P$4,d_City,$Q$4,d_Cuisine,$R$4,d_Pay,$S$4,d_Type,$T$4)/C88,0) -> 0.080808081
B89: Green Bowl | C89: =COUNTIFS(d_Rest,$B89,d_Year,$P$4,d_City,$Q$4,d_Cuisine,$R$4,d_Pay,$S$4,d_Type,$T$4) -> 98 | D89: =IFERROR(AVERAGEIFS(d_CRating,d_Rest,$B89,d_Year,$P$4,d_City,$Q$4,d_Cuisine,$R$4,d_Pay,$S$4,d_Type,$T$4),0) -> 4.1836735 | E89: =IFERROR(AVERAGEIFS(d_RRating,d_Rest,$B89,d_Year,$P$4,d_City,$Q$4,d_Cuisine,$R$4,d_Pay,$S$4,d_Type,$T$4),0) -> 3.7 | F89: =IFERROR(COUNTIFS(d_Rest,$B89,d_CRating,">=4",d_Year,$P$4,d_City,$Q$4,d_Cuisine,$R$4,d_Pay,$S$4,d_Type,$T$4)/C89,0) -> 0.80612245 | G89: =IFERROR(COUNTIFS(d_Rest,$B89,d_CRating,"<=2",d_Year,$P$4,d_City,$Q$4,d_Cuisine,$R$4,d_Pay,$S$4,d_Type,$T$4)/C89,0) -> 0.071428571
B90: The Food Corner | C90: =COUNTIFS(d_Rest,$B90,d_Year,$P$4,d_City,$Q$4,d_Cuisine,$R$4,d_Pay,$S$4,d_Type,$T$4) -> 97 | D90: =IFERROR(AVERAGEIFS(d_CRating,d_Rest,$B90,d_Year,$P$4,d_City,$Q$4,d_Cuisine,$R$4,d_Pay,$S$4,d_Type,$T$4),0) -> 3.8556701 | E90: =IFERROR(AVERAGEIFS(d_RRating,d_Rest,$B90,d_Year,$P$4,d_City,$Q$4,d_Cuisine,$R$4,d_Pay,$S$4,d_Type,$T$4),0) -> 3.7618557 | F90: =IFERROR(COUNTIFS(d_Rest,$B90,d_CRating,">=4",d_Year,$P$4,d_City,$Q$4,d_Cuisine,$R$4,d_Pay,$S$4,d_Type,$T$4)/C90,0) -> 0.64948454 | G90: =IFERROR(COUNTIFS(d_Rest,$B90,d_CRating,"<=2",d_Year,$P$4,d_City,$Q$4,d_Cuisine,$R$4,d_Pay,$S$4,d_Type,$T$4)/C90,0) -> 0.16494845
B91: Royal Biryani | C91: =COUNTIFS(d_Rest,$B91,d_Year,$P$4,d_City,$Q$4,d_Cuisine,$R$4,d_Pay,$S$4,d_Type,$T$4) -> 93 | D91: =IFERROR(AVERAGEIFS(d_CRating,d_Rest,$B91,d_Year,$P$4,d_City,$Q$4,d_Cuisine,$R$4,d_Pay,$S$4,d_Type,$T$4),0) -> 4.0215054 | E91: =IFERROR(AVERAGEIFS(d_RRating,d_Rest,$B91,d_Year,$P$4,d_City,$Q$4,d_Cuisine,$R$4,d_Pay,$S$4,d_Type,$T$4),0) -> 3.7215054 | F91: =IFERROR(COUNTIFS(d_Rest,$B91,d_CRating,">=4",d_Year,$P$4,d_City,$Q$4,d_Cuisine,$R$4,d_Pay,$S$4,d_Type,$T$4)/C91,0) -> 0.70967742 | G91: =IFERROR(COUNTIFS(d_Rest,$B91,d_CRating,"<=2",d_Year,$P$4,d_City,$Q$4,d_Cuisine,$R$4,d_Pay,$S$4,d_Type,$T$4)/C91,0) -> 0.10752688
B92: Food Street | C92: =COUNTIFS(d_Rest,$B92,d_Year,$P$4,d_City,$Q$4,d_Cuisine,$R$4,d_Pay,$S$4,d_Type,$T$4) -> 93 | D92: =IFERROR(AVERAGEIFS(d_CRating,d_Rest,$B92,d_Year,$P$4,d_City,$Q$4,d_Cuisine,$R$4,d_Pay,$S$4,d_Type,$T$4),0) -> 3.9677419 | E92: =IFERROR(AVERAGEIFS(d_RRating,d_Rest,$B92,d_Year,$P$4,d_City,$Q$4,d_Cuisine,$R$4,d_Pay,$S$4,d_Type,$T$4),0) -> 3.6021505 | F92: =IFERROR(COUNTIFS(d_Rest,$B92,d_CRating,">=4",d_Year,$P$4,d_City,$Q$4,d_Cuisine,$R$4,d_Pay,$S$4,d_Type,$T$4)/C92,0) -> 0.64516129 | G92: =IFERROR(COUNTIFS(d_Rest,$B92,d_CRating,"<=2",d_Year,$P$4,d_City,$Q$4,d_Cuisine,$R$4,d_Pay,$S$4,d_Type,$T$4)/C92,0) -> 0.086021505
B93: Momo Nation | C93: =COUNTIFS(d_Rest,$B93,d_Year,$P$4,d_City,$Q$4,d_Cuisine,$R$4,d_Pay,$S$4,d_Type,$T$4) -> 89 | D93: =IFERROR(AVERAGEIFS(d_CRating,d_Rest,$B93,d_Year,$P$4,d_City,$Q$4,d_Cuisine,$R$4,d_Pay,$S$4,d_Type,$T$4),0) -> 4.0337079 | E93: =IFERROR(AVERAGEIFS(d_RRating,d_Rest,$B93,d_Year,$P$4,d_City,$Q$4,d_Cuisine,$R$4,d_Pay,$S$4,d_Type,$T$4),0) -> 3.6561798 | F93: =IFERROR(COUNTIFS(d_Rest,$B93,d_CRating,">=4",d_Year,$P$4,d_City,$Q$4,d_Cuisine,$R$4,d_Pay,$S$4,d_Type,$T$4)/C93,0) -> 0.75280899 | G93: =IFERROR(COUNTIFS(d_Rest,$B93,d_CRating,"<=2",d_Year,$P$4,d_City,$Q$4,d_Cuisine,$R$4,d_Pay,$S$4,d_Type,$T$4)/C93,0) -> 0.13483146
B96: Ratings by cuisine
B97: Cuisine | C97: Orders | D97: Avg customer rating | E97: Avg restaurant rating | F97: % 4–5 stars | G97: % 1–2 stars
B98: Burgers | C98: =COUNTIFS(d_Cuisine,$B98,d_Year,$P$4,d_City,$Q$4,d_Cuisine,$R$4,d_Pay,$S$4,d_Type,$T$4) -> 138 | D98: =IFERROR(AVERAGEIFS(d_CRating,d_Cuisine,$B98,d_Year,$P$4,d_City,$Q$4,d_Cuisine,$R$4,d_Pay,$S$4,d_Type,$T$4),0) -> 3.9565217 | E98: =IFERROR(AVERAGEIFS(d_RRating,d_Cuisine,$B98,d_Year,$P$4,d_City,$Q$4,d_Cuisine,$R$4,d_Pay,$S$4,d_Type,$T$4),0) -> 3.7536232 | F98: =IFERROR(COUNTIFS(d_Cuisine,$B98,d_CRating,">=4",d_Year,$P$4,d_City,$Q$4,d_Cuisine,$R$4,d_Pay,$S$4,d_Type,$T$4)/C98,0) -> 0.70289855 | G98: =IFERROR(COUNTIFS(d_Cuisine,$B98,d_CRating,"<=2",d_Year,$P$4,d_City,$Q$4,d_Cuisine,$R$4,d_Pay,$S$4,d_Type,$T$4)/C98,0) -> 0.13043478
B99: North Indian | C99: =COUNTIFS(d_Cuisine,$B99,d_Year,$P$4,d_City,$Q$4,d_Cuisine,$R$4,d_Pay,$S$4,d_Type,$T$4) -> 136 | D99: =IFERROR(AVERAGEIFS(d_CRating,d_Cuisine,$B99,d_Year,$P$4,d_City,$Q$4,d_Cuisine,$R$4,d_Pay,$S$4,d_Type,$T$4),0) -> 4.1176471 | E99: =IFERROR(AVERAGEIFS(d_RRating,d_Cuisine,$B99,d_Year,$P$4,d_City,$Q$4,d_Cuisine,$R$4,d_Pay,$S$4,d_Type,$T$4),0) -> 3.6588235 | F99: =IFERROR(COUNTIFS(d_Cuisine,$B99,d_CRating,">=4",d_Year,$P$4,d_City,$Q$4,d_Cuisine,$R$4,d_Pay,$S$4,d_Type,$T$4)/C99,0) -> 0.75 | G99: =IFERROR(COUNTIFS(d_Cuisine,$B99,d_CRating,"<=2",d_Year,$P$4,d_City,$Q$4,d_Cuisine,$R$4,d_Pay,$S$4,d_Type,$T$4)/C99,0) -> 0.066176471
B100: Desserts | C100: =COUNTIFS(d_Cuisine,$B100,d_Year,$P$4,d_City,$Q$4,d_Cuisine,$R$4,d_Pay,$S$4,d_Type,$T$4) -> 128 | D100: =IFERROR(AVERAGEIFS(d_CRating,d_Cuisine,$B100,d_Year,$P$4,d_City,$Q$4,d_Cuisine,$R$4,d_Pay,$S$4,d_Type,$T$4),0) -> 4.046875 | E100: =IFERROR(AVERAGEIFS(d_RRating,d_Cuisine,$B100,d_Year,$P$4,d_City,$Q$4,d_Cuisine,$R$4,d_Pay,$S$4,d_Type,$T$4),0) -> 3.709375 | F100: =IFERROR(COUNTIFS(d_Cuisine,$B100,d_CRating,">=4",d_Year,$P$4,d_City,$Q$4,d_Cuisine,$R$4,d_Pay,$S$4,d_Type,$T$4)/C100,0) -> 0.734375 | G100: =IFERROR(COUNTIFS(d_Cuisine,$B100,d_CRating,"<=2",d_Year,$P$4,d_City,$Q$4,d_Cuisine,$R$4,d_Pay,$S$4,d_Type,$T$4)/C100,0) -> 0.0859375
B101: Fast Food | C101: =COUNTIFS(d_Cuisine,$B101,d_Year,$P$4,d_City,$Q$4,d_Cuisine,$R$4,d_Pay,$S$4,d_Type,$T$4) -> 122 | D101: =IFERROR(AVERAGEIFS(d_CRating,d_Cuisine,$B101,d_Year,$P$4,d_City,$Q$4,d_Cuisine,$R$4,d_Pay,$S$4,d_Type,$T$4),0) -> 4.1147541 | E101: =IFERROR(AVERAGEIFS(d_RRating,d_Cuisine,$B101,d_Year,$P$4,d_City,$Q$4,d_Cuisine,$R$4,d_Pay,$S$4,d_Type,$T$4),0) -> 3.7672131 | F101: =IFERROR(COUNTIFS(d_Cuisine,$B101,d_CRating,">=4",d_Year,$P$4,d_City,$Q$4,d_Cuisine,$R$4,d_Pay,$S$4,d_Type,$T$4)/C101,0) -> 0.76229508 | G101: =IFERROR(COUNTIFS(d_Cuisine,$B101,d_CRating,"<=2",d_Year,$P$4,d_City,$Q$4,d_Cuisine,$R$4,d_Pay,$S$4,d_Type,$T$4)/C101,0) -> 0.13114754
B102: Chinese | C102: =COUNTIFS(d_Cuisine,$B102,d_Year,$P$4,d_City,$Q$4,d_Cuisine,$R$4,d_Pay,$S$4,d_Type,$T$4) -> 121 | D102: =IFERROR(AVERAGEIFS(d_CRating,d_Cuisine,$B102,d_Year,$P$4,d_City,$Q$4,d_Cuisine,$R$4,d_Pay,$S$4,d_Type,$T$4),0) -> 3.9421488 | E102: =IFERROR(AVERAGEIFS(d_RRating,d_Cuisine,$B102,d_Year,$P$4,d_City,$Q$4,d_Cuisine,$R$4,d_Pay,$S$4,d_Type,$T$4),0) -> 3.6958678 | F102: =IFERROR(COUNTIFS(d_Cuisine,$B102,d_CRating,">=4",d_Year,$P$4,d_City,$Q$4,d_Cuisine,$R$4,d_Pay,$S$4,d_Type,$T$4)/C102,0) -> 0.69421488 | G102: =IFERROR(COUNTIFS(d_Cuisine,$B102,d_CRating,"<=2",d_Year,$P$4,d_City,$Q$4,d_Cuisine,$R$4,d_Pay,$S$4,d_Type,$T$4)/C102,0) -> 0.099173554
B103: Momos | C103: =COUNTIFS(d_Cuisine,$B103,d_Year,$P$4,d_City,$Q$4,d_Cuisine,$R$4,d_Pay,$S$4,d_Type,$T$4) -> 116 | D103: =IFERROR(AVERAGEIFS(d_CRating,d_Cuisine,$B103,d_Year,$P$4,d_City,$Q$4,d_Cuisine,$R$4,d_Pay,$S$4,d_Type,$T$4),0) -> 4.112069 | E103: =IFERROR(AVERAGEIFS(d_RRating,d_Cuisine,$B103,d_Year,$P$4,d_City,$Q$4,d_Cuisine,$R$4,d_Pay,$S$4,d_Type,$T$4),0) -> 3.7017241 | F103: =IFERROR(COUNTIFS(d_Cuisine,$B103,d_CRating,">=4",d_Year,$P$4,d_City,$Q$4,d_Cuisine,$R$4,d_Pay,$S$4,d_Type,$T$4)/C103,0) -> 0.75862069 | G103: =IFERROR(COUNTIFS(d_Cuisine,$B103,d_CRating,"<=2",d_Year,$P$4,d_City,$Q$4,d_Cuisine,$R$4,d_Pay,$S$4,d_Type,$T$4)/C103,0) -> 0.060344828
B104: Biryani | C104: =COUNTIFS(d_Cuisine,$B104,d_Year,$P$4,d_City,$Q$4,d_Cuisine,$R$4,d_Pay,$S$4,d_Type,$T$4) -> 115 | D104: =IFERROR(AVERAGEIFS(d_CRating,d_Cuisine,$B104,d_Year,$P$4,d_City,$Q$4,d_Cuisine,$R$4,d_Pay,$S$4,d_Type,$T$4),0) -> 3.9913043 | E104: =IFERROR(AVERAGEIFS(d_RRating,d_Cuisine,$B104,d_Year,$P$4,d_City,$Q$4,d_Cuisine,$R$4,d_Pay,$S$4,d_Type,$T$4),0) -> 3.8113043 | F104: =IFERROR(COUNTIFS(d_Cuisine,$B104,d_CRating,">=4",d_Year,$P$4,d_City,$Q$4,d_Cuisine,$R$4,d_Pay,$S$4,d_Type,$T$4)/C104,0) -> 0.73043478 | G104: =IFERROR(COUNTIFS(d_Cuisine,$B104,d_CRating,"<=2",d_Year,$P$4,d_City,$Q$4,d_Cuisine,$R$4,d_Pay,$S$4,d_Type,$T$4)/C104,0) -> 0.13043478
B105: Healthy | C105: =COUNTIFS(d_Cuisine,$B105,d_Year,$P$4,d_City,$Q$4,d_Cuisine,$R$4,d_Pay,$S$4,d_Type,$T$4) -> 114 | D105: =IFERROR(AVERAGEIFS(d_CRating,d_Cuisine,$B105,d_Year,$P$4,d_City,$Q$4,d_Cuisine,$R$4,d_Pay,$S$4,d_Type,$T$4),0) -> 3.7982456 | E105: =IFERROR(AVERAGEIFS(d_RRating,d_Cuisine,$B105,d_Year,$P$4,d_City,$Q$4,d_Cuisine,$R$4,d_Pay,$S$4,d_Type,$T$4),0) -> 3.7675439 | F105: =IFERROR(COUNTIFS(d_Cuisine,$B105,d_CRating,">=4",d_Year,$P$4,d_City,$Q$4,d_Cuisine,$R$4,d_Pay,$S$4,d_Type,$T$4)/C105,0) -> 0.64912281 | G105: =IFERROR(COUNTIFS(d_Cuisine,$B105,d_CRating,"<=2",d_Year,$P$4,d_City,$Q$4,d_Cuisine,$R$4,d_Pay,$S$4,d_Type,$T$4)/C105,0) -> 0.1754386
B106: Pizza | C106: =COUNTIFS(d_Cuisine,$B106,d_Year,$P$4,d_City,$Q$4,d_Cuisine,$R$4,d_Pay,$S$4,d_Type,$T$4) -> 109 | D106: =IFERROR(AVERAGEIFS(d_CRating,d_Cuisine,$B106,d_Year,$P$4,d_City,$Q$4,d_Cuisine,$R$4,d_Pay,$S$4,d_Type,$T$4),0) -> 4.0275229 | E106: =IFERROR(AVERAGEIFS(d_RRating,d_Cuisine,$B106,d_Year,$P$4,d_City,$Q$4,d_Cuisine,$R$4,d_Pay,$S$4,d_Type,$T$4),0) -> 3.6146789 | F106: =IFERROR(COUNTIFS(d_Cuisine,$B106,d_CRating,">=4",d_Year,$P$4,d_City,$Q$4,d_Cuisine,$R$4,d_Pay,$S$4,d_Type,$T$4)/C106,0) -> 0.78899083 | G106: =IFERROR(COUNTIFS(d_Cuisine,$B106,d_CRating,"<=2",d_Year,$P$4,d_City,$Q$4,d_Cuisine,$R$4,d_Pay,$S$4,d_Type,$T$4)/C106,0) -> 0.11926606
B107: South Indian | C107: =COUNTIFS(d_Cuisine,$B107,d_Year,$P$4,d_City,$Q$4,d_Cuisine,$R$4,d_Pay,$S$4,d_Type,$T$4) -> 101 | D107: =IFERROR(AVERAGEIFS(d_CRating,d_Cuisine,$B107,d_Year,$P$4,d_City,$Q$4,d_Cuisine,$R$4,d_Pay,$S$4,d_Type,$T$4),0) -> 4.0693069 | E107: =IFERROR(AVERAGEIFS(d_RRating,d_Cuisine,$B107,d_Year,$P$4,d_City,$Q$4,d_Cuisine,$R$4,d_Pay,$S$4,d_Type,$T$4),0) -> 3.6891089 | F107: =IFERROR(COUNTIFS(d_Cuisine,$B107,d_CRating,">=4",d_Year,$P$4,d_City,$Q$4,d_Cuisine,$R$4,d_Pay,$S$4,d_Type,$T$4)/C107,0) -> 0.76237624 | G107: =IFERROR(COUNTIFS(d_Cuisine,$B107,d_CRating,"<=2",d_Year,$P$4,d_City,$Q$4,d_Cuisine,$R$4,d_Pay,$S$4,d_Type,$T$4)/C107,0) -> 0.11881188
B110: Ratings by city
B111: City | C111: Orders | D111: Avg customer rating | E111: Avg restaurant rating | F111: % 4–5 stars | G111: % 1–2 stars
B112: Delhi | C112: =COUNTIFS(d_City,$B112,d_Year,$P$4,d_City,$Q$4,d_Cuisine,$R$4,d_Pay,$S$4,d_Type,$T$4) -> 119 | D112: =IFERROR(AVERAGEIFS(d_CRating,d_City,$B112,d_Year,$P$4,d_City,$Q$4,d_Cuisine,$R$4,d_Pay,$S$4,d_Type,$T$4),0) -> 4.1344538 | E112: =IFERROR(AVERAGEIFS(d_RRating,d_City,$B112,d_Year,$P$4,d_City,$Q$4,d_Cuisine,$R$4,d_Pay,$S$4,d_Type,$T$4),0) -> 3.7781513 | F112: =IFERROR(COUNTIFS(d_City,$B112,d_CRating,">=4",d_Year,$P$4,d_City,$Q$4,d_Cuisine,$R$4,d_Pay,$S$4,d_Type,$T$4)/C112,0) -> 0.79831933 | G112: =IFERROR(COUNTIFS(d_City,$B112,d_CRating,"<=2",d_Year,$P$4,d_City,$Q$4,d_Cuisine,$R$4,d_Pay,$S$4,d_Type,$T$4)/C112,0) -> 0.084033613
B113: Ahmedabad | C113: =COUNTIFS(d_City,$B113,d_Year,$P$4,d_City,$Q$4,d_Cuisine,$R$4,d_Pay,$S$4,d_Type,$T$4) -> 114 | D113: =IFERROR(AVERAGEIFS(d_CRating,d_City,$B113,d_Year,$P$4,d_City,$Q$4,d_Cuisine,$R$4,d_Pay,$S$4,d_Type,$T$4),0) -> 3.9912281 | E113: =IFERROR(AVERAGEIFS(d_RRating,d_City,$B113,d_Year,$P$4,d_City,$Q$4,d_Cuisine,$R$4,d_Pay,$S$4,d_Type,$T$4),0) -> 3.6342105 | F113: =IFERROR(COUNTIFS(d_City,$B113,d_CRating,">=4",d_Year,$P$4,d_City,$Q$4,d_Cuisine,$R$4,d_Pay,$S$4,d_Type,$T$4)/C113,0) -> 0.74561404 | G113: =IFERROR(COUNTIFS(d_City,$B113,d_CRating,"<=2",d_Year,$P$4,d_City,$Q$4,d_Cuisine,$R$4,d_Pay,$S$4,d_Type,$T$4)/C113,0) -> 0.13157895
B114: Bengaluru | C114: =COUNTIFS(d_City,$B114,d_Year,$P$4,d_City,$Q$4,d_Cuisine,$R$4,d_Pay,$S$4,d_Type,$T$4) -> 110 | D114: =IFERROR(AVERAGEIFS(d_CRating,d_City,$B114,d_Year,$P$4,d_City,$Q$4,d_Cuisine,$R$4,d_Pay,$S$4,d_Type,$T$4),0) -> 4.1090909 | E114: =IFERROR(AVERAGEIFS(d_RRating,d_City,$B114,d_Year,$P$4,d_City,$Q$4,d_Cuisine,$R$4,d_Pay,$S$4,d_Type,$T$4),0) -> 3.7045455 | F114: =IFERROR(COUNTIFS(d_City,$B114,d_CRating,">=4",d_Year,$P$4,d_City,$Q$4,d_Cuisine,$R$4,d_Pay,$S$4,d_Type,$T$4)/C114,0) -> 0.77272727 | G114: =IFERROR(COUNTIFS(d_City,$B114,d_CRating,"<=2",d_Year,$P$4,d_City,$Q$4,d_Cuisine,$R$4,d_Pay,$S$4,d_Type,$T$4)/C114,0) -> 0.1
B115: Chennai | C115: =COUNTIFS(d_City,$B115,d_Year,$P$4,d_City,$Q$4,d_Cuisine,$R$4,d_Pay,$S$4,d_Type,$T$4) -> 108 | D115: =IFERROR(AVERAGEIFS(d_CRating,d_City,$B115,d_Year,$P$4,d_City,$Q$4,d_Cuisine,$R$4,d_Pay,$S$4,d_Type,$T$4),0) -> 4 | E115: =IFERROR(AVERAGEIFS(d_RRating,d_City,$B115,d_Year,$P$4,d_City,$Q$4,d_Cuisine,$R$4,d_Pay,$S$4,d_Type,$T$4),0) -> 3.7101852 | F115: =IFERROR(COUNTIFS(d_City,$B115,d_CRating,">=4",d_Year,$P$4,d_City,$Q$4,d_Cuisine,$R$4,d_Pay,$S$4,d_Type,$T$4)/C115,0) -> 0.7037037 | G115: =IFERROR(COUNTIFS(d_City,$B115,d_CRating,"<=2",d_Year,$P$4,d_City,$Q$4,d_Cuisine,$R$4,d_Pay,$S$4,d_Type,$T$4)/C115,0) -> 0.092592593
B116: Noida | C116: =COUNTIFS(d_City,$B116,d_Year,$P$4,d_City,$Q$4,d_Cuisine,$R$4,d_Pay,$S$4,d_Type,$T$4) -> 107 | D116: =IFERROR(AVERAGEIFS(d_CRating,d_City,$B116,d_Year,$P$4,d_City,$Q$4,d_Cuisine,$R$4,d_Pay,$S$4,d_Type,$T$4),0) -> 3.9439252 | E116: =IFERROR(AVERAGEIFS(d_RRating,d_City,$B116,d_Year,$P$4,d_City,$Q$4,d_Cuisine,$R$4,d_Pay,$S$4,d_Type,$T$4),0) -> 3.7056075 | F116: =IFERROR(COUNTIFS(d_City,$B116,d_CRating,">=4",d_Year,$P$4,d_City,$Q$4,d_Cuisine,$R$4,d_Pay,$S$4,d_Type,$T$4)/C116,0) -> 0.70093458 | G116: =IFERROR(COUNTIFS(d_City,$B116,d_CRating,"<=2",d_Year,$P$4,d_City,$Q$4,d_Cuisine,$R$4,d_Pay,$S$4,d_Type,$T$4)/C116,0) -> 0.12149533
B117: Jaipur | C117: =COUNTIFS(d_City,$B117,d_Year,$P$4,d_City,$Q$4,d_Cuisine,$R$4,d_Pay,$S$4,d_Type,$T$4) -> 102 | D117: =IFERROR(AVERAGEIFS(d_CRating,d_City,$B117,d_Year,$P$4,d_City,$Q$4,d_Cuisine,$R$4,d_Pay,$S$4,d_Type,$T$4),0) -> 4 | E117: =IFERROR(AVERAGEIFS(d_RRating,d_City,$B117,d_Year,$P$4,d_City,$Q$4,d_Cuisine,$R$4,d_Pay,$S$4,d_Type,$T$4),0) -> 3.745098 | F117: =IFERROR(COUNTIFS(d_City,$B117,d_CRating,">=4",d_Year,$P$4,d_City,$Q$4,d_Cuisine,$R$4,d_Pay,$S$4,d_Type,$T$4)/C117,0) -> 0.70588235 | G117: =IFERROR(COUNTIFS(d_City,$B117,d_CRating,"<=2",d_Year,$P$4,d_City,$Q$4,d_Cuisine,$R$4,d_Pay,$S$4,d_Type,$T$4)/C117,0) -> 0.10784314
B118: Hyderabad | C118: =COUNTIFS(d_City,$B118,d_Year,$P$4,d_City,$Q$4,d_Cuisine,$R$4,d_Pay,$S$4,d_Type,$T$4) -> 96 | D118: =IFERROR(AVERAGEIFS(d_CRating,d_City,$B118,d_Year,$P$4,d_City,$Q$4,d_Cuisine,$R$4,d_Pay,$S$4,d_Type,$T$4),0) -> 4.03125 | E118: =IFERROR(AVERAGEIFS(d_RRating,d_City,$B118,d_Year,$P$4,d_City,$Q$4,d_Cuisine,$R$4,d_Pay,$S$4,d_Type,$T$4),0) -> 3.7333333 | F118: =IFERROR(COUNTIFS(d_City,$B118,d_CRating,">=4",d_Year,$P$4,d_City,$Q$4,d_Cuisine,$R$4,d_Pay,$S$4,d_Type,$T$4)/C118,0) -> 0.73958333 | G118: =IFERROR(COUNTIFS(d_City,$B118,d_CRating,"<=2",d_Year,$P$4,d_City,$Q$4,d_Cuisine,$R$4,d_Pay,$S$4,d_Type,$T$4)/C118,0) -> 0.10416667
B119: Pune | C119: =COUNTIFS(d_City,$B119,d_Year,$P$4,d_City,$Q$4,d_Cuisine,$R$4,d_Pay,$S$4,d_Type,$T$4) -> 96 | D119: =IFERROR(AVERAGEIFS(d_CRating,d_City,$B119,d_Year,$P$4,d_City,$Q$4,d_Cuisine,$R$4,d_Pay,$S$4,d_Type,$T$4),0) -> 4.1979167 | E119: =IFERROR(AVERAGEIFS(d_RRating,d_City,$B119,d_Year,$P$4,d_City,$Q$4,d_Cuisine,$R$4,d_Pay,$S$4,d_Type,$T$4),0) -> 3.7322917 | F119: =IFERROR(COUNTIFS(d_City,$B119,d_CRating,">=4",d_Year,$P$4,d_City,$Q$4,d_Cuisine,$R$4,d_Pay,$S$4,d_Type,$T$4)/C119,0) -> 0.78125 | G119: =IFERROR(COUNTIFS(d_City,$B119,d_CRating,"<=2",d_Year,$P$4,d_City,$Q$4,d_Cuisine,$R$4,d_Pay,$S$4,d_Type,$T$4)/C119,0) -> 0.09375
B120: Kolkata | C120: =COUNTIFS(d_City,$B120,d_Year,$P$4,d_City,$Q$4,d_Cuisine,$R$4,d_Pay,$S$4,d_Type,$T$4) -> 94 | D120: =IFERROR(AVERAGEIFS(d_CRating,d_City,$B120,d_Year,$P$4,d_City,$Q$4,d_Cuisine,$R$4,d_Pay,$S$4,d_Type,$T$4),0) -> 4.0531915 | E120: =IFERROR(AVERAGEIFS(d_RRating,d_City,$B120,d_Year,$P$4,d_City,$Q$4,d_Cuisine,$R$4,d_Pay,$S$4,d_Type,$T$4),0) -> 3.6489362 | F120: =IFERROR(COUNTIFS(d_City,$B120,d_CRating,">=4",d_Year,$P$4,d_City,$Q$4,d_Cuisine,$R$4,d_Pay,$S$4,d_Type,$T$4)/C120,0) -> 0.70212766 | G120: =IFERROR(COUNTIFS(d_City,$B120,d_CRating,"<=2",d_Year,$P$4,d_City,$Q$4,d_Cuisine,$R$4,d_Pay,$S$4,d_Type,$T$4)/C120,0) -> 0.063829787
B121: Lucknow | C121: =COUNTIFS(d_City,$B121,d_Year,$P$4,d_City,$Q$4,d_Cuisine,$R$4,d_Pay,$S$4,d_Type,$T$4) -> 91 | D121: =IFERROR(AVERAGEIFS(d_CRating,d_City,$B121,d_Year,$P$4,d_City,$Q$4,d_Cuisine,$R$4,d_Pay,$S$4,d_Type,$T$4),0) -> 3.9120879 | E121: =IFERROR(AVERAGEIFS(d_RRating,d_City,$B121,d_Year,$P$4,d_City,$Q$4,d_Cuisine,$R$4,d_Pay,$S$4,d_Type,$T$4),0) -> 3.7285714 | F121: =IFERROR(COUNTIFS(d_City,$B121,d_CRating,">=4",d_Year,$P$4,d_City,$Q$4,d_Cuisine,$R$4,d_Pay,$S$4,d_Type,$T$4)/C121,0) -> 0.73626374 | G121: =IFERROR(COUNTIFS(d_City,$B121,d_CRating,"<=2",d_Year,$P$4,d_City,$Q$4,d_Cuisine,$R$4,d_Pay,$S$4,d_Type,$T$4)/C121,0) -> 0.13186813
B122: Mumbai | C122: =COUNTIFS(d_City,$B122,d_Year,$P$4,d_City,$Q$4,d_Cuisine,$R$4,d_Pay,$S$4,d_Type,$T$4) -> 83 | D122: =IFERROR(AVERAGEIFS(d_CRating,d_City,$B122,d_Year,$P$4,d_City,$Q$4,d_Cuisine,$R$4,d_Pay,$S$4,d_Type,$T$4),0) -> 3.939759 | E122: =IFERROR(AVERAGEIFS(d_RRating,d_City,$B122,d_Year,$P$4,d_City,$Q$4,d_Cuisine,$R$4,d_Pay,$S$4,d_Type,$T$4),0) -> 3.7975904 | F122: =IFERROR(COUNTIFS(d_City,$B122,d_CRating,">=4",d_Year,$P$4,d_City,$Q$4,d_Cuisine,$R$4,d_Pay,$S$4,d_Type,$T$4)/C122,0) -> 0.73493976 | G122: =IFERROR(COUNTIFS(d_City,$B122,d_CRating,"<=2",d_Year,$P$4,d_City,$Q$4,d_Cuisine,$R$4,d_Pay,$S$4,d_Type,$T$4)/C122,0) -> 0.15662651
B123: Gurugram | C123: =COUNTIFS(d_City,$B123,d_Year,$P$4,d_City,$Q$4,d_Cuisine,$R$4,d_Pay,$S$4,d_Type,$T$4) -> 80 | D123: =IFERROR(AVERAGEIFS(d_CRating,d_City,$B123,d_Year,$P$4,d_City,$Q$4,d_Cuisine,$R$4,d_Pay,$S$4,d_Type,$T$4),0) -> 3.8375 | E123: =IFERROR(AVERAGEIFS(d_RRating,d_City,$B123,d_Year,$P$4,d_City,$Q$4,d_Cuisine,$R$4,d_Pay,$S$4,d_Type,$T$4),0) -> 3.7025 | F123: =IFERROR(COUNTIFS(d_City,$B123,d_CRating,">=4",d_Year,$P$4,d_City,$Q$4,d_Cuisine,$R$4,d_Pay,$S$4,d_Type,$T$4)/C123,0) -> 0.6375 | G123: =IFERROR(COUNTIFS(d_City,$B123,d_CRating,"<=2",d_Year,$P$4,d_City,$Q$4,d_Cuisine,$R$4,d_Pay,$S$4,d_Type,$T$4)/C123,0) -> 0.1625
B126: Monthly average ratings
B127: Month | C127: Month start | D127: Orders | E127: Avg customer rating | F127: Avg restaurant rating
B128: =TEXT(C128,"mmm-yy") -> Jan-25 | C128: 45658 | D128: =COUNTIFS(d_Date,">="&$C128,d_Date,"<"&EDATE($C128,1),d_Year,$P$4,d_City,$Q$4,d_Cuisine,$R$4,d_Pay,$S$4,d_Type,$T$4) -> 93 | E128: =IFERROR(AVERAGEIFS(d_CRating,d_Date,">="&$C128,d_Date,"<"&EDATE($C128,1),d_Year,$P$4,d_City,$Q$4,d_Cuisine,$R$4,d_Pay,$S$4,d_Type,$T$4),0) -> 4.1075269 | F128: =IFERROR(AVERAGEIFS(d_RRating,d_Date,">="&$C128,d_Date,"<"&EDATE($C128,1),d_Year,$P$4,d_City,$Q$4,d_Cuisine,$R$4,d_Pay,$S$4,d_Type,$T$4),0) -> 3.6806452
B129: =TEXT(C129,"mmm-yy") -> Feb-25 | C129: 45689 | D129: =COUNTIFS(d_Date,">="&$C129,d_Date,"<"&EDATE($C129,1),d_Year,$P$4,d_City,$Q$4,d_Cuisine,$R$4,d_Pay,$S$4,d_Type,$T$4) -> 84 | E129: =IFERROR(AVERAGEIFS(d_CRating,d_Date,">="&$C129,d_Date,"<"&EDATE($C129,1),d_Year,$P$4,d_City,$Q$4,d_Cuisine,$R$4,d_Pay,$S$4,d_Type,$T$4),0) -> 4.047619 | F129: =IFERROR(AVERAGEIFS(d_RRating,d_Date,">="&$C129,d_Date,"<"&EDATE($C129,1),d_Year,$P$4,d_City,$Q$4,d_Cuisine,$R$4,d_Pay,$S$4,d_Type,$T$4),0) -> 3.5654762
B130: =TEXT(C130,"mmm-yy") -> Mar-25 | C130: 45717 | D130: =COUNTIFS(d_Date,">="&$C130,d_Date,"<"&EDATE($C130,1),d_Year,$P$4,d_City,$Q$4,d_Cuisine,$R$4,d_Pay,$S$4,d_Type,$T$4) -> 93 | E130: =IFERROR(AVERAGEIFS(d_CRating,d_Date,">="&$C130,d_Date,"<"&EDATE($C130,1),d_Year,$P$4,d_City,$Q$4,d_Cuisine,$R$4,d_Pay,$S$4,d_Type,$T$4),0) -> 4.0645161 | F130: =IFERROR(AVERAGEIFS(d_RRating,d_Date,">="&$C130,d_Date,"<"&EDATE($C130,1),d_Year,$P$4,d_City,$Q$4,d_Cuisine,$R$4,d_Pay,$S$4,d_Type,$T$4),0) -> 3.7516129
B131: =TEXT(C131,"mmm-yy") -> Apr-25 | C131: 45748 | D131: =COUNTIFS(d_Date,">="&$C131,d_Date,"<"&EDATE($C131,1),d_Year,$P$4,d_City,$Q$4,d_Cuisine,$R$4,d_Pay,$S$4,d_Type,$T$4) -> 90 | E131: =IFERROR(AVERAGEIFS(d_CRating,d_Date,">="&$C131,d_Date,"<"&EDATE($C131,1),d_Year,$P$4,d_City,$Q$4,d_Cuisine,$R$4,d_Pay,$S$4,d_Type,$T$4),0) -> 4.0555556 | F131: =IFERROR(AVERAGEIFS(d_RRating,d_Date,">="&$C131,d_Date,"<"&EDATE($C131,1),d_Year,$P$4,d_City,$Q$4,d_Cuisine,$R$4,d_Pay,$S$4,d_Type,$T$4),0) -> 3.7677778
B132: =TEXT(C132,"mmm-yy") -> May-25 | C132: 45778 | D132: =COUNTIFS(d_Date,">="&$C132,d_Date,"<"&EDATE($C132,1),d_Year,$P$4,d_City,$Q$4,d_Cuisine,$R$4,d_Pay,$S$4,d_Type,$T$4) -> 93 | E132: =IFERROR(AVERAGEIFS(d_CRating,d_Date,">="&$C132,d_Date,"<"&EDATE($C132,1),d_Year,$P$4,d_City,$Q$4,d_Cuisine,$R$4,d_Pay,$S$4,d_Type,$T$4),0) -> 3.9677419 | F132: =IFERROR(AVERAGEIFS(d_RRating,d_Date,">="&$C132,d_Date,"<"&EDATE($C132,1),d_Year,$P$4,d_City,$Q$4,d_Cuisine,$R$4,d_Pay,$S$4,d_Type,$T$4),0) -> 3.7247312
B133: =TEXT(C133,"mmm-yy") -> Jun-25 | C133: 45809 | D133: =COUNTIFS(d_Date,">="&$C133,d_Date,"<"&EDATE($C133,1),d_Year,$P$4,d_City,$Q$4,d_Cuisine,$R$4,d_Pay,$S$4,d_Type,$T$4) -> 90 | E133: =IFERROR(AVERAGEIFS(d_CRating,d_Date,">="&$C133,d_Date,"<"&EDATE($C133,1),d_Year,$P$4,d_City,$Q$4,d_Cuisine,$R$4,d_Pay,$S$4,d_Type,$T$4),0) -> 3.8777778 | F133: =IFERROR(AVERAGEIFS(d_RRating,d_Date,">="&$C133,d_Date,"<"&EDATE($C133,1),d_Year,$P$4,d_City,$Q$4,d_Cuisine,$R$4,d_Pay,$S$4,d_Type,$T$4),0) -> 3.7111111
B134: =TEXT(C134,"mmm-yy") -> Jul-25 | C134: 45839 | D134: =COUNTIFS(d_Date,">="&$C134,d_Date,"<"&EDATE($C134,1),d_Year,$P$4,d_City,$Q$4,d_Cuisine,$R$4,d_Pay,$S$4,d_Type,$T$4) -> 93 | E134: =IFERROR(AVERAGEIFS(d_CRating,d_Date,">="&$C134,d_Date,"<"&EDATE($C134,1),d_Year,$P$4,d_City,$Q$4,d_Cuisine,$R$4,d_Pay,$S$4,d_Type,$T$4),0) -> 3.9892473 | F134: =IFERROR(AVERAGEIFS(d_RRating,d_Date,">="&$C134,d_Date,"<"&EDATE($C134,1),d_Year,$P$4,d_City,$Q$4,d_Cuisine,$R$4,d_Pay,$S$4,d_Type,$T$4),0) -> 3.7010753
B135: =TEXT(C135,"mmm-yy") -> Aug-25 | C135: 45870 | D135: =COUNTIFS(d_Date,">="&$C135,d_Date,"<"&EDATE($C135,1),d_Year,$P$4,d_City,$Q$4,d_Cuisine,$R$4,d_Pay,$S$4,d_Type,$T$4) -> 93 | E135: =IFERROR(AVERAGEIFS(d_CRating,d_Date,">="&$C135,d_Date,"<"&EDATE($C135,1),d_Year,$P$4,d_City,$Q$4,d_Cuisine,$R$4,d_Pay,$S$4,d_Type,$T$4),0) -> 4.0322581 | F135: =IFERROR(AVERAGEIFS(d_RRating,d_Date,">="&$C135,d_Date,"<"&EDATE($C135,1),d_Year,$P$4,d_City,$Q$4,d_Cuisine,$R$4,d_Pay,$S$4,d_Type,$T$4),0) -> 3.5569892
B136: =TEXT(C136,"mmm-yy") -> Sep-25 | C136: 45901 | D136: =COUNTIFS(d_Date,">="&$C136,d_Date,"<"&EDATE($C136,1),d_Year,$P$4,d_City,$Q$4,d_Cuisine,$R$4,d_Pay,$S$4,d_Type,$T$4) -> 90 | E136: =IFERROR(AVERAGEIFS(d_CRating,d_Date,">="&$C136,d_Date,"<"&EDATE($C136,1),d_Year,$P$4,d_City,$Q$4,d_Cuisine,$R$4,d_Pay,$S$4,d_Type,$T$4),0) -> 3.9777778 | F136: =IFERROR(AVERAGEIFS(d_RRating,d_Date,">="&$C136,d_Date,"<"&EDATE($C136,1),d_Year,$P$4,d_City,$Q$4,d_Cuisine,$R$4,d_Pay,$S$4,d_Type,$T$4),0) -> 3.7811111
B137: =TEXT(C137,"mmm-yy") -> Oct-25 | C137: 45931 | D137: =COUNTIFS(d_Date,">="&$C137,d_Date,"<"&EDATE($C137,1),d_Year,$P$4,d_City,$Q$4,d_Cuisine,$R$4,d_Pay,$S$4,d_Type,$T$4) -> 93 | E137: =IFERROR(AVERAGEIFS(d_CRating,d_Date,">="&$C137,d_Date,"<"&EDATE($C137,1),d_Year,$P$4,d_City,$Q$4,d_Cuisine,$R$4,d_Pay,$S$4,d_Type,$T$4),0) -> 4.1075269 | F137: =IFERROR(AVERAGEIFS(d_RRating,d_Date,">="&$C137,d_Date,"<"&EDATE($C137,1),d_Year,$P$4,d_City,$Q$4,d_Cuisine,$R$4,d_Pay,$S$4,d_Type,$T$4),0) -> 3.7612903
B138: =TEXT(C138,"mmm-yy") -> Nov-25 | C138: 45962 | D138: =COUNTIFS(d_Date,">="&$C138,d_Date,"<"&EDATE($C138,1),d_Year,$P$4,d_City,$Q$4,d_Cuisine,$R$4,d_Pay,$S$4,d_Type,$T$4) -> 90 | E138: =IFERROR(AVERAGEIFS(d_CRating,d_Date,">="&$C138,d_Date,"<"&EDATE($C138,1),d_Year,$P$4,d_City,$Q$4,d_Cuisine,$R$4,d_Pay,$S$4,d_Type,$T$4),0) -> 3.8888889 | F138: =IFERROR(AVERAGEIFS(d_RRating,d_Date,">="&$C138,d_Date,"<"&EDATE($C138,1),d_Year,$P$4,d_City,$Q$4,d_Cuisine,$R$4,d_Pay,$S$4,d_Type,$T$4),0) -> 3.8455556
B139: =TEXT(C139,"mmm-yy") -> Dec-25 | C139: 45992 | D139: =COUNTIFS(d_Date,">="&$C139,d_Date,"<"&EDATE($C139,1),d_Year,$P$4,d_City,$Q$4,d_Cuisine,$R$4,d_Pay,$S$4,d_Type,$T$4) -> 93 | E139: =IFERROR(AVERAGEIFS(d_CRating,d_Date,">="&$C139,d_Date,"<"&EDATE($C139,1),d_Year,$P$4,d_City,$Q$4,d_Cuisine,$R$4,d_Pay,$S$4,d_Type,$T$4),0) -> 4.0645161 | F139: =IFERROR(AVERAGEIFS(d_RRating,d_Date,">="&$C139,d_Date,"<"&EDATE($C139,1),d_Year,$P$4,d_City,$Q$4,d_Cuisine,$R$4,d_Pay,$S$4,d_Type,$T$4),0) -> 3.7784946
... B141: =TEXT(C141,"mmm-yy") -> Feb-26 | C141: 46054 | D141: =COUNTIFS(d_Date,">="&$C141,d_Date,"<"&EDATE($C141,1),d_Year,$P$4,d_City,$Q$4,d_Cuisine,$R$4,d_Pay,$S$4,d_Type,$T$4) -> 12 | E141: =IFERROR(AVERAGEIFS(d_CRating,d_Date,">="&$C141,d_Date,"<"&EDATE($C141,1),d_Year,$P$4,d_City,$Q$4,d_Cuisine,$R$4,d_Pay,$S$4,d_Type,$T$4),0) -> 3.75 | F141: =IFERROR(AVERAGEIFS(d_RRating,d_Date,">="&$C141,d_Date,"<"&EDATE($C141,1),d_Year,$P$4,d_City,$Q$4,d_Cuisine,$R$4,d_Pay,$S$4,d_Type,$T$4),0) -> 3.7666667

Sheet Revenue Dashboard
B2: Revenue Dashboard
B3: Realised revenue = Delivered orders only. Gross = order value + delivery fee; Net = Gross − discount (floored at 0), as in the Data sheet. ▸ Use the yellow filters in row 4 – every KPI, chart and table updates. | L3: ← Back to Home
B4: Year: | C4: All | D4: City: | E4: All | F4: Cuisine: | G4: All | H4: Payment: | I4: All | J4: Order type: | K4: All | L4: ="Orders in view: "&TEXT(COUNTIFS(d_ID,"<>",d_Year,$P$4,d_City,$Q$4,d_Cuisine,$R$4,d_Pay,$S$4,d_Type,$T$4),"#,##0") -> Orders in view: 1,200 | P4: =IF(C4="All",">0",C4) -> >0 | Q4: =IF(E4="All","*",E4) -> * | R4: =IF(G4="All","*",G4) -> * | S4: =IF(I4="All","*",I4) -> * | T4: =IF(K4="All","*",K4) -> *
B5: GROSS REVENUE | D5: DISCOUNTS GIVEN | F5: NET REVENUE | H5: AVG NET / ORDER | J5: DISCOUNT RATE | L5: PENDING REVENUE
B6: =SUMIFS(d_Gross,d_Status,"Delivered",d_Year,$P$4,d_City,$Q$4,d_Cuisine,$R$4,d_Pay,$S$4,d_Type,$T$4) -> 755840 | D6: =SUMIFS(d_Disc,d_Status,"Delivered",d_Year,$P$4,d_City,$Q$4,d_Cuisine,$R$4,d_Pay,$S$4,d_Type,$T$4) -> 56065 | F6: =SUMIFS(d_Net,d_Status,"Delivered",d_Year,$P$4,d_City,$Q$4,d_Cuisine,$R$4,d_Pay,$S$4,d_Type,$T$4) -> 699950 | H6: =IFERROR(SUMIFS(d_Net,d_Status,"Delivered",d_Year,$P$4,d_City,$Q$4,d_Cuisine,$R$4,d_Pay,$S$4,d_Type,$T$4)/COUNTIFS(d_Status,"Delivered",d_Year,$P$4,d_City,$Q$4,d_Cuisine,$R$4,d_Pay,$S$4,d_Type,$T$4),0) -> 884.89254 | J6: =IFERROR(SUMIFS(d_Disc,d_Status,"Delivered",d_Year,$P$4,d_City,$Q$4,d_Cuisine,$R$4,d_Pay,$S$4,d_Type,$T$4)/SUMIFS(d_Gross,d_Status,"Delivered",d_Year,$P$4,d_City,$Q$4,d_Cuisine,$R$4,d_Pay,$S$4,d_Type,$T$4),0) -> 0.074175751 | L6: =SUMIFS(d_Net,d_Status,"Pending",d_Year,$P$4,d_City,$Q$4,d_Cuisine,$R$4,d_Pay,$S$4,d_Type,$T$4) -> 194755
B7: Delivered orders | D7: On delivered orders | F7: Realised revenue | H7: Net ÷ delivered orders | J7: Discounts ÷ gross | L7: Net value not yet realised
B57: Supporting data (feeds the charts above)
B59: Monthly revenue (Delivered orders)
B60: Month | C60: Month start | D60: Delivered orders | E60: Gross revenue | F60: Discounts | G60: Net revenue | H60: Avg net / order
B61: =TEXT(C61,"mmm-yy") -> Jan-25 | C61: 45658 | D61: =COUNTIFS(d_Date,">="&$C61,d_Date,"<"&EDATE($C61,1),d_Status,"Delivered",d_Year,$P$4,d_City,$Q$4,d_Cuisine,$R$4,d_Pay,$S$4,d_Type,$T$4) -> 66 | E61: =SUMIFS(d_Gross,d_Date,">="&$C61,d_Date,"<"&EDATE($C61,1),d_Status,"Delivered",d_Year,$P$4,d_City,$Q$4,d_Cuisine,$R$4,d_Pay,$S$4,d_Type,$T$4) -> 62827 | F61: =SUMIFS(d_Disc,d_Date,">="&$C61,d_Date,"<"&EDATE($C61,1),d_Status,"Delivered",d_Year,$P$4,d_City,$Q$4,d_Cuisine,$R$4,d_Pay,$S$4,d_Type,$T$4) -> 4985 | G61: =SUMIFS(d_Net,d_Date,">="&$C61,d_Date,"<"&EDATE($C61,1),d_Status,"Delivered",d_Year,$P$4,d_City,$Q$4,d_Cuisine,$R$4,d_Pay,$S$4,d_Type,$T$4) -> 57842 | H61: =IFERROR(G61/D61,0) -> 876.39394
B62: =TEXT(C62,"mmm-yy") -> Feb-25 | C62: 45689 | D62: =COUNTIFS(d_Date,">="&$C62,d_Date,"<"&EDATE($C62,1),d_Status,"Delivered",d_Year,$P$4,d_City,$Q$4,d_Cuisine,$R$4,d_Pay,$S$4,d_Type,$T$4) -> 48 | E62: =SUMIFS(d_Gross,d_Date,">="&$C62,d_Date,"<"&EDATE($C62,1),d_Status,"Delivered",d_Year,$P$4,d_City,$Q$4,d_Cuisine,$R$4,d_Pay,$S$4,d_Type,$T$4) -> 47979 | F62: =SUMIFS(d_Disc,d_Date,">="&$C62,d_Date,"<"&EDATE($C62,1),d_Status,"Delivered",d_Year,$P$4,d_City,$Q$4,d_Cuisine,$R$4,d_Pay,$S$4,d_Type,$T$4) -> 3330 | G62: =SUMIFS(d_Net,d_Date,">="&$C62,d_Date,"<"&EDATE($C62,1),d_Status,"Delivered",d_Year,$P$4,d_City,$Q$4,d_Cuisine,$R$4,d_Pay,$S$4,d_Type,$T$4) -> 44649 | H62: =IFERROR(G62/D62,0) -> 930.1875
B63: =TEXT(C63,"mmm-yy") -> Mar-25 | C63: 45717 | D63: =COUNTIFS(d_Date,">="&$C63,d_Date,"<"&EDATE($C63,1),d_Status,"Delivered",d_Year,$P$4,d_City,$Q$4,d_Cuisine,$R$4,d_Pay,$S$4,d_Type,$T$4) -> 55 | E63: =SUMIFS(d_Gross,d_Date,">="&$C63,d_Date,"<"&EDATE($C63,1),d_Status,"Delivered",d_Year,$P$4,d_City,$Q$4,d_Cuisine,$R$4,d_Pay,$S$4,d_Type,$T$4) -> 55750 | F63: =SUMIFS(d_Disc,d_Date,">="&$C63,d_Date,"<"&EDATE($C63,1),d_Status,"Delivered",d_Year,$P$4,d_City,$Q$4,d_Cuisine,$R$4,d_Pay,$S$4,d_Type,$T$4) -> 4910 | G63: =SUMIFS(d_Net,d_Date,">="&$C63,d_Date,"<"&EDATE($C63,1),d_Status,"Delivered",d_Year,$P$4,d_City,$Q$4,d_Cuisine,$R$4,d_Pay,$S$4,d_Type,$T$4) -> 50840 | H63: =IFERROR(G63/D63,0) -> 924.36364
B64: =TEXT(C64,"mmm-yy") -> Apr-25 | C64: 45748 | D64: =COUNTIFS(d_Date,">="&$C64,d_Date,"<"&EDATE($C64,1),d_Status,"Delivered",d_Year,$P$4,d_City,$Q$4,d_Cuisine,$R$4,d_Pay,$S$4,d_Type,$T$4) -> 61 | E64: =SUMIFS(d_Gross,d_Date,">="&$C64,d_Date,"<"&EDATE($C64,1),d_Status,"Delivered",d_Year,$P$4,d_City,$Q$4,d_Cuisine,$R$4,d_Pay,$S$4,d_Type,$T$4) -> 55046 | F64: =SUMIFS(d_Disc,d_Date,">="&$C64,d_Date,"<"&EDATE($C64,1),d_Status,"Delivered",d_Year,$P$4,d_City,$Q$4,d_Cuisine,$R$4,d_Pay,$S$4,d_Type,$T$4) -> 4050 | G64: =SUMIFS(d_Net,d_Date,">="&$C64,d_Date,"<"&EDATE($C64,1),d_Status,"Delivered",d_Year,$P$4,d_City,$Q$4,d_Cuisine,$R$4,d_Pay,$S$4,d_Type,$T$4) -> 50996 | H64: =IFERROR(G64/D64,0) -> 836
B65: =TEXT(C65,"mmm-yy") -> May-25 | C65: 45778 | D65: =COUNTIFS(d_Date,">="&$C65,d_Date,"<"&EDATE($C65,1),d_Status,"Delivered",d_Year,$P$4,d_City,$Q$4,d_Cuisine,$R$4,d_Pay,$S$4,d_Type,$T$4) -> 59 | E65: =SUMIFS(d_Gross,d_Date,">="&$C65,d_Date,"<"&EDATE($C65,1),d_Status,"Delivered",d_Year,$P$4,d_City,$Q$4,d_Cuisine,$R$4,d_Pay,$S$4,d_Type,$T$4) -> 56594 | F65: =SUMIFS(d_Disc,d_Date,">="&$C65,d_Date,"<"&EDATE($C65,1),d_Status,"Delivered",d_Year,$P$4,d_City,$Q$4,d_Cuisine,$R$4,d_Pay,$S$4,d_Type,$T$4) -> 3545 | G65: =SUMIFS(d_Net,d_Date,">="&$C65,d_Date,"<"&EDATE($C65,1),d_Status,"Delivered",d_Year,$P$4,d_City,$Q$4,d_Cuisine,$R$4,d_Pay,$S$4,d_Type,$T$4) -> 53126 | H65: =IFERROR(G65/D65,0) -> 900.44068
B66: =TEXT(C66,"mmm-yy") -> Jun-25 | C66: 45809 | D66: =COUNTIFS(d_Date,">="&$C66,d_Date,"<"&EDATE($C66,1),d_Status,"Delivered",d_Year,$P$4,d_City,$Q$4,d_Cuisine,$R$4,d_Pay,$S$4,d_Type,$T$4) -> 58 | E66: =SUMIFS(d_Gross,d_Date,">="&$C66,d_Date,"<"&EDATE($C66,1),d_Status,"Delivered",d_Year,$P$4,d_City,$Q$4,d_Cuisine,$R$4,d_Pay,$S$4,d_Type,$T$4) -> 57273 | F66: =SUMIFS(d_Disc,d_Date,">="&$C66,d_Date,"<"&EDATE($C66,1),d_Status,"Delivered",d_Year,$P$4,d_City,$Q$4,d_Cuisine,$R$4,d_Pay,$S$4,d_Type,$T$4) -> 4075 | G66: =SUMIFS(d_Net,d_Date,">="&$C66,d_Date,"<"&EDATE($C66,1),d_Status,"Delivered",d_Year,$P$4,d_City,$Q$4,d_Cuisine,$R$4,d_Pay,$S$4,d_Type,$T$4) -> 53242 | H66: =IFERROR(G66/D66,0) -> 917.96552
B67: =TEXT(C67,"mmm-yy") -> Jul-25 | C67: 45839 | D67: =COUNTIFS(d_Date,">="&$C67,d_Date,"<"&EDATE($C67,1),d_Status,"Delivered",d_Year,$P$4,d_City,$Q$4,d_Cuisine,$R$4,d_Pay,$S$4,d_Type,$T$4) -> 59 | E67: =SUMIFS(d_Gross,d_Date,">="&$C67,d_Date,"<"&EDATE($C67,1),d_Status,"Delivered",d_Year,$P$4,d_City,$Q$4,d_Cuisine,$R$4,d_Pay,$S$4,d_Type,$T$4) -> 63191 | F67: =SUMIFS(d_Disc,d_Date,">="&$C67,d_Date,"<"&EDATE($C67,1),d_Status,"Delivered",d_Year,$P$4,d_City,$Q$4,d_Cuisine,$R$4,d_Pay,$S$4,d_Type,$T$4) -> 4490 | G67: =SUMIFS(d_Net,d_Date,">="&$C67,d_Date,"<"&EDATE($C67,1),d_Status,"Delivered",d_Year,$P$4,d_City,$Q$4,d_Cuisine,$R$4,d_Pay,$S$4,d_Type,$T$4) -> 58701 | H67: =IFERROR(G67/D67,0) -> 994.9322
B68: =TEXT(C68,"mmm-yy") -> Aug-25 | C68: 45870 | D68: =COUNTIFS(d_Date,">="&$C68,d_Date,"<"&EDATE($C68,1),d_Status,"Delivered",d_Year,$P$4,d_City,$Q$4,d_Cuisine,$R$4,d_Pay,$S$4,d_Type,$T$4) -> 70 | E68: =SUMIFS(d_Gross,d_Date,">="&$C68,d_Date,"<"&EDATE($C68,1),d_Status,"Delivered",d_Year,$P$4,d_City,$Q$4,d_Cuisine,$R$4,d_Pay,$S$4,d_Type,$T$4) -> 60407 | F68: =SUMIFS(d_Disc,d_Date,">="&$C68,d_Date,"<"&EDATE($C68,1),d_Status,"Delivered",d_Year,$P$4,d_City,$Q$4,d_Cuisine,$R$4,d_Pay,$S$4,d_Type,$T$4) -> 4935 | G68: =SUMIFS(d_Net,d_Date,">="&$C68,d_Date,"<"&EDATE($C68,1),d_Status,"Delivered",d_Year,$P$4,d_City,$Q$4,d_Cuisine,$R$4,d_Pay,$S$4,d_Type,$T$4) -> 55472 | H68: =IFERROR(G68/D68,0) -> 792.45714
B69: =TEXT(C69,"mmm-yy") -> Sep-25 | C69: 45901 | D69: =COUNTIFS(d_Date,">="&$C69,d_Date,"<"&EDATE($C69,1),d_Status,"Delivered",d_Year,$P$4,d_City,$Q$4,d_Cuisine,$R$4,d_Pay,$S$4,d_Type,$T$4) -> 60 | E69: =SUMIFS(d_Gross,d_Date,">="&$C69,d_Date,"<"&EDATE($C69,1),d_Status,"Delivered",d_Year,$P$4,d_City,$Q$4,d_Cuisine,$R$4,d_Pay,$S$4,d_Type,$T$4) -> 57870 | F69: =SUMIFS(d_Disc,d_Date,">="&$C69,d_Date,"<"&EDATE($C69,1),d_Status,"Delivered",d_Year,$P$4,d_City,$Q$4,d_Cuisine,$R$4,d_Pay,$S$4,d_Type,$T$4) -> 4040 | G69: =SUMIFS(d_Net,d_Date,">="&$C69,d_Date,"<"&EDATE($C69,1),d_Status,"Delivered",d_Year,$P$4,d_City,$Q$4,d_Cuisine,$R$4,d_Pay,$S$4,d_Type,$T$4) -> 53830 | H69: =IFERROR(G69/D69,0) -> 897.16667
B70: =TEXT(C70,"mmm-yy") -> Oct-25 | C70: 45931 | D70: =COUNTIFS(d_Date,">="&$C70,d_Date,"<"&EDATE($C70,1),d_Status,"Delivered",d_Year,$P$4,d_City,$Q$4,d_Cuisine,$R$4,d_Pay,$S$4,d_Type,$T$4) -> 63 | E70: =SUMIFS(d_Gross,d_Date,">="&$C70,d_Date,"<"&EDATE($C70,1),d_Status,"Delivered",d_Year,$P$4,d_City,$Q$4,d_Cuisine,$R$4,d_Pay,$S$4,d_Type,$T$4) -> 58274 | F70: =SUMIFS(d_Disc,d_Date,">="&$C70,d_Date,"<"&EDATE($C70,1),d_Status,"Delivered",d_Year,$P$4,d_City,$Q$4,d_Cuisine,$R$4,d_Pay,$S$4,d_Type,$T$4) -> 4555 | G70: =SUMIFS(d_Net,d_Date,">="&$C70,d_Date,"<"&EDATE($C70,1),d_Status,"Delivered",d_Year,$P$4,d_City,$Q$4,d_Cuisine,$R$4,d_Pay,$S$4,d_Type,$T$4) -> 53755 | H70: =IFERROR(G70/D70,0) -> 853.25397
B71: =TEXT(C71,"mmm-yy") -> Nov-25 | C71: 45962 | D71: =COUNTIFS(d_Date,">="&$C71,d_Date,"<"&EDATE($C71,1),d_Status,"Delivered",d_Year,$P$4,d_City,$Q$4,d_Cuisine,$R$4,d_Pay,$S$4,d_Type,$T$4) -> 61 | E71: =SUMIFS(d_Gross,d_Date,">="&$C71,d_Date,"<"&EDATE($C71,1),d_Status,"Delivered",d_Year,$P$4,d_City,$Q$4,d_Cuisine,$R$4,d_Pay,$S$4,d_Type,$T$4) -> 61149 | F71: =SUMIFS(d_Disc,d_Date,">="&$C71,d_Date,"<"&EDATE($C71,1),d_Status,"Delivered",d_Year,$P$4,d_City,$Q$4,d_Cuisine,$R$4,d_Pay,$S$4,d_Type,$T$4) -> 4395 | G71: =SUMIFS(d_Net,d_Date,">="&$C71,d_Date,"<"&EDATE($C71,1),d_Status,"Delivered",d_Year,$P$4,d_City,$Q$4,d_Cuisine,$R$4,d_Pay,$S$4,d_Type,$T$4) -> 56754 | H71: =IFERROR(G71/D71,0) -> 930.39344
B72: =TEXT(C72,"mmm-yy") -> Dec-25 | C72: 45992 | D72: =COUNTIFS(d_Date,">="&$C72,d_Date,"<"&EDATE($C72,1),d_Status,"Delivered",d_Year,$P$4,d_City,$Q$4,d_Cuisine,$R$4,d_Pay,$S$4,d_Type,$T$4) -> 61 | E72: =SUMIFS(d_Gross,d_Date,">="&$C72,d_Date,"<"&EDATE($C72,1),d_Status,"Delivered",d_Year,$P$4,d_City,$Q$4,d_Cuisine,$R$4,d_Pay,$S$4,d_Type,$T$4) -> 57316 | F72: =SUMIFS(d_Disc,d_Date,">="&$C72,d_Date,"<"&EDATE($C72,1),d_Status,"Delivered",d_Year,$P$4,d_City,$Q$4,d_Cuisine,$R$4,d_Pay,$S$4,d_Type,$T$4) -> 3985 | G72: =SUMIFS(d_Net,d_Date,">="&$C72,d_Date,"<"&EDATE($C72,1),d_Status,"Delivered",d_Year,$P$4,d_City,$Q$4,d_Cuisine,$R$4,d_Pay,$S$4,d_Type,$T$4) -> 53347 | H72: =IFERROR(G72/D72,0) -> 874.54098
... B74: =TEXT(C74,"mmm-yy") -> Feb-26 | C74: 46054 | D74: =COUNTIFS(d_Date,">="&$C74,d_Date,"<"&EDATE($C74,1),d_Status,"Delivered",d_Year,$P$4,d_City,$Q$4,d_Cuisine,$R$4,d_Pay,$S$4,d_Type,$T$4) -> 7 | E74: =SUMIFS(d_Gross,d_Date,">="&$C74,d_Date,"<"&EDATE($C74,1),d_Status,"Delivered",d_Year,$P$4,d_City,$Q$4,d_Cuisine,$R$4,d_Pay,$S$4,d_Type,$T$4) -> 4808 | F74: =SUMIFS(d_Disc,d_Date,">="&$C74,d_Date,"<"&EDATE($C74,1),d_Status,"Delivered",d_Year,$P$4,d_City,$Q$4,d_Cuisine,$R$4,d_Pay,$S$4,d_Type,$T$4) -> 785 | G74: =SUMIFS(d_Net,d_Date,">="&$C74,d_Date,"<"&EDATE($C74,1),d_Status,"Delivered",d_Year,$P$4,d_City,$Q$4,d_Cuisine,$R$4,d_Pay,$S$4,d_Type,$T$4) -> 4025 | H74: =IFERROR(G74/D74,0) -> 575
B75: Total / Overall | D75: =SUM(D61:D74) -> 791 | E75: =SUM(E61:E74) -> 755840 | F75: =SUM(F61:F74) -> 56065 | G75: =SUM(G61:G74) -> 699950 | H75: =IFERROR(G75/D75,0) -> 884.89254
B76: Gross − Discounts may differ from Net by a few rupees where a discount exceeded the order amount (Net floored at 0 in source data).
B79: Revenue by city
B80: City | C80: Delivered orders | D80: Gross revenue | E80: Discounts | F80: Net revenue | G80: Share of net | H80: Avg net / order
B81: Delhi | C81: =COUNTIFS(d_City,$B81,d_Status,"Delivered",d_Year,$P$4,d_City,$Q$4,d_Cuisine,$R$4,d_Pay,$S$4,d_Type,$T$4) -> 81 | D81: =SUMIFS(d_Gross,d_City,$B81,d_Status,"Delivered",d_Year,$P$4,d_City,$Q$4,d_Cuisine,$R$4,d_Pay,$S$4,d_Type,$T$4) -> 78708 | E81: =SUMIFS(d_Disc,d_City,$B81,d_Status,"Delivered",d_Year,$P$4,d_City,$Q$4,d_Cuisine,$R$4,d_Pay,$S$4,d_Type,$T$4) -> 6615 | F81: =SUMIFS(d_Net,d_City,$B81,d_Status,"Delivered",d_Year,$P$4,d_City,$Q$4,d_Cuisine,$R$4,d_Pay,$S$4,d_Type,$T$4) -> 72095 | G81: =IFERROR(F81/SUMIFS(d_Net,d_Status,"Delivered",d_Year,$P$4,d_City,$Q$4,d_Cuisine,$R$4,d_Pay,$S$4,d_Type,$T$4),0) -> 0.10300021 | H81: =IFERROR(F81/C81,0) -> 890.06173
B82: Ahmedabad | C82: =COUNTIFS(d_City,$B82,d_Status,"Delivered",d_Year,$P$4,d_City,$Q$4,d_Cuisine,$R$4,d_Pay,$S$4,d_Type,$T$4) -> 80 | D82: =SUMIFS(d_Gross,d_City,$B82,d_Status,"Delivered",d_Year,$P$4,d_City,$Q$4,d_Cuisine,$R$4,d_Pay,$S$4,d_Type,$T$4) -> 73459 | E82: =SUMIFS(d_Disc,d_City,$B82,d_Status,"Delivered",d_Year,$P$4,d_City,$Q$4,d_Cuisine,$R$4,d_Pay,$S$4,d_Type,$T$4) -> 5220 | F82: =SUMIFS(d_Net,d_City,$B82,d_Status,"Delivered",d_Year,$P$4,d_City,$Q$4,d_Cuisine,$R$4,d_Pay,$S$4,d_Type,$T$4) -> 68239 | G82: =IFERROR(F82/SUMIFS(d_Net,d_Status,"Delivered",d_Year,$P$4,d_City,$Q$4,d_Cuisine,$R$4,d_Pay,$S$4,d_Type,$T$4),0) -> 0.097491249 | H82: =IFERROR(F82/C82,0) -> 852.9875
B83: Bengaluru | C83: =COUNTIFS(d_City,$B83,d_Status,"Delivered",d_Year,$P$4,d_City,$Q$4,d_Cuisine,$R$4,d_Pay,$S$4,d_Type,$T$4) -> 71 | D83: =SUMIFS(d_Gross,d_City,$B83,d_Status,"Delivered",d_Year,$P$4,d_City,$Q$4,d_Cuisine,$R$4,d_Pay,$S$4,d_Type,$T$4) -> 67838 | E83: =SUMIFS(d_Disc,d_City,$B83,d_Status,"Delivered",d_Year,$P$4,d_City,$Q$4,d_Cuisine,$R$4,d_Pay,$S$4,d_Type,$T$4) -> 4600 | F83: =SUMIFS(d_Net,d_City,$B83,d_Status,"Delivered",d_Year,$P$4,d_City,$Q$4,d_Cuisine,$R$4,d_Pay,$S$4,d_Type,$T$4) -> 63265 | G83: =IFERROR(F83/SUMIFS(d_Net,d_Status,"Delivered",d_Year,$P$4,d_City,$Q$4,d_Cuisine,$R$4,d_Pay,$S$4,d_Type,$T$4),0) -> 0.090385028 | H83: =IFERROR(F83/C83,0) -> 891.05634
B84: Chennai | C84: =COUNTIFS(d_City,$B84,d_Status,"Delivered",d_Year,$P$4,d_City,$Q$4,d_Cuisine,$R$4,d_Pay,$S$4,d_Type,$T$4) -> 72 | D84: =SUMIFS(d_Gross,d_City,$B84,d_Status,"Delivered",d_Year,$P$4,d_City,$Q$4,d_Cuisine,$R$4,d_Pay,$S$4,d_Type,$T$4) -> 68210 | E84: =SUMIFS(d_Disc,d_City,$B84,d_Status,"Delivered",d_Year,$P$4,d_City,$Q$4,d_Cuisine,$R$4,d_Pay,$S$4,d_Type,$T$4) -> 6240 | F84: =SUMIFS(d_Net,d_City,$B84,d_Status,"Delivered",d_Year,$P$4,d_City,$Q$4,d_Cuisine,$R$4,d_Pay,$S$4,d_Type,$T$4) -> 61979 | G84: =IFERROR(F84/SUMIFS(d_Net,d_Status,"Delivered",d_Year,$P$4,d_City,$Q$4,d_Cuisine,$R$4,d_Pay,$S$4,d_Type,$T$4),0) -> 0.088547753 | H84: =IFERROR(F84/C84,0) -> 860.81944
B85: Noida | C85: =COUNTIFS(d_City,$B85,d_Status,"Delivered",d_Year,$P$4,d_City,$Q$4,d_Cuisine,$R$4,d_Pay,$S$4,d_Type,$T$4) -> 67 | D85: =SUMIFS(d_Gross,d_City,$B85,d_Status,"Delivered",d_Year,$P$4,d_City,$Q$4,d_Cuisine,$R$4,d_Pay,$S$4,d_Type,$T$4) -> 67623 | E85: =SUMIFS(d_Disc,d_City,$B85,d_Status,"Delivered",d_Year,$P$4,d_City,$Q$4,d_Cuisine,$R$4,d_Pay,$S$4,d_Type,$T$4) -> 4305 | F85: =SUMIFS(d_Net,d_City,$B85,d_Status,"Delivered",d_Year,$P$4,d_City,$Q$4,d_Cuisine,$R$4,d_Pay,$S$4,d_Type,$T$4) -> 63318 | G85: =IFERROR(F85/SUMIFS(d_Net,d_Status,"Delivered",d_Year,$P$4,d_City,$Q$4,d_Cuisine,$R$4,d_Pay,$S$4,d_Type,$T$4),0) -> 0.090460747 | H85: =IFERROR(F85/C85,0) -> 945.04478
B86: Jaipur | C86: =COUNTIFS(d_City,$B86,d_Status,"Delivered",d_Year,$P$4,d_City,$Q$4,d_Cuisine,$R$4,d_Pay,$S$4,d_Type,$T$4) -> 71 | D86: =SUMIFS(d_Gross,d_City,$B86,d_Status,"Delivered",d_Year,$P$4,d_City,$Q$4,d_Cuisine,$R$4,d_Pay,$S$4,d_Type,$T$4) -> 66968 | E86: =SUMIFS(d_Disc,d_City,$B86,d_Status,"Delivered",d_Year,$P$4,d_City,$Q$4,d_Cuisine,$R$4,d_Pay,$S$4,d_Type,$T$4) -> 4645 | F86: =SUMIFS(d_Net,d_City,$B86,d_Status,"Delivered",d_Year,$P$4,d_City,$Q$4,d_Cuisine,$R$4,d_Pay,$S$4,d_Type,$T$4) -> 62339 | G86: =IFERROR(F86/SUMIFS(d_Net,d_Status,"Delivered",d_Year,$P$4,d_City,$Q$4,d_Cuisine,$R$4,d_Pay,$S$4,d_Type,$T$4),0) -> 0.089062076 | H86: =IFERROR(F86/C86,0) -> 878.01408
B87: Hyderabad | C87: =COUNTIFS(d_City,$B87,d_Status,"Delivered",d_Year,$P$4,d_City,$Q$4,d_Cuisine,$R$4,d_Pay,$S$4,d_Type,$T$4) -> 57 | D87: =SUMIFS(d_Gross,d_City,$B87,d_Status,"Delivered",d_Year,$P$4,d_City,$Q$4,d_Cuisine,$R$4,d_Pay,$S$4,d_Type,$T$4) -> 55758 | E87: =SUMIFS(d_Disc,d_City,$B87,d_Status,"Delivered",d_Year,$P$4,d_City,$Q$4,d_Cuisine,$R$4,d_Pay,$S$4,d_Type,$T$4) -> 4695 | F87: =SUMIFS(d_Net,d_City,$B87,d_Status,"Delivered",d_Year,$P$4,d_City,$Q$4,d_Cuisine,$R$4,d_Pay,$S$4,d_Type,$T$4) -> 51140 | G87: =IFERROR(F87/SUMIFS(d_Net,d_Status,"Delivered",d_Year,$P$4,d_City,$Q$4,d_Cuisine,$R$4,d_Pay,$S$4,d_Type,$T$4),0) -> 0.073062362 | H87: =IFERROR(F87/C87,0) -> 897.19298
B88: Pune | C88: =COUNTIFS(d_City,$B88,d_Status,"Delivered",d_Year,$P$4,d_City,$Q$4,d_Cuisine,$R$4,d_Pay,$S$4,d_Type,$T$4) -> 61 | D88: =SUMIFS(d_Gross,d_City,$B88,d_Status,"Delivered",d_Year,$P$4,d_City,$Q$4,d_Cuisine,$R$4,d_Pay,$S$4,d_Type,$T$4) -> 55660 | E88: =SUMIFS(d_Disc,d_City,$B88,d_Status,"Delivered",d_Year,$P$4,d_City,$Q$4,d_Cuisine,$R$4,d_Pay,$S$4,d_Type,$T$4) -> 4450 | F88: =SUMIFS(d_Net,d_City,$B88,d_Status,"Delivered",d_Year,$P$4,d_City,$Q$4,d_Cuisine,$R$4,d_Pay,$S$4,d_Type,$T$4) -> 51254 | G88: =IFERROR(F88/SUMIFS(d_Net,d_Status,"Delivered",d_Year,$P$4,d_City,$Q$4,d_Cuisine,$R$4,d_Pay,$S$4,d_Type,$T$4),0) -> 0.07322523 | H88: =IFERROR(F88/C88,0) -> 840.22951
B89: Kolkata | C89: =COUNTIFS(d_City,$B89,d_Status,"Delivered",d_Year,$P$4,d_City,$Q$4,d_Cuisine,$R$4,d_Pay,$S$4,d_Type,$T$4) -> 62 | D89: =SUMIFS(d_Gross,d_City,$B89,d_Status,"Delivered",d_Year,$P$4,d_City,$Q$4,d_Cuisine,$R$4,d_Pay,$S$4,d_Type,$T$4) -> 54061 | E89: =SUMIFS(d_Disc,d_City,$B89,d_Status,"Delivered",d_Year,$P$4,d_City,$Q$4,d_Cuisine,$R$4,d_Pay,$S$4,d_Type,$T$4) -> 3350 | F89: =SUMIFS(d_Net,d_City,$B89,d_Status,"Delivered",d_Year,$P$4,d_City,$Q$4,d_Cuisine,$R$4,d_Pay,$S$4,d_Type,$T$4) -> 50711 | G89: =IFERROR(F89/SUMIFS(d_Net,d_Status,"Delivered",d_Year,$P$4,d_City,$Q$4,d_Cuisine,$R$4,d_Pay,$S$4,d_Type,$T$4),0) -> 0.072449461 | H89: =IFERROR(F89/C89,0) -> 817.91935
B90: Lucknow | C90: =COUNTIFS(d_City,$B90,d_Status,"Delivered",d_Year,$P$4,d_City,$Q$4,d_Cuisine,$R$4,d_Pay,$S$4,d_Type,$T$4) -> 61 | D90: =SUMIFS(d_Gross,d_City,$B90,d_Status,"Delivered",d_Year,$P$4,d_City,$Q$4,d_Cuisine,$R$4,d_Pay,$S$4,d_Type,$T$4) -> 63629 | E90: =SUMIFS(d_Disc,d_City,$B90,d_Status,"Delivered",d_Year,$P$4,d_City,$Q$4,d_Cuisine,$R$4,d_Pay,$S$4,d_Type,$T$4) -> 5040 | F90: =SUMIFS(d_Net,d_City,$B90,d_Status,"Delivered",d_Year,$P$4,d_City,$Q$4,d_Cuisine,$R$4,d_Pay,$S$4,d_Type,$T$4) -> 58589 | G90: =IFERROR(F90/SUMIFS(d_Net,d_Status,"Delivered",d_Year,$P$4,d_City,$Q$4,d_Cuisine,$R$4,d_Pay,$S$4,d_Type,$T$4),0) -> 0.08370455 | H90: =IFERROR(F90/C90,0) -> 960.47541
B91: Mumbai | C91: =COUNTIFS(d_City,$B91,d_Status,"Delivered",d_Year,$P$4,d_City,$Q$4,d_Cuisine,$R$4,d_Pay,$S$4,d_Type,$T$4) -> 53 | D91: =SUMIFS(d_Gross,d_City,$B91,d_Status,"Delivered",d_Year,$P$4,d_City,$Q$4,d_Cuisine,$R$4,d_Pay,$S$4,d_Type,$T$4) -> 47690 | E91: =SUMIFS(d_Disc,d_City,$B91,d_Status,"Delivered",d_Year,$P$4,d_City,$Q$4,d_Cuisine,$R$4,d_Pay,$S$4,d_Type,$T$4) -> 3395 | F91: =SUMIFS(d_Net,d_City,$B91,d_Status,"Delivered",d_Year,$P$4,d_City,$Q$4,d_Cuisine,$R$4,d_Pay,$S$4,d_Type,$T$4) -> 44295 | G91: =IFERROR(F91/SUMIFS(d_Net,d_Status,"Delivered",d_Year,$P$4,d_City,$Q$4,d_Cuisine,$R$4,d_Pay,$S$4,d_Type,$T$4),0) -> 0.063283092 | H91: =IFERROR(F91/C91,0) -> 835.75472
B92: Gurugram | C92: =COUNTIFS(d_City,$B92,d_Status,"Delivered",d_Year,$P$4,d_City,$Q$4,d_Cuisine,$R$4,d_Pay,$S$4,d_Type,$T$4) -> 55 | D92: =SUMIFS(d_Gross,d_City,$B92,d_Status,"Delivered",d_Year,$P$4,d_City,$Q$4,d_Cuisine,$R$4,d_Pay,$S$4,d_Type,$T$4) -> 56236 | E92: =SUMIFS(d_Disc,d_City,$B92,d_Status,"Delivered",d_Year,$P$4,d_City,$Q$4,d_Cuisine,$R$4,d_Pay,$S$4,d_Type,$T$4) -> 3510 | F92: =SUMIFS(d_Net,d_City,$B92,d_Status,"Delivered",d_Year,$P$4,d_City,$Q$4,d_Cuisine,$R$4,d_Pay,$S$4,d_Type,$T$4) -> 52726 | G92: =IFERROR(F92/SUMIFS(d_Net,d_Status,"Delivered",d_Year,$P$4,d_City,$Q$4,d_Cuisine,$R$4,d_Pay,$S$4,d_Type,$T$4),0) -> 0.075328238 | H92: =IFERROR(F92/C92,0) -> 958.65455
B93: Total / Overall | C93: =SUM(C81:C92) -> 791 | D93: =SUM(D81:D92) -> 755840 | E93: =SUM(E81:E92) -> 56065 | F93: =SUM(F81:F92) -> 699950 | G93: =SUM(G81:G92) -> 1 | H93: =IFERROR(F93/C93,0) -> 884.89254
B96: Revenue by cuisine
B97: Cuisine | C97: Delivered orders | D97: Gross revenue | E97: Discounts | F97: Net revenue | G97: Share of net | H97: Avg net / order
B98: Burgers | C98: =COUNTIFS(d_Cuisine,$B98,d_Status,"Delivered",d_Year,$P$4,d_City,$Q$4,d_Cuisine,$R$4,d_Pay,$S$4,d_Type,$T$4) -> 98 | D98: =SUMIFS(d_Gross,d_Cuisine,$B98,d_Status,"Delivered",d_Year,$P$4,d_City,$Q$4,d_Cuisine,$R$4,d_Pay,$S$4,d_Type,$T$4) -> 90601 | E98: =SUMIFS(d_Disc,d_Cuisine,$B98,d_Status,"Delivered",d_Year,$P$4,d_City,$Q$4,d_Cuisine,$R$4,d_Pay,$S$4,d_Type,$T$4) -> 5810 | F98: =SUMIFS(d_Net,d_Cuisine,$B98,d_Status,"Delivered",d_Year,$P$4,d_City,$Q$4,d_Cuisine,$R$4,d_Pay,$S$4,d_Type,$T$4) -> 84791 | G98: =IFERROR(F98/SUMIFS(d_Net,d_Status,"Delivered",d_Year,$P$4,d_City,$Q$4,d_Cuisine,$R$4,d_Pay,$S$4,d_Type,$T$4),0) -> 0.12113865 | H98: =IFERROR(F98/C98,0) -> 865.21429
B99: North Indian | C99: =COUNTIFS(d_Cuisine,$B99,d_Status,"Delivered",d_Year,$P$4,d_City,$Q$4,d_Cuisine,$R$4,d_Pay,$S$4,d_Type,$T$4) -> 88 | D99: =SUMIFS(d_Gross,d_Cuisine,$B99,d_Status,"Delivered",d_Year,$P$4,d_City,$Q$4,d_Cuisine,$R$4,d_Pay,$S$4,d_Type,$T$4) -> 79762 | E99: =SUMIFS(d_Disc,d_Cuisine,$B99,d_Status,"Delivered",d_Year,$P$4,d_City,$Q$4,d_Cuisine,$R$4,d_Pay,$S$4,d_Type,$T$4) -> 7850 | F99: =SUMIFS(d_Net,d_Cuisine,$B99,d_Status,"Delivered",d_Year,$P$4,d_City,$Q$4,d_Cuisine,$R$4,d_Pay,$S$4,d_Type,$T$4) -> 71912 | G99: =IFERROR(F99/SUMIFS(d_Net,d_Status,"Delivered",d_Year,$P$4,d_City,$Q$4,d_Cuisine,$R$4,d_Pay,$S$4,d_Type,$T$4),0) -> 0.10273877 | H99: =IFERROR(F99/C99,0) -> 817.18182
B100: Desserts | C100: =COUNTIFS(d_Cuisine,$B100,d_Status,"Delivered",d_Year,$P$4,d_City,$Q$4,d_Cuisine,$R$4,d_Pay,$S$4,d_Type,$T$4) -> 84 | D100: =SUMIFS(d_Gross,d_Cuisine,$B100,d_Status,"Delivered",d_Year,$P$4,d_City,$Q$4,d_Cuisine,$R$4,d_Pay,$S$4,d_Type,$T$4) -> 76812 | E100: =SUMIFS(d_Disc,d_Cuisine,$B100,d_Status,"Delivered",d_Year,$P$4,d_City,$Q$4,d_Cuisine,$R$4,d_Pay,$S$4,d_Type,$T$4) -> 6320 | F100: =SUMIFS(d_Net,d_Cuisine,$B100,d_Status,"Delivered",d_Year,$P$4,d_City,$Q$4,d_Cuisine,$R$4,d_Pay,$S$4,d_Type,$T$4) -> 70578 | G100: =IFERROR(F100/SUMIFS(d_Net,d_Status,"Delivered",d_Year,$P$4,d_City,$Q$4,d_Cuisine,$R$4,d_Pay,$S$4,d_Type,$T$4),0) -> 0.10083292 | H100: =IFERROR(F100/C100,0) -> 840.21429
B101: Fast Food | C101: =COUNTIFS(d_Cuisine,$B101,d_Status,"Delivered",d_Year,$P$4,d_City,$Q$4,d_Cuisine,$R$4,d_Pay,$S$4,d_Type,$T$4) -> 83 | D101: =SUMIFS(d_Gross,d_Cuisine,$B101,d_Status,"Delivered",d_Year,$P$4,d_City,$Q$4,d_Cuisine,$R$4,d_Pay,$S$4,d_Type,$T$4) -> 72288 | E101: =SUMIFS(d_Disc,d_Cuisine,$B101,d_Status,"Delivered",d_Year,$P$4,d_City,$Q$4,d_Cuisine,$R$4,d_Pay,$S$4,d_Type,$T$4) -> 6220 | F101: =SUMIFS(d_Net,d_Cuisine,$B101,d_Status,"Delivered",d_Year,$P$4,d_City,$Q$4,d_Cuisine,$R$4,d_Pay,$S$4,d_Type,$T$4) -> 66084 | G101: =IFERROR(F101/SUMIFS(d_Net,d_Status,"Delivered",d_Year,$P$4,d_City,$Q$4,d_Cuisine,$R$4,d_Pay,$S$4,d_Type,$T$4),0) -> 0.094412458 | H101: =IFERROR(F101/C101,0) -> 796.19277
B102: Chinese | C102: =COUNTIFS(d_Cuisine,$B102,d_Status,"Delivered",d_Year,$P$4,d_City,$Q$4,d_Cuisine,$R$4,d_Pay,$S$4,d_Type,$T$4) -> 81 | D102: =SUMIFS(d_Gross,d_Cuisine,$B102,d_Status,"Delivered",d_Year,$P$4,d_City,$Q$4,d_Cuisine,$R$4,d_Pay,$S$4,d_Type,$T$4) -> 81394 | E102: =SUMIFS(d_Disc,d_Cuisine,$B102,d_Status,"Delivered",d_Year,$P$4,d_City,$Q$4,d_Cuisine,$R$4,d_Pay,$S$4,d_Type,$T$4) -> 6350 | F102: =SUMIFS(d_Net,d_Cuisine,$B102,d_Status,"Delivered",d_Year,$P$4,d_City,$Q$4,d_Cuisine,$R$4,d_Pay,$S$4,d_Type,$T$4) -> 75044 | G102: =IFERROR(F102/SUMIFS(d_Net,d_Status,"Delivered",d_Year,$P$4,d_City,$Q$4,d_Cuisine,$R$4,d_Pay,$S$4,d_Type,$T$4),0) -> 0.10721337 | H102: =IFERROR(F102/C102,0) -> 926.46914
B103: Momos | C103: =COUNTIFS(d_Cuisine,$B103,d_Status,"Delivered",d_Year,$P$4,d_City,$Q$4,d_Cuisine,$R$4,d_Pay,$S$4,d_Type,$T$4) -> 71 | D103: =SUMIFS(d_Gross,d_Cuisine,$B103,d_Status,"Delivered",d_Year,$P$4,d_City,$Q$4,d_Cuisine,$R$4,d_Pay,$S$4,d_Type,$T$4) -> 70267 | E103: =SUMIFS(d_Disc,d_Cuisine,$B103,d_Status,"Delivered",d_Year,$P$4,d_City,$Q$4,d_Cuisine,$R$4,d_Pay,$S$4,d_Type,$T$4) -> 3765 | F103: =SUMIFS(d_Net,d_Cuisine,$B103,d_Status,"Delivered",d_Year,$P$4,d_City,$Q$4,d_Cuisine,$R$4,d_Pay,$S$4,d_Type,$T$4) -> 66546 | G103: =IFERROR(F103/SUMIFS(d_Net,d_Status,"Delivered",d_Year,$P$4,d_City,$Q$4,d_Cuisine,$R$4,d_Pay,$S$4,d_Type,$T$4),0) -> 0.095072505 | H103: =IFERROR(F103/C103,0) -> 937.26761
B104: Biryani | C104: =COUNTIFS(d_Cuisine,$B104,d_Status,"Delivered",d_Year,$P$4,d_City,$Q$4,d_Cuisine,$R$4,d_Pay,$S$4,d_Type,$T$4) -> 81 | D104: =SUMIFS(d_Gross,d_Cuisine,$B104,d_Status,"Delivered",d_Year,$P$4,d_City,$Q$4,d_Cuisine,$R$4,d_Pay,$S$4,d_Type,$T$4) -> 78668 | E104: =SUMIFS(d_Disc,d_Cuisine,$B104,d_Status,"Delivered",d_Year,$P$4,d_City,$Q$4,d_Cuisine,$R$4,d_Pay,$S$4,d_Type,$T$4) -> 5830 | F104: =SUMIFS(d_Net,d_Cuisine,$B104,d_Status,"Delivered",d_Year,$P$4,d_City,$Q$4,d_Cuisine,$R$4,d_Pay,$S$4,d_Type,$T$4) -> 72865 | G104: =IFERROR(F104/SUMIFS(d_Net,d_Status,"Delivered",d_Year,$P$4,d_City,$Q$4,d_Cuisine,$R$4,d_Pay,$S$4,d_Type,$T$4),0) -> 0.10410029 | H104: =IFERROR(F104/C104,0) -> 899.5679
B105: Healthy | C105: =COUNTIFS(d_Cuisine,$B105,d_Status,"Delivered",d_Year,$P$4,d_City,$Q$4,d_Cuisine,$R$4,d_Pay,$S$4,d_Type,$T$4) -> 76 | D105: =SUMIFS(d_Gross,d_Cuisine,$B105,d_Status,"Delivered",d_Year,$P$4,d_City,$Q$4,d_Cuisine,$R$4,d_Pay,$S$4,d_Type,$T$4) -> 77913 | E105: =SUMIFS(d_Disc,d_Cuisine,$B105,d_Status,"Delivered",d_Year,$P$4,d_City,$Q$4,d_Cuisine,$R$4,d_Pay,$S$4,d_Type,$T$4) -> 5585 | F105: =SUMIFS(d_Net,d_Cuisine,$B105,d_Status,"Delivered",d_Year,$P$4,d_City,$Q$4,d_Cuisine,$R$4,d_Pay,$S$4,d_Type,$T$4) -> 72330 | G105: =IFERROR(F105/SUMIFS(d_Net,d_Status,"Delivered",d_Year,$P$4,d_City,$Q$4,d_Cuisine,$R$4,d_Pay,$S$4,d_Type,$T$4),0) -> 0.10333595 | H105: =IFERROR(F105/C105,0) -> 951.71053
B106: Pizza | C106: =COUNTIFS(d_Cuisine,$B106,d_Status,"Delivered",d_Year,$P$4,d_City,$Q$4,d_Cuisine,$R$4,d_Pay,$S$4,d_Type,$T$4) -> 63 | D106: =SUMIFS(d_Gross,d_Cuisine,$B106,d_Status,"Delivered",d_Year,$P$4,d_City,$Q$4,d_Cuisine,$R$4,d_Pay,$S$4,d_Type,$T$4) -> 63374 | E106: =SUMIFS(d_Disc,d_Cuisine,$B106,d_Status,"Delivered",d_Year,$P$4,d_City,$Q$4,d_Cuisine,$R$4,d_Pay,$S$4,d_Type,$T$4) -> 3855 | F106: =SUMIFS(d_Net,d_Cuisine,$B106,d_Status,"Delivered",d_Year,$P$4,d_City,$Q$4,d_Cuisine,$R$4,d_Pay,$S$4,d_Type,$T$4) -> 59519 | G106: =IFERROR(F106/SUMIFS(d_Net,d_Status,"Delivered",d_Year,$P$4,d_City,$Q$4,d_Cuisine,$R$4,d_Pay,$S$4,d_Type,$T$4),0) -> 0.085033217 | H106: =IFERROR(F106/C106,0) -> 944.74603
B107: South Indian | C107: =COUNTIFS(d_Cuisine,$B107,d_Status,"Delivered",d_Year,$P$4,d_City,$Q$4,d_Cuisine,$R$4,d_Pay,$S$4,d_Type,$T$4) -> 66 | D107: =SUMIFS(d_Gross,d_Cuisine,$B107,d_Status,"Delivered",d_Year,$P$4,d_City,$Q$4,d_Cuisine,$R$4,d_Pay,$S$4,d_Type,$T$4) -> 64761 | E107: =SUMIFS(d_Disc,d_Cuisine,$B107,d_Status,"Delivered",d_Year,$P$4,d_City,$Q$4,d_Cuisine,$R$4,d_Pay,$S$4,d_Type,$T$4) -> 4480 | F107: =SUMIFS(d_Net,d_Cuisine,$B107,d_Status,"Delivered",d_Year,$P$4,d_City,$Q$4,d_Cuisine,$R$4,d_Pay,$S$4,d_Type,$T$4) -> 60281 | G107: =IFERROR(F107/SUMIFS(d_Net,d_Status,"Delivered",d_Year,$P$4,d_City,$Q$4,d_Cuisine,$R$4,d_Pay,$S$4,d_Type,$T$4),0) -> 0.086121866 | H107: =IFERROR(F107/C107,0) -> 913.34848
B108: Total / Overall | C108: =SUM(C98:C107) -> 791 | D108: =SUM(D98:D107) -> 755840 | E108: =SUM(E98:E107) -> 56065 | F108: =SUM(F98:F107) -> 699950 | G108: =SUM(G98:G107) -> 1 | H108: =IFERROR(F108/C108,0) -> 884.89254
B111: Revenue by payment method
B112: Payment method | C112: Delivered orders | D112: Gross revenue | E112: Discounts | F112: Net revenue | G112: Share of net | H112: Avg net / order
B113: UPI | C113: =COUNTIFS(d_Pay,$B113,d_Status,"Delivered",d_Year,$P$4,d_City,$Q$4,d_Cuisine,$R$4,d_Pay,$S$4,d_Type,$T$4) -> 334 | D113: =SUMIFS(d_Gross,d_Pay,$B113,d_Status,"Delivered",d_Year,$P$4,d_City,$Q$4,d_Cuisine,$R$4,d_Pay,$S$4,d_Type,$T$4) -> 309135 | E113: =SUMIFS(d_Disc,d_Pay,$B113,d_Status,"Delivered",d_Year,$P$4,d_City,$Q$4,d_Cuisine,$R$4,d_Pay,$S$4,d_Type,$T$4) -> 22770 | F113: =SUMIFS(d_Net,d_Pay,$B113,d_Status,"Delivered",d_Year,$P$4,d_City,$Q$4,d_Cuisine,$R$4,d_Pay,$S$4,d_Type,$T$4) -> 286374 | G113: =IFERROR(F113/SUMIFS(d_Net,d_Status,"Delivered",d_Year,$P$4,d_City,$Q$4,d_Cuisine,$R$4,d_Pay,$S$4,d_Type,$T$4),0) -> 0.40913494 | H113: =IFERROR(F113/C113,0) -> 857.40719
B114: Credit Card | C114: =COUNTIFS(d_Pay,$B114,d_Status,"Delivered",d_Year,$P$4,d_City,$Q$4,d_Cuisine,$R$4,d_Pay,$S$4,d_Type,$T$4) -> 159 | D114: =SUMIFS(d_Gross,d_Pay,$B114,d_Status,"Delivered",d_Year,$P$4,d_City,$Q$4,d_Cuisine,$R$4,d_Pay,$S$4,d_Type,$T$4) -> 153578 | E114: =SUMIFS(d_Disc,d_Pay,$B114,d_Status,"Delivered",d_Year,$P$4,d_City,$Q$4,d_Cuisine,$R$4,d_Pay,$S$4,d_Type,$T$4) -> 11540 | F114: =SUMIFS(d_Net,d_Pay,$B114,d_Status,"Delivered",d_Year,$P$4,d_City,$Q$4,d_Cuisine,$R$4,d_Pay,$S$4,d_Type,$T$4) -> 142038 | G114: =IFERROR(F114/SUMIFS(d_Net,d_Status,"Delivered",d_Year,$P$4,d_City,$Q$4,d_Cuisine,$R$4,d_Pay,$S$4,d_Type,$T$4),0) -> 0.20292592 | H114: =IFERROR(F114/C114,0) -> 893.32075
B115: Debit Card | C115: =COUNTIFS(d_Pay,$B115,d_Status,"Delivered",d_Year,$P$4,d_City,$Q$4,d_Cuisine,$R$4,d_Pay,$S$4,d_Type,$T$4) -> 145 | D115: =SUMIFS(d_Gross,d_Pay,$B115,d_Status,"Delivered",d_Year,$P$4,d_City,$Q$4,d_Cuisine,$R$4,d_Pay,$S$4,d_Type,$T$4) -> 138520 | E115: =SUMIFS(d_Disc,d_Pay,$B115,d_Status,"Delivered",d_Year,$P$4,d_City,$Q$4,d_Cuisine,$R$4,d_Pay,$S$4,d_Type,$T$4) -> 10075 | F115: =SUMIFS(d_Net,d_Pay,$B115,d_Status,"Delivered",d_Year,$P$4,d_City,$Q$4,d_Cuisine,$R$4,d_Pay,$S$4,d_Type,$T$4) -> 128565 | G115: =IFERROR(F115/SUMIFS(d_Net,d_Status,"Delivered",d_Year,$P$4,d_City,$Q$4,d_Cuisine,$R$4,d_Pay,$S$4,d_Type,$T$4),0) -> 0.18367741 | H115: =IFERROR(F115/C115,0) -> 886.65517
B116: Cash | C116: =COUNTIFS(d_Pay,$B116,d_Status,"Delivered",d_Year,$P$4,d_City,$Q$4,d_Cuisine,$R$4,d_Pay,$S$4,d_Type,$T$4) -> 90 | D116: =SUMIFS(d_Gross,d_Pay,$B116,d_Status,"Delivered",d_Year,$P$4,d_City,$Q$4,d_Cuisine,$R$4,d_Pay,$S$4,d_Type,$T$4) -> 89001 | E116: =SUMIFS(d_Disc,d_Pay,$B116,d_Status,"Delivered",d_Year,$P$4,d_City,$Q$4,d_Cuisine,$R$4,d_Pay,$S$4,d_Type,$T$4) -> 6695 | F116: =SUMIFS(d_Net,d_Pay,$B116,d_Status,"Delivered",d_Year,$P$4,d_City,$Q$4,d_Cuisine,$R$4,d_Pay,$S$4,d_Type,$T$4) -> 82308 | G116: =IFERROR(F116/SUMIFS(d_Net,d_Status,"Delivered",d_Year,$P$4,d_City,$Q$4,d_Cuisine,$R$4,d_Pay,$S$4,d_Type,$T$4),0) -> 0.11759126 | H116: =IFERROR(F116/C116,0) -> 914.53333
B117: Wallet | C117: =COUNTIFS(d_Pay,$B117,d_Status,"Delivered",d_Year,$P$4,d_City,$Q$4,d_Cuisine,$R$4,d_Pay,$S$4,d_Type,$T$4) -> 63 | D117: =SUMIFS(d_Gross,d_Pay,$B117,d_Status,"Delivered",d_Year,$P$4,d_City,$Q$4,d_Cuisine,$R$4,d_Pay,$S$4,d_Type,$T$4) -> 65606 | E117: =SUMIFS(d_Disc,d_Pay,$B117,d_Status,"Delivered",d_Year,$P$4,d_City,$Q$4,d_Cuisine,$R$4,d_Pay,$S$4,d_Type,$T$4) -> 4985 | F117: =SUMIFS(d_Net,d_Pay,$B117,d_Status,"Delivered",d_Year,$P$4,d_City,$Q$4,d_Cuisine,$R$4,d_Pay,$S$4,d_Type,$T$4) -> 60665 | G117: =IFERROR(F117/SUMIFS(d_Net,d_Status,"Delivered",d_Year,$P$4,d_City,$Q$4,d_Cuisine,$R$4,d_Pay,$S$4,d_Type,$T$4),0) -> 0.086670476 | H117: =IFERROR(F117/C117,0) -> 962.93651
B118: Total / Overall | C118: =SUM(C113:C117) -> 791 | D118: =SUM(D113:D117) -> 755840 | E118: =SUM(E113:E117) -> 56065 | F118: =SUM(F113:F117) -> 699950 | G118: =SUM(G113:G117) -> 1 | H118: =IFERROR(F118/C118,0) -> 884.89254
B121: Revenue by restaurant
B122: Restaurant | C122: Delivered orders | D122: Gross revenue | E122: Discounts | F122: Net revenue | G122: Share of net | H122: Avg net / order
B123: Urban Tadka | C123: =COUNTIFS(d_Rest,$B123,d_Status,"Delivered",d_Year,$P$4,d_City,$Q$4,d_Cuisine,$R$4,d_Pay,$S$4,d_Type,$T$4) -> 78 | D123: =SUMIFS(d_Gross,d_Rest,$B123,d_Status,"Delivered",d_Year,$P$4,d_City,$Q$4,d_Cuisine,$R$4,d_Pay,$S$4,d_Type,$T$4) -> 72233 | E123: =SUMIFS(d_Disc,d_Rest,$B123,d_Status,"Delivered",d_Year,$P$4,d_City,$Q$4,d_Cuisine,$R$4,d_Pay,$S$4,d_Type,$T$4) -> 5455 | F123: =SUMIFS(d_Net,d_Rest,$B123,d_Status,"Delivered",d_Year,$P$4,d_City,$Q$4,d_Cuisine,$R$4,d_Pay,$S$4,d_Type,$T$4) -> 66822 | G123: =IFERROR(F123/SUMIFS(d_Net,d_Status,"Delivered",d_Year,$P$4,d_City,$Q$4,d_Cuisine,$R$4,d_Pay,$S$4,d_Type,$T$4),0) -> 0.095466819 | H123: =IFERROR(F123/C123,0) -> 856.69231
B124: Taste Junction | C124: =COUNTIFS(d_Rest,$B124,d_Status,"Delivered",d_Year,$P$4,d_City,$Q$4,d_Cuisine,$R$4,d_Pay,$S$4,d_Type,$T$4) -> 73 | D124: =SUMIFS(d_Gross,d_Rest,$B124,d_Status,"Delivered",d_Year,$P$4,d_City,$Q$4,d_Cuisine,$R$4,d_Pay,$S$4,d_Type,$T$4) -> 65451 | E124: =SUMIFS(d_Disc,d_Rest,$B124,d_Status,"Delivered",d_Year,$P$4,d_City,$Q$4,d_Cuisine,$R$4,d_Pay,$S$4,d_Type,$T$4) -> 5365 | F124: =SUMIFS(d_Net,d_Rest,$B124,d_Status,"Delivered",d_Year,$P$4,d_City,$Q$4,d_Cuisine,$R$4,d_Pay,$S$4,d_Type,$T$4) -> 60113 | G124: =IFERROR(F124/SUMIFS(d_Net,d_Status,"Delivered",d_Year,$P$4,d_City,$Q$4,d_Cuisine,$R$4,d_Pay,$S$4,d_Type,$T$4),0) -> 0.085881849 | H124: =IFERROR(F124/C124,0) -> 823.46575
B125: Cafe Aroma | C125: =COUNTIFS(d_Rest,$B125,d_Status,"Delivered",d_Year,$P$4,d_City,$Q$4,d_Cuisine,$R$4,d_Pay,$S$4,d_Type,$T$4) -> 70 | D125: =SUMIFS(d_Gross,d_Rest,$B125,d_Status,"Delivered",d_Year,$P$4,d_City,$Q$4,d_Cuisine,$R$4,d_Pay,$S$4,d_Type,$T$4) -> 60104 | E125: =SUMIFS(d_Disc,d_Rest,$B125,d_Status,"Delivered",d_Year,$P$4,d_City,$Q$4,d_Cuisine,$R$4,d_Pay,$S$4,d_Type,$T$4) -> 4565 | F125: =SUMIFS(d_Net,d_Rest,$B125,d_Status,"Delivered",d_Year,$P$4,d_City,$Q$4,d_Cuisine,$R$4,d_Pay,$S$4,d_Type,$T$4) -> 55539 | G125: =IFERROR(F125/SUMIFS(d_Net,d_Status,"Delivered",d_Year,$P$4,d_City,$Q$4,d_Cuisine,$R$4,d_Pay,$S$4,d_Type,$T$4),0) -> 0.079347096 | H125: =IFERROR(F125/C125,0) -> 793.41429
B126: Delhi Zaika | C126: =COUNTIFS(d_Rest,$B126,d_Status,"Delivered",d_Year,$P$4,d_City,$Q$4,d_Cuisine,$R$4,d_Pay,$S$4,d_Type,$T$4) -> 70 | D126: =SUMIFS(d_Gross,d_Rest,$B126,d_Status,"Delivered",d_Year,$P$4,d_City,$Q$4,d_Cuisine,$R$4,d_Pay,$S$4,d_Type,$T$4) -> 63848 | E126: =SUMIFS(d_Disc,d_Rest,$B126,d_Status,"Delivered",d_Year,$P$4,d_City,$Q$4,d_Cuisine,$R$4,d_Pay,$S$4,d_Type,$T$4) -> 4670 | F126: =SUMIFS(d_Net,d_Rest,$B126,d_Status,"Delivered",d_Year,$P$4,d_City,$Q$4,d_Cuisine,$R$4,d_Pay,$S$4,d_Type,$T$4) -> 59187 | G126: =IFERROR(F126/SUMIFS(d_Net,d_Status,"Delivered",d_Year,$P$4,d_City,$Q$4,d_Cuisine,$R$4,d_Pay,$S$4,d_Type,$T$4),0) -> 0.084558897 | H126: =IFERROR(F126/C126,0) -> 845.52857
B127: Burger House | C127: =COUNTIFS(d_Rest,$B127,d_Status,"Delivered",d_Year,$P$4,d_City,$Q$4,d_Cuisine,$R$4,d_Pay,$S$4,d_Type,$T$4) -> 69 | D127: =SUMIFS(d_Gross,d_Rest,$B127,d_Status,"Delivered",d_Year,$P$4,d_City,$Q$4,d_Cuisine,$R$4,d_Pay,$S$4,d_Type,$T$4) -> 72637 | E127: =SUMIFS(d_Disc,d_Rest,$B127,d_Status,"Delivered",d_Year,$P$4,d_City,$Q$4,d_Cuisine,$R$4,d_Pay,$S$4,d_Type,$T$4) -> 4985 | F127: =SUMIFS(d_Net,d_Rest,$B127,d_Status,"Delivered",d_Year,$P$4,d_City,$Q$4,d_Cuisine,$R$4,d_Pay,$S$4,d_Type,$T$4) -> 67652 | G127: =IFERROR(F127/SUMIFS(d_Net,d_Status,"Delivered",d_Year,$P$4,d_City,$Q$4,d_Cuisine,$R$4,d_Pay,$S$4,d_Type,$T$4),0) -> 0.096652618 | H127: =IFERROR(F127/C127,0) -> 980.46377
B128: Spice Hub | C128: =COUNTIFS(d_Rest,$B128,d_Status,"Delivered",d_Year,$P$4,d_City,$Q$4,d_Cuisine,$R$4,d_Pay,$S$4,d_Type,$T$4) -> 67 | D128: =SUMIFS(d_Gross,d_Rest,$B128,d_Status,"Delivered",d_Year,$P$4,d_City,$Q$4,d_Cuisine,$R$4,d_Pay,$S$4,d_Type,$T$4) -> 68094 | E128: =SUMIFS(d_Disc,d_Rest,$B128,d_Status,"Delivered",d_Year,$P$4,d_City,$Q$4,d_Cuisine,$R$4,d_Pay,$S$4,d_Type,$T$4) -> 4630 | F128: =SUMIFS(d_Net,d_Rest,$B128,d_Status,"Delivered",d_Year,$P$4,d_City,$Q$4,d_Cuisine,$R$4,d_Pay,$S$4,d_Type,$T$4) -> 63464 | G128: =IFERROR(F128/SUMIFS(d_Net,d_Status,"Delivered",d_Year,$P$4,d_City,$Q$4,d_Cuisine,$R$4,d_Pay,$S$4,d_Type,$T$4),0) -> 0.090669334 | H128: =IFERROR(F128/C128,0) -> 947.22388
B129: Pizza Point | C129: =COUNTIFS(d_Rest,$B129,d_Status,"Delivered",d_Year,$P$4,d_City,$Q$4,d_Cuisine,$R$4,d_Pay,$S$4,d_Type,$T$4) -> 74 | D129: =SUMIFS(d_Gross,d_Rest,$B129,d_Status,"Delivered",d_Year,$P$4,d_City,$Q$4,d_Cuisine,$R$4,d_Pay,$S$4,d_Type,$T$4) -> 66874 | E129: =SUMIFS(d_Disc,d_Rest,$B129,d_Status,"Delivered",d_Year,$P$4,d_City,$Q$4,d_Cuisine,$R$4,d_Pay,$S$4,d_Type,$T$4) -> 5905 | F129: =SUMIFS(d_Net,d_Rest,$B129,d_Status,"Delivered",d_Year,$P$4,d_City,$Q$4,d_Cuisine,$R$4,d_Pay,$S$4,d_Type,$T$4) -> 60969 | G129: =IFERROR(F129/SUMIFS(d_Net,d_Status,"Delivered",d_Year,$P$4,d_City,$Q$4,d_Cuisine,$R$4,d_Pay,$S$4,d_Type,$T$4),0) -> 0.087104793 | H129: =IFERROR(F129/C129,0) -> 823.90541
B130: Green Bowl | C130: =COUNTIFS(d_Rest,$B130,d_Status,"Delivered",d_Year,$P$4,d_City,$Q$4,d_Cuisine,$R$4,d_Pay,$S$4,d_Type,$T$4) -> 60 | D130: =SUMIFS(d_Gross,d_Rest,$B130,d_Status,"Delivered",d_Year,$P$4,d_City,$Q$4,d_Cuisine,$R$4,d_Pay,$S$4,d_Type,$T$4) -> 58258 | E130: =SUMIFS(d_Disc,d_Rest,$B130,d_Status,"Delivered",d_Year,$P$4,d_City,$Q$4,d_Cuisine,$R$4,d_Pay,$S$4,d_Type,$T$4) -> 3735 | F130: =SUMIFS(d_Net,d_Rest,$B130,d_Status,"Delivered",d_Year,$P$4,d_City,$Q$4,d_Cuisine,$R$4,d_Pay,$S$4,d_Type,$T$4) -> 54523 | G130: =IFERROR(F130/SUMIFS(d_Net,d_Status,"Delivered",d_Year,$P$4,d_City,$Q$4,d_Cuisine,$R$4,d_Pay,$S$4,d_Type,$T$4),0) -> 0.077895564 | H130: =IFERROR(F130/C130,0) -> 908.71667
B131: The Food Corner | C131: =COUNTIFS(d_Rest,$B131,d_Status,"Delivered",d_Year,$P$4,d_City,$Q$4,d_Cuisine,$R$4,d_Pay,$S$4,d_Type,$T$4) -> 62 | D131: =SUMIFS(d_Gross,d_Rest,$B131,d_Status,"Delivered",d_Year,$P$4,d_City,$Q$4,d_Cuisine,$R$4,d_Pay,$S$4,d_Type,$T$4) -> 61092 | E131: =SUMIFS(d_Disc,d_Rest,$B131,d_Status,"Delivered",d_Year,$P$4,d_City,$Q$4,d_Cuisine,$R$4,d_Pay,$S$4,d_Type,$T$4) -> 4160 | F131: =SUMIFS(d_Net,d_Rest,$B131,d_Status,"Delivered",d_Year,$P$4,d_City,$Q$4,d_Cuisine,$R$4,d_Pay,$S$4,d_Type,$T$4) -> 56948 | G131: =IFERROR(F131/SUMIFS(d_Net,d_Status,"Delivered",d_Year,$P$4,d_City,$Q$4,d_Cuisine,$R$4,d_Pay,$S$4,d_Type,$T$4),0) -> 0.081360097 | H131: =IFERROR(F131/C131,0) -> 918.51613
